Workbook

Sheet Inputs
A1: Ember Scaling Model v6.8
A4: CASH
A5: Starting cash ($) | B5: 1600000
A6: Fixed costs monthly ($) | B6: 250000
A8: CREDIT CARD
A9: CC limit ($) | B9: 500000
A11: PVX CAPITAL
A12: PVX interest rate | B12: 0.05
A14: FORECAST
A15: Projected ROAS@36 | B15: 2.5
A16: Projected WD ratio | B16: 0.31
A18: GAMING ECONOMICS
A19: Wager volume per $1 net receipts | B19: 28.5
A20: Blended house edge | B20: 0.03
A21: % wager from 3rd party games | B21: 0.3
A22: 3rd party house edge cost | B22: 0.08
A24: AGENCY FEES
A25: Agency fee rate | B25: 0.08
A26: % of ad spend via agency | B26: 0.7
A28: PVX Terms:
A29: - PVX gets 100% of net rev until payback (Cum Paid >= Draw)
A30: - After payback, PVX gets 50% + interest until cap
A31: - Cap = Draw × (1 + Interest Rate)
A32: - After cap hit, Company keeps 100%
A34: 3rd Party Cost Formula:
A35: Total Receipts × Wager/Receipts × House Edge × 3rd Party % × Edge Cost

Sheet Curves
A1: Revenue Curves
A2: 0.5% flat tail per month from month 13-36
A4: Age | B4: Cum R% | C4: Inc R% | D4: Cum W% | E4: Inc W%
A5: 0 | B5: 0.315935 | C5: 0.315935 | D5: 0.13798726 | E5: 0.13798726
A6: 1 | B6: 0.46658363 | C6: 0.15064863 | D6: 0.28981942 | E6: 0.15183216
A7: 2 | B7: 0.56315096 | C7: 0.096567329 | D7: 0.3750433 | E7: 0.085223875
A8: 3 | B8: 0.63109187 | C8: 0.067940906 | D8: 0.46700843 | E8: 0.091965128
A9: 4 | B9: 0.67148476 | C9: 0.040392894 | D9: 0.55942041 | E9: 0.092411982
A10: 5 | B10: 0.70769399 | C10: 0.036209227 | D10: 0.62748327 | E10: 0.068062864
A11: 6 | B11: 0.73896589 | C11: 0.0312719 | D11: 0.71708222 | E11: 0.089598951
A12: 7 | B12: 0.76659636 | C12: 0.02763047 | D12: 0.75640645 | E12: 0.039324228
A13: 8 | B13: 0.79129689 | C13: 0.024700532 | D13: 0.78182533 | E13: 0.025418881
A14: 9 | B14: 0.82 | C14: 0.028703111 | D14: 0.82 | E14: 0.038174668
A15: 10 | B15: 0.84 | C15: 0.02 | D15: 0.84 | E15: 0.02
A16: 11 | B16: 0.86 | C16: 0.02 | D16: 0.86 | E16: 0.02
... A41: 36 | B41: 1 | C41: 0.005 | D41: 1 | E41: 0.005

Sheet Baseline_Decay
A1: Baseline Decay (Fixed Schedule)
A3: Month | B3: Receipts | C3: WD | D3: Net
A4: 0 | B4: 700000 | C4: 350000 | D4: =B4-C4 -> 350000
A5: 1 | B5: 500000 | C5: 250000 | D5: =B5-C5 -> 250000
A6: 2 | B6: 400000 | C6: 200000 | D6: =B6-C6 -> 200000
A7: 3 | B7: 300000 | C7: 150000 | D7: =B7-C7 -> 150000
A8: 4 | B8: 200000 | C8: 100000 | D8: =B8-C8 -> 100000
A9: 5 | B9: 200000 | C9: 100000 | D9: =B9-C9 -> 100000
A10: 6 | B10: 200000 | C10: 100000 | D10: =B10-C10 -> 100000
A11: 7 | B11: 200000 | C11: 100000 | D11: =B11-C11 -> 100000
A12: 8 | B12: 200000 | C12: 100000 | D12: =B12-C12 -> 100000
A13: 9 | B13: 200000 | C13: 100000 | D13: =B13-C13 -> 100000
A14: 10 | B14: 200000 | C14: 100000 | D14: =B14-C14 -> 100000
A15: 11 | B15: 200000 | C15: 100000 | D15: =B15-C15 -> 100000
... A39: 35 | B39: 200000 | C39: 100000 | D39: =B39-C39 -> 100000

Sheet Cohort_Summary
A1: Monthly Cohort Summary
A3: Cohort | B3: Spend | C3: Users | D3: CAC | E3: Age (wks) | F3: Current ROAS | G3: Proj ROAS | H3: Curr Payback | I3: Proj Payback | J3: WD Ratio
A4: 2025-04-01 | B4: 83561.574 | C4: 47087 | D4: 1.7746209 | E4: 42 | F4: 2.5414799 | G4: 3.0993657 | H4: 1.4 | I4: 0.8 | J4: 0.26361038
A5: 2025-05-01 | B5: 77127.49 | C5: 41122 | D5: 1.8755773 | E5: 38 | F5: 3.149368 | G5: 3.9800081 | H5: 1.4 | I5: 0.6 | J5: 0.38310655
A6: 2025-06-01 | B6: 75728.607 | C6: 27893 | D6: 2.7149682 | E6: 34 | F6: 2.7144184 | G6: 3.5408704 | H6: 1.4 | I6: 0.8 | J6: 0.36257797
A7: 2025-07-01 | B7: 130031.25 | C7: 31351 | D7: 4.147595 | E7: 29 | F7: 1.8294541 | G7: 2.4756949 | H7: 5.5 | I7: 4.2 | J7: 0.40330617
A8: 2025-08-01 | B8: 151857.02 | C8: 29508 | D8: 5.1462999 | E8: 25 | F8: 1.8573266 | G8: 2.6244771 | H8: 3.5 | I8: 1.9 | J8: 0.31191477
A9: 2025-09-01 | B9: 179833.77 | C9: 25901 | D9: 6.9431208 | E9: 21 | F9: 1.1475205 | G9: 1.7089301 | I9: 11.9 | J9: 0.33293292
A10: 2025-10-01 | B10: 160252.72 | C10: 24024 | D10: 6.6705261 | E10: 16 | F10: 1.2249096 | G10: 1.9409371 | I10: 4 | J10: 0.23262339
A11: 2025-11-01 | B11: 132959.21 | C11: 23008 | D11: 5.7788251 | E11: 12 | F11: 1.7377281 | G11: 3.0857235 | H11: 2.3 | I11: 1.1 | J11: 0.32002614
A12: 2025-12-01 | B12: 205458.01 | C12: 32217 | D12: 6.3773166 | E12: 8 | F12: 1.1163 | G12: 2.3924972 | I12: 2.4 | J12: 0.29114511
A13: 2026-01-01 | B13: 184702.43 | C13: 30321 | D13: 6.0915679 | E13: 3 | F13: 0.74618209 | G13: 2.3618216 | I13: 1.9 | J13: 0.23856045

Sheet Acquisition_Plan
A1: Acquisition Plan
A3: Month | B3: Total Spend | C3: Use CC | D3: CC Spend | E3: PVX Spend | F3: Cash Spend
A4: 2026-02-01 | B4: 200000 | C4: 1 | D4: 200000 | E4: 0 | F4: =B4-D4-E4 -> 0
A5: 2026-03-03 | B5: 250000 | C5: 1 | D5: =B5 -> 250000 | E5: 0 | F5: =B5-D5-E5 -> 0
A6: 2026-04-02 | B6: 300000 | C6: 1 | D6: 150000 | E6: 150000 | F6: =B6-D6-E6 -> 0
A7: 2026-05-02 | B7: 300000 | C7: 1 | D7: =B7/2 -> 150000 | E7: =B7/2 -> 150000 | F7: =B7-D7-E7 -> 0
A8: 2026-06-01 | B8: 400000 | C8: 1 | D8: =B8/2 -> 200000 | E8: =B8/2 -> 200000 | F8: =B8-D8-E8 -> 0
A9: 2026-07-01 | B9: 400000 | C9: 1 | D9: =B9/2 -> 200000 | E9: =B9/2 -> 200000 | F9: =B9-D9-E9 -> 0
A10: 2026-07-31 | B10: 500000 | C10: 1 | D10: =B10/2 -> 250000 | E10: =B10/2 -> 250000 | F10: =B10-D10-E10 -> 0
A11: 2026-08-30 | B11: 500000 | C11: 1 | D11: =B11/2 -> 250000 | E11: =B11/2 -> 250000 | F11: =B11-D11-E11 -> 0
A12: 2026-09-29 | B12: 600000 | C12: 1 | D12: =B12/2 -> 300000 | E12: =B12/2 -> 300000 | F12: =B12-D12-E12 -> 0
A13: 2026-10-29 | B13: 600000 | C13: 1 | D13: =B13/2 -> 300000 | E13: =B13/2 -> 300000 | F13: =B13-D13-E13 -> 0
A14: 2026-11-28 | B14: 700000 | C14: 1 | D14: =B14/2 -> 350000 | E14: =B14/2 -> 350000 | F14: =B14-D14-E14 -> 0
A15: 2026-12-28 | B15: 700000 | C15: 1 | D15: =B15/2 -> 350000 | E15: =B15/2 -> 350000 | F15: =B15-D15-E15 -> 0
A16: 2027-01-27 | B16: 800000 | C16: 1 | D16: =B16/2 -> 400000 | E16: =B16/2 -> 400000 | F16: =B16-D16-E16 -> 0
A17: 2027-02-26 | B17: 800000 | C17: 1 | D17: =B17/2 -> 400000 | E17: =B17/2 -> 400000 | F17: =B17-D17-E17 -> 0
A18: 2027-03-28 | B18: 800000 | C18: 1 | D18: =B18/2 -> 400000 | E18: =B18/2 -> 400000 | F18: =B18-D18-E18 -> 0
... A39: 2028-12-17 | B39: 800000 | C39: 1 | D39: =B39/2 -> 400000 | E39: =B39/2 -> 400000 | F39: =B39-D39-E39 -> 0

Sheet New_Cohort_Rev
A1: New Cohort Revenue (All Sources)
A2: Spend = CC + Cash + PVX
A4: Cohort | B4: Spend | C4: M0 | D4: M1 | E4: M2 | F4: M3 | G4: M4 | H4: M5 | I4: M6 | J4: M7 | K4: M8 | L4: M9 | M4: M10 | N4: M11 | O4: M12 | P4: M13 | Q4: M14 | R4: M15 | S4: M16 | T4: M17 | U4: M18 | V4: M19 | W4: M20 | X4: M21 | Y4: M22 | Z4: M23 | AA4: M24 | AB4: M25 | AC4: M26 | AD4: M27 | AE4: M28 | AF4: M29 | AG4: M30 | AH4: M31 | AI4: M32 | AJ4: M33 | AK4: M34 | AL4: M35
A5: =Acquisition_Plan!A4 -> 2026-02-01 | B5: =Acquisition_Plan!D4+Acquisition_Plan!F4+Acquisition_Plan!E4 -> 200000 | C5: =$B5*Inputs!$B$15*Curves!$C$5 -> 157967.5 | D5: =$B5*Inputs!$B$15*Curves!$C$6 -> 75324.315 | E5: =$B5*Inputs!$B$15*Curves!$C$7 -> 48283.664 | F5: =$B5*Inputs!$B$15*Curves!$C$8 -> 33970.453 | G5: =$B5*Inputs!$B$15*Curves!$C$9 -> 20196.447 | H5: =$B5*Inputs!$B$15*Curves!$C$10 -> 18104.613 | I5: =$B5*Inputs!$B$15*Curves!$C$11 -> 15635.95 | J5: =$B5*Inputs!$B$15*Curves!$C$12 -> 13815.235 | K5: =$B5*Inputs!$B$15*Curves!$C$13 -> 12350.266 | L5: =$B5*Inputs!$B$15*Curves!$C$14 -> 14351.555 | M5: =$B5*Inputs!$B$15*Curves!$C$15 -> 10000 | N5: =$B5*Inputs!$B$15*Curves!$C$16 -> 10000 | O5: =$B5*Inputs!$B$15*Curves!$C$17 -> 10000 | P5: =$B5*Inputs!$B$15*Curves!$C$18 -> 2500 | Q5: =$B5*Inputs!$B$15*Curves!$C$19 -> 2500 | R5: =$B5*Inputs!$B$15*Curves!$C$20 -> 2500 | S5: =$B5*Inputs!$B$15*Curves!$C$21 -> 2500 | T5: =$B5*Inputs!$B$15*Curves!$C$22 -> 2500 | U5: =$B5*Inputs!$B$15*Curves!$C$23 -> 2500 | V5: =$B5*Inputs!$B$15*Curves!$C$24 -> 2500 | W5: =$B5*Inputs!$B$15*Curves!$C$25 -> 2500 | X5: =$B5*Inputs!$B$15*Curves!$C$26 -> 2500 | Y5: =$B5*Inputs!$B$15*Curves!$C$27 -> 2500 | Z5: =$B5*Inputs!$B$15*Curves!$C$28 -> 2500 | AA5: =$B5*Inputs!$B$15*Curves!$C$29 -> 2500 | AB5: =$B5*Inputs!$B$15*Curves!$C$30 -> 2500 | AC5: =$B5*Inputs!$B$15*Curves!$C$31 -> 2500 | AD5: =$B5*Inputs!$B$15*Curves!$C$32 -> 2500 | AE5: =$B5*Inputs!$B$15*Curves!$C$33 -> 2500 | AF5: =$B5*Inputs!$B$15*Curves!$C$34 -> 2500 | AG5: =$B5*Inputs!$B$15*Curves!$C$35 -> 2500 | AH5: =$B5*Inputs!$B$15*Curves!$C$36 -> 2500 | AI5: =$B5*Inputs!$B$15*Curves!$C$37 -> 2500 | AJ5: =$B5*Inputs!$B$15*Curves!$C$38 -> 2500 | AK5: =$B5*Inputs!$B$15*Curves!$C$39 -> 2500 | AL5: =$B5*Inputs!$B$15*Curves!$C$40 -> 2500
A6: =Acquisition_Plan!A5 -> 2026-03-03 | B6: =Acquisition_Plan!D5+Acquisition_Plan!F5+Acquisition_Plan!E5 -> 250000 | C6: 0 | D6: =$B6*Inputs!$B$15*Curves!$C$5 -> 197459.38 | E6: =$B6*Inputs!$B$15*Curves!$C$6 -> 94155.394 | F6: =$B6*Inputs!$B$15*Curves!$C$7 -> 60354.581 | G6: =$B6*Inputs!$B$15*Curves!$C$8 -> 42463.066 | H6: =$B6*Inputs!$B$15*Curves!$C$9 -> 25245.559 | I6: =$B6*Inputs!$B$15*Curves!$C$10 -> 22630.767 | J6: =$B6*Inputs!$B$15*Curves!$C$11 -> 19544.937 | K6: =$B6*Inputs!$B$15*Curves!$C$12 -> 17269.044 | L6: =$B6*Inputs!$B$15*Curves!$C$13 -> 15437.832 | M6: =$B6*Inputs!$B$15*Curves!$C$14 -> 17939.444 | N6: =$B6*Inputs!$B$15*Curves!$C$15 -> 12500 | O6: =$B6*Inputs!$B$15*Curves!$C$16 -> 12500 | P6: =$B6*Inputs!$B$15*Curves!$C$17 -> 12500 | Q6: =$B6*Inputs!$B$15*Curves!$C$18 -> 3125 | R6: =$B6*Inputs!$B$15*Curves!$C$19 -> 3125 | S6: =$B6*Inputs!$B$15*Curves!$C$20 -> 3125 | T6: =$B6*Inputs!$B$15*Curves!$C$21 -> 3125 | U6: =$B6*Inputs!$B$15*Curves!$C$22 -> 3125 | V6: =$B6*Inputs!$B$15*Curves!$C$23 -> 3125 | W6: =$B6*Inputs!$B$15*Curves!$C$24 -> 3125 | X6: =$B6*Inputs!$B$15*Curves!$C$25 -> 3125 | Y6: =$B6*Inputs!$B$15*Curves!$C$26 -> 3125 | Z6: =$B6*Inputs!$B$15*Curves!$C$27 -> 3125 | AA6: =$B6*Inputs!$B$15*Curves!$C$28 -> 3125 | AB6: =$B6*Inputs!$B$15*Curves!$C$29 -> 3125 | AC6: =$B6*Inputs!$B$15*Curves!$C$30 -> 3125 | AD6: =$B6*Inputs!$B$15*Curves!$C$31 -> 3125 | AE6: =$B6*Inputs!$B$15*Curves!$C$32 -> 3125 | AF6: =$B6*Inputs!$B$15*Curves!$C$33 -> 3125 | AG6: =$B6*Inputs!$B$15*Curves!$C$34 -> 3125 | AH6: =$B6*Inputs!$B$15*Curves!$C$35 -> 3125 | AI6: =$B6*Inputs!$B$15*Curves!$C$36 -> 3125 | AJ6: =$B6*Inputs!$B$15*Curves!$C$37 -> 3125 | AK6: =$B6*Inputs!$B$15*Curves!$C$38 -> 3125 | AL6: =$B6*Inputs!$B$15*Curves!$C$39 -> 3125
A7: =Acquisition_Plan!A6 -> 2026-04-02 | B7: =Acquisition_Plan!D6+Acquisition_Plan!F6+Acquisition_Plan!E6 -> 300000 | C7: 0 | D7: 0 | E7: =$B7*Inputs!$B$15*Curves!$C$5 -> 236951.25 | F7: =$B7*Inputs!$B$15*Curves!$C$6 -> 112986.47 | G7: =$B7*Inputs!$B$15*Curves!$C$7 -> 72425.497 | H7: =$B7*Inputs!$B$15*Curves!$C$8 -> 50955.68 | I7: =$B7*Inputs!$B$15*Curves!$C$9 -> 30294.671 | J7: =$B7*Inputs!$B$15*Curves!$C$10 -> 27156.92 | K7: =$B7*Inputs!$B$15*Curves!$C$11 -> 23453.925 | L7: =$B7*Inputs!$B$15*Curves!$C$12 -> 20722.852 | M7: =$B7*Inputs!$B$15*Curves!$C$13 -> 18525.399 | N7: =$B7*Inputs!$B$15*Curves!$C$14 -> 21527.333 | O7: =$B7*Inputs!$B$15*Curves!$C$15 -> 15000 | P7: =$B7*Inputs!$B$15*Curves!$C$16 -> 15000 | Q7: =$B7*Inputs!$B$15*Curves!$C$17 -> 15000 | R7: =$B7*Inputs!$B$15*Curves!$C$18 -> 3750 | S7: =$B7*Inputs!$B$15*Curves!$C$19 -> 3750 | T7: =$B7*Inputs!$B$15*Curves!$C$20 -> 3750 | U7: =$B7*Inputs!$B$15*Curves!$C$21 -> 3750 | V7: =$B7*Inputs!$B$15*Curves!$C$22 -> 3750 | W7: =$B7*Inputs!$B$15*Curves!$C$23 -> 3750 | X7: =$B7*Inputs!$B$15*Curves!$C$24 -> 3750 | Y7: =$B7*Inputs!$B$15*Curves!$C$25 -> 3750 | Z7: =$B7*Inputs!$B$15*Curves!$C$26 -> 3750 | AA7: =$B7*Inputs!$B$15*Curves!$C$27 -> 3750 | AB7: =$B7*Inputs!$B$15*Curves!$C$28 -> 3750 | AC7: =$B7*Inputs!$B$15*Curves!$C$29 -> 3750 | AD7: =$B7*Inputs!$B$15*Curves!$C$30 -> 3750 | AE7: =$B7*Inputs!$B$15*Curves!$C$31 -> 3750 | AF7: =$B7*Inputs!$B$15*Curves!$C$32 -> 3750 | AG7: =$B7*Inputs!$B$15*Curves!$C$33 -> 3750 | AH7: =$B7*Inputs!$B$15*Curves!$C$34 -> 3750 | AI7: =$B7*Inputs!$B$15*Curves!$C$35 -> 3750 | AJ7: =$B7*Inputs!$B$15*Curves!$C$36 -> 3750 | AK7: =$B7*Inputs!$B$15*Curves!$C$37 -> 3750 | AL7: =$B7*Inputs!$B$15*Curves!$C$38 -> 3750
A8: =Acquisition_Plan!A7 -> 2026-05-02 | B8: =Acquisition_Plan!D7+Acquisition_Plan!F7+Acquisition_Plan!E7 -> 300000 | C8: 0 | D8: 0 | E8: 0 | F8: =$B8*Inputs!$B$15*Curves!$C$5 -> 236951.25 | G8: =$B8*Inputs!$B$15*Curves!$C$6 -> 112986.47 | H8: =$B8*Inputs!$B$15*Curves!$C$7 -> 72425.497 | I8: =$B8*Inputs!$B$15*Curves!$C$8 -> 50955.68 | J8: =$B8*Inputs!$B$15*Curves!$C$9 -> 30294.671 | K8: =$B8*Inputs!$B$15*Curves!$C$10 -> 27156.92 | L8: =$B8*Inputs!$B$15*Curves!$C$11 -> 23453.925 | M8: =$B8*Inputs!$B$15*Curves!$C$12 -> 20722.852 | N8: =$B8*Inputs!$B$15*Curves!$C$13 -> 18525.399 | O8: =$B8*Inputs!$B$15*Curves!$C$14 -> 21527.333 | P8: =$B8*Inputs!$B$15*Curves!$C$15 -> 15000 | Q8: =$B8*Inputs!$B$15*Curves!$C$16 -> 15000 | R8: =$B8*Inputs!$B$15*Curves!$C$17 -> 15000 | S8: =$B8*Inputs!$B$15*Curves!$C$18 -> 3750 | T8: =$B8*Inputs!$B$15*Curves!$C$19 -> 3750 | U8: =$B8*Inputs!$B$15*Curves!$C$20 -> 3750 | V8: =$B8*Inputs!$B$15*Curves!$C$21 -> 3750 | W8: =$B8*Inputs!$B$15*Curves!$C$22 -> 3750 | X8: =$B8*Inputs!$B$15*Curves!$C$23 -> 3750 | Y8: =$B8*Inputs!$B$15*Curves!$C$24 -> 3750 | Z8: =$B8*Inputs!$B$15*Curves!$C$25 -> 3750 | AA8: =$B8*Inputs!$B$15*Curves!$C$26 -> 3750 | AB8: =$B8*Inputs!$B$15*Curves!$C$27 -> 3750 | AC8: =$B8*Inputs!$B$15*Curves!$C$28 -> 3750 | AD8: =$B8*Inputs!$B$15*Curves!$C$29 -> 3750 | AE8: =$B8*Inputs!$B$15*Curves!$C$30 -> 3750 | AF8: =$B8*Inputs!$B$15*Curves!$C$31 -> 3750 | AG8: =$B8*Inputs!$B$15*Curves!$C$32 -> 3750 | AH8: =$B8*Inputs!$B$15*Curves!$C$33 -> 3750 | AI8: =$B8*Inputs!$B$15*Curves!$C$34 -> 3750 | AJ8: =$B8*Inputs!$B$15*Curves!$C$35 -> 3750 | AK8: =$B8*Inputs!$B$15*Curves!$C$36 -> 3750 | AL8: =$B8*Inputs!$B$15*Curves!$C$37 -> 3750
A9: =Acquisition_Plan!A8 -> 2026-06-01 | B9: =Acquisition_Plan!D8+Acquisition_Plan!F8+Acquisition_Plan!E8 -> 400000 | C9: 0 | D9: 0 | E9: 0 | F9: 0 | G9: =$B9*Inputs!$B$15*Curves!$C$5 -> 315935 | H9: =$B9*Inputs!$B$15*Curves!$C$6 -> 150648.63 | I9: =$B9*Inputs!$B$15*Curves!$C$7 -> 96567.329 | J9: =$B9*Inputs!$B$15*Curves!$C$8 -> 67940.906 | K9: =$B9*Inputs!$B$15*Curves!$C$9 -> 40392.894 | L9: =$B9*Inputs!$B$15*Curves!$C$10 -> 36209.227 | M9: =$B9*Inputs!$B$15*Curves!$C$11 -> 31271.9 | N9: =$B9*Inputs!$B$15*Curves!$C$12 -> 27630.47 | O9: =$B9*Inputs!$B$15*Curves!$C$13 -> 24700.532 | P9: =$B9*Inputs!$B$15*Curves!$C$14 -> 28703.111 | Q9: =$B9*Inputs!$B$15*Curves!$C$15 -> 20000 | R9: =$B9*Inputs!$B$15*Curves!$C$16 -> 20000 | S9: =$B9*Inputs!$B$15*Curves!$C$17 -> 20000 | T9: =$B9*Inputs!$B$15*Curves!$C$18 -> 5000 | U9: =$B9*Inputs!$B$15*Curves!$C$19 -> 5000 | V9: =$B9*Inputs!$B$15*Curves!$C$20 -> 5000 | W9: =$B9*Inputs!$B$15*Curves!$C$21 -> 5000 | X9: =$B9*Inputs!$B$15*Curves!$C$22 -> 5000 | Y9: =$B9*Inputs!$B$15*Curves!$C$23 -> 5000 | Z9: =$B9*Inputs!$B$15*Curves!$C$24 -> 5000 | AA9: =$B9*Inputs!$B$15*Curves!$C$25 -> 5000 | AB9: =$B9*Inputs!$B$15*Curves!$C$26 -> 5000 | AC9: =$B9*Inputs!$B$15*Curves!$C$27 -> 5000 | AD9: =$B9*Inputs!$B$15*Curves!$C$28 -> 5000 | AE9: =$B9*Inputs!$B$15*Curves!$C$29 -> 5000 | AF9: =$B9*Inputs!$B$15*Curves!$C$30 -> 5000 | AG9: =$B9*Inputs!$B$15*Curves!$C$31 -> 5000 | AH9: =$B9*Inputs!$B$15*Curves!$C$32 -> 5000 | AI9: =$B9*Inputs!$B$15*Curves!$C$33 -> 5000 | AJ9: =$B9*Inputs!$B$15*Curves!$C$34 -> 5000 | AK9: =$B9*Inputs!$B$15*Curves!$C$35 -> 5000 | AL9: =$B9*Inputs!$B$15*Curves!$C$36 -> 5000
A10: =Acquisition_Plan!A9 -> 2026-07-01 | B10: =Acquisition_Plan!D9+Acquisition_Plan!F9+Acquisition_Plan!E9 -> 400000 | C10: 0 | D10: 0 | E10: 0 | F10: 0 | G10: 0 | H10: =$B10*Inputs!$B$15*Curves!$C$5 -> 315935 | I10: =$B10*Inputs!$B$15*Curves!$C$6 -> 150648.63 | J10: =$B10*Inputs!$B$15*Curves!$C$7 -> 96567.329 | K10: =$B10*Inputs!$B$15*Curves!$C$8 -> 67940.906 | L10: =$B10*Inputs!$B$15*Curves!$C$9 -> 40392.894 | M10: =$B10*Inputs!$B$15*Curves!$C$10 -> 36209.227 | N10: =$B10*Inputs!$B$15*Curves!$C$11 -> 31271.9 | O10: =$B10*Inputs!$B$15*Curves!$C$12 -> 27630.47 | P10: =$B10*Inputs!$B$15*Curves!$C$13 -> 24700.532 | Q10: =$B10*Inputs!$B$15*Curves!$C$14 -> 28703.111 | R10: =$B10*Inputs!$B$15*Curves!$C$15 -> 20000 | S10: =$B10*Inputs!$B$15*Curves!$C$16 -> 20000 | T10: =$B10*Inputs!$B$15*Curves!$C$17 -> 20000 | U10: =$B10*Inputs!$B$15*Curves!$C$18 -> 5000 | V10: =$B10*Inputs!$B$15*Curves!$C$19 -> 5000 | W10: =$B10*Inputs!$B$15*Curves!$C$20 -> 5000 | X10: =$B10*Inputs!$B$15*Curves!$C$21 -> 5000 | Y10: =$B10*Inputs!$B$15*Curves!$C$22 -> 5000 | Z10: =$B10*Inputs!$B$15*Curves!$C$23 -> 5000 | AA10: =$B10*Inputs!$B$15*Curves!$C$24 -> 5000 | AB10: =$B10*Inputs!$B$15*Curves!$C$25 -> 5000 | AC10: =$B10*Inputs!$B$15*Curves!$C$26 -> 5000 | AD10: =$B10*Inputs!$B$15*Curves!$C$27 -> 5000 | AE10: =$B10*Inputs!$B$15*Curves!$C$28 -> 5000 | AF10: =$B10*Inputs!$B$15*Curves!$C$29 -> 5000 | AG10: =$B10*Inputs!$B$15*Curves!$C$30 -> 5000 | AH10: =$B10*Inputs!$B$15*Curves!$C$31 -> 5000 | AI10: =$B10*Inputs!$B$15*Curves!$C$32 -> 5000 | AJ10: =$B10*Inputs!$B$15*Curves!$C$33 -> 5000 | AK10: =$B10*Inputs!$B$15*Curves!$C$34 -> 5000 | AL10: =$B10*Inputs!$B$15*Curves!$C$35 -> 5000
A11: =Acquisition_Plan!A10 -> 2026-07-31 | B11: =Acquisition_Plan!D10+Acquisition_Plan!F10+Acquisition_Plan!E10 -> 500000 | C11: 0 | D11: 0 | E11: 0 | F11: 0 | G11: 0 | H11: 0 | I11: =$B11*Inputs!$B$15*Curves!$C$5 -> 394918.75 | J11: =$B11*Inputs!$B$15*Curves!$C$6 -> 188310.79 | K11: =$B11*Inputs!$B$15*Curves!$C$7 -> 120709.16 | L11: =$B11*Inputs!$B$15*Curves!$C$8 -> 84926.133 | M11: =$B11*Inputs!$B$15*Curves!$C$9 -> 50491.118 | N11: =$B11*Inputs!$B$15*Curves!$C$10 -> 45261.534 | O11: =$B11*Inputs!$B$15*Curves!$C$11 -> 39089.875 | P11: =$B11*Inputs!$B$15*Curves!$C$12 -> 34538.087 | Q11: =$B11*Inputs!$B$15*Curves!$C$13 -> 30875.665 | R11: =$B11*Inputs!$B$15*Curves!$C$14 -> 35878.889 | S11: =$B11*Inputs!$B$15*Curves!$C$15 -> 25000 | T11: =$B11*Inputs!$B$15*Curves!$C$16 -> 25000 | U11: =$B11*Inputs!$B$15*Curves!$C$17 -> 25000 | V11: =$B11*Inputs!$B$15*Curves!$C$18 -> 6250 | W11: =$B11*Inputs!$B$15*Curves!$C$19 -> 6250 | X11: =$B11*Inputs!$B$15*Curves!$C$20 -> 6250 | Y11: =$B11*Inputs!$B$15*Curves!$C$21 -> 6250 | Z11: =$B11*Inputs!$B$15*Curves!$C$22 -> 6250 | AA11: =$B11*Inputs!$B$15*Curves!$C$23 -> 6250 | AB11: =$B11*Inputs!$B$15*Curves!$C$24 -> 6250 | AC11: =$B11*Inputs!$B$15*Curves!$C$25 -> 6250 | AD11: =$B11*Inputs!$B$15*Curves!$C$26 -> 6250 | AE11: =$B11*Inputs!$B$15*Curves!$C$27 -> 6250 | AF11: =$B11*Inputs!$B$15*Curves!$C$28 -> 6250 | AG11: =$B11*Inputs!$B$15*Curves!$C$29 -> 6250 | AH11: =$B11*Inputs!$B$15*Curves!$C$30 -> 6250 | AI11: =$B11*Inputs!$B$15*Curves!$C$31 -> 6250 | AJ11: =$B11*Inputs!$B$15*Curves!$C$32 -> 6250 | AK11: =$B11*Inputs!$B$15*Curves!$C$33 -> 6250 | AL11: =$B11*Inputs!$B$15*Curves!$C$34 -> 6250
A12: =Acquisition_Plan!A11 -> 2026-08-30 | B12: =Acquisition_Plan!D11+Acquisition_Plan!F11+Acquisition_Plan!E11 -> 500000 | C12: 0 | D12: 0 | E12: 0 | F12: 0 | G12: 0 | H12: 0 | I12: 0 | J12: =$B12*Inputs!$B$15*Curves!$C$5 -> 394918.75 | K12: =$B12*Inputs!$B$15*Curves!$C$6 -> 188310.79 | L12: =$B12*Inputs!$B$15*Curves!$C$7 -> 120709.16 | M12: =$B12*Inputs!$B$15*Curves!$C$8 -> 84926.133 | N12: =$B12*Inputs!$B$15*Curves!$C$9 -> 50491.118 | O12: =$B12*Inputs!$B$15*Curves!$C$10 -> 45261.534 | P12: =$B12*Inputs!$B$15*Curves!$C$11 -> 39089.875 | Q12: =$B12*Inputs!$B$15*Curves!$C$12 -> 34538.087 | R12: =$B12*Inputs!$B$15*Curves!$C$13 -> 30875.665 | S12: =$B12*Inputs!$B$15*Curves!$C$14 -> 35878.889 | T12: =$B12*Inputs!$B$15*Curves!$C$15 -> 25000 | U12: =$B12*Inputs!$B$15*Curves!$C$16 -> 25000 | V12: =$B12*Inputs!$B$15*Curves!$C$17 -> 25000 | W12: =$B12*Inputs!$B$15*Curves!$C$18 -> 6250 | X12: =$B12*Inputs!$B$15*Curves!$C$19 -> 6250 | Y12: =$B12*Inputs!$B$15*Curves!$C$20 -> 6250 | Z12: =$B12*Inputs!$B$15*Curves!$C$21 -> 6250 | AA12: =$B12*Inputs!$B$15*Curves!$C$22 -> 6250 | AB12: =$B12*Inputs!$B$15*Curves!$C$23 -> 6250 | AC12: =$B12*Inputs!$B$15*Curves!$C$24 -> 6250 | AD12: =$B12*Inputs!$B$15*Curves!$C$25 -> 6250 | AE12: =$B12*Inputs!$B$15*Curves!$C$26 -> 6250 | AF12: =$B12*Inputs!$B$15*Curves!$C$27 -> 6250 | AG12: =$B12*Inputs!$B$15*Curves!$C$28 -> 6250 | AH12: =$B12*Inputs!$B$15*Curves!$C$29 -> 6250 | AI12: =$B12*Inputs!$B$15*Curves!$C$30 -> 6250 | AJ12: =$B12*Inputs!$B$15*Curves!$C$31 -> 6250 | AK12: =$B12*Inputs!$B$15*Curves!$C$32 -> 6250 | AL12: =$B12*Inputs!$B$15*Curves!$C$33 -> 6250
A13: =Acquisition_Plan!A12 -> 2026-09-29 | B13: =Acquisition_Plan!D12+Acquisition_Plan!F12+Acquisition_Plan!E12 -> 600000 | C13: 0 | D13: 0 | E13: 0 | F13: 0 | G13: 0 | H13: 0 | I13: 0 | J13: 0 | K13: =$B13*Inputs!$B$15*Curves!$C$5 -> 473902.5 | L13: =$B13*Inputs!$B$15*Curves!$C$6 -> 225972.95 | M13: =$B13*Inputs!$B$15*Curves!$C$7 -> 144850.99 | N13: =$B13*Inputs!$B$15*Curves!$C$8 -> 101911.36 | O13: =$B13*Inputs!$B$15*Curves!$C$9 -> 60589.342 | P13: =$B13*Inputs!$B$15*Curves!$C$10 -> 54313.84 | Q13: =$B13*Inputs!$B$15*Curves!$C$11 -> 46907.85 | R13: =$B13*Inputs!$B$15*Curves!$C$12 -> 41445.705 | S13: =$B13*Inputs!$B$15*Curves!$C$13 -> 37050.798 | T13: =$B13*Inputs!$B$15*Curves!$C$14 -> 43054.666 | U13: =$B13*Inputs!$B$15*Curves!$C$15 -> 30000 | V13: =$B13*Inputs!$B$15*Curves!$C$16 -> 30000 | W13: =$B13*Inputs!$B$15*Curves!$C$17 -> 30000 | X13: =$B13*Inputs!$B$15*Curves!$C$18 -> 7500 | Y13: =$B13*Inputs!$B$15*Curves!$C$19 -> 7500 | Z13: =$B13*Inputs!$B$15*Curves!$C$20 -> 7500 | AA13: =$B13*Inputs!$B$15*Curves!$C$21 -> 7500 | AB13: =$B13*Inputs!$B$15*Curves!$C$22 -> 7500 | AC13: =$B13*Inputs!$B$15*Curves!$C$23 -> 7500 | AD13: =$B13*Inputs!$B$15*Curves!$C$24 -> 7500 | AE13: =$B13*Inputs!$B$15*Curves!$C$25 -> 7500 | AF13: =$B13*Inputs!$B$15*Curves!$C$26 -> 7500 | AG13: =$B13*Inputs!$B$15*Curves!$C$27 -> 7500 | AH13: =$B13*Inputs!$B$15*Curves!$C$28 -> 7500 | AI13: =$B13*Inputs!$B$15*Curves!$C$29 -> 7500 | AJ13: =$B13*Inputs!$B$15*Curves!$C$30 -> 7500 | AK13: =$B13*Inputs!$B$15*Curves!$C$31 -> 7500 | AL13: =$B13*Inputs!$B$15*Curves!$C$32 -> 7500
A14: =Acquisition_Plan!A13 -> 2026-10-29 | B14: =Acquisition_Plan!D13+Acquisition_Plan!F13+Acquisition_Plan!E13 -> 600000 | C14: 0 | D14: 0 | E14: 0 | F14: 0 | G14: 0 | H14: 0 | I14: 0 | J14: 0 | K14: 0 | L14: =$B14*Inputs!$B$15*Curves!$C$5 -> 473902.5 | M14: =$B14*Inputs!$B$15*Curves!$C$6 -> 225972.95 | N14: =$B14*Inputs!$B$15*Curves!$C$7 -> 144850.99 | O14: =$B14*Inputs!$B$15*Curves!$C$8 -> 101911.36 | P14: =$B14*Inputs!$B$15*Curves!$C$9 -> 60589.342 | Q14: =$B14*Inputs!$B$15*Curves!$C$10 -> 54313.84 | R14: =$B14*Inputs!$B$15*Curves!$C$11 -> 46907.85 | S14: =$B14*Inputs!$B$15*Curves!$C$12 -> 41445.705 | T14: =$B14*Inputs!$B$15*Curves!$C$13 -> 37050.798 | U14: =$B14*Inputs!$B$15*Curves!$C$14 -> 43054.666 | V14: =$B14*Inputs!$B$15*Curves!$C$15 -> 30000 | W14: =$B14*Inputs!$B$15*Curves!$C$16 -> 30000 | X14: =$B14*Inputs!$B$15*Curves!$C$17 -> 30000 | Y14: =$B14*Inputs!$B$15*Curves!$C$18 -> 7500 | Z14: =$B14*Inputs!$B$15*Curves!$C$19 -> 7500 | AA14: =$B14*Inputs!$B$15*Curves!$C$20 -> 7500 | AB14: =$B14*Inputs!$B$15*Curves!$C$21 -> 7500 | AC14: =$B14*Inputs!$B$15*Curves!$C$22 -> 7500 | AD14: =$B14*Inputs!$B$15*Curves!$C$23 -> 7500 | AE14: =$B14*Inputs!$B$15*Curves!$C$24 -> 7500 | AF14: =$B14*Inputs!$B$15*Curves!$C$25 -> 7500 | AG14: =$B14*Inputs!$B$15*Curves!$C$26 -> 7500 | AH14: =$B14*Inputs!$B$15*Curves!$C$27 -> 7500 | AI14: =$B14*Inputs!$B$15*Curves!$C$28 -> 7500 | AJ14: =$B14*Inputs!$B$15*Curves!$C$29 -> 7500 | AK14: =$B14*Inputs!$B$15*Curves!$C$30 -> 7500 | AL14: =$B14*Inputs!$B$15*Curves!$C$31 -> 7500
A15: =Acquisition_Plan!A14 -> 2026-11-28 | B15: =Acquisition_Plan!D14+Acquisition_Plan!F14+Acquisition_Plan!E14 -> 700000 | C15: 0 | D15: 0 | E15: 0 | F15: 0 | G15: 0 | H15: 0 | I15: 0 | J15: 0 | K15: 0 | L15: 0 | M15: =$B15*Inputs!$B$15*Curves!$C$5 -> 552886.25 | N15: =$B15*Inputs!$B$15*Curves!$C$6 -> 263635.1 | O15: =$B15*Inputs!$B$15*Curves!$C$7 -> 168992.83 | P15: =$B15*Inputs!$B$15*Curves!$C$8 -> 118896.59 | Q15: =$B15*Inputs!$B$15*Curves!$C$9 -> 70687.565 | R15: =$B15*Inputs!$B$15*Curves!$C$10 -> 63366.147 | S15: =$B15*Inputs!$B$15*Curves!$C$11 -> 54725.825 | T15: =$B15*Inputs!$B$15*Curves!$C$12 -> 48353.322 | U15: =$B15*Inputs!$B$15*Curves!$C$13 -> 43225.93 | V15: =$B15*Inputs!$B$15*Curves!$C$14 -> 50230.444 | W15: =$B15*Inputs!$B$15*Curves!$C$15 -> 35000 | X15: =$B15*Inputs!$B$15*Curves!$C$16 -> 35000 | Y15: =$B15*Inputs!$B$15*Curves!$C$17 -> 35000 | Z15: =$B15*Inputs!$B$15*Curves!$C$18 -> 8750 | AA15: =$B15*Inputs!$B$15*Curves!$C$19 -> 8750 | AB15: =$B15*Inputs!$B$15*Curves!$C$20 -> 8750 | AC15: =$B15*Inputs!$B$15*Curves!$C$21 -> 8750 | AD15: =$B15*Inputs!$B$15*Curves!$C$22 -> 8750 | AE15: =$B15*Inputs!$B$15*Curves!$C$23 -> 8750 | AF15: =$B15*Inputs!$B$15*Curves!$C$24 -> 8750 | AG15: =$B15*Inputs!$B$15*Curves!$C$25 -> 8750 | AH15: =$B15*Inputs!$B$15*Curves!$C$26 -> 8750 | AI15: =$B15*Inputs!$B$15*Curves!$C$27 -> 8750 | AJ15: =$B15*Inputs!$B$15*Curves!$C$28 -> 8750 | AK15: =$B15*Inputs!$B$15*Curves!$C$29 -> 8750 | AL15: =$B15*Inputs!$B$15*Curves!$C$30 -> 8750
A16: =Acquisition_Plan!A15 -> 2026-12-28 | B16: =Acquisition_Plan!D15+Acquisition_Plan!F15+Acquisition_Plan!E15 -> 700000 | C16: 0 | D16: 0 | E16: 0 | F16: 0 | G16: 0 | H16: 0 | I16: 0 | J16: 0 | K16: 0 | L16: 0 | M16: 0 | N16: =$B16*Inputs!$B$15*Curves!$C$5 -> 552886.25 | O16: =$B16*Inputs!$B$15*Curves!$C$6 -> 263635.1 | P16: =$B16*Inputs!$B$15*Curves!$C$7 -> 168992.83 | Q16: =$B16*Inputs!$B$15*Curves!$C$8 -> 118896.59 | R16: =$B16*Inputs!$B$15*Curves!$C$9 -> 70687.565 | S16: =$B16*Inputs!$B$15*Curves!$C$10 -> 63366.147 | T16: =$B16*Inputs!$B$15*Curves!$C$11 -> 54725.825 | U16: =$B16*Inputs!$B$15*Curves!$C$12 -> 48353.322 | V16: =$B16*Inputs!$B$15*Curves!$C$13 -> 43225.93 | W16: =$B16*Inputs!$B$15*Curves!$C$14 -> 50230.444 | X16: =$B16*Inputs!$B$15*Curves!$C$15 -> 35000 | Y16: =$B16*Inputs!$B$15*Curves!$C$16 -> 35000 | Z16: =$B16*Inputs!$B$15*Curves!$C$17 -> 35000 | AA16: =$B16*Inputs!$B$15*Curves!$C$18 -> 8750 | AB16: =$B16*Inputs!$B$15*Curves!$C$19 -> 8750 | AC16: =$B16*Inputs!$B$15*Curves!$C$20 -> 8750 | AD16: =$B16*Inputs!$B$15*Curves!$C$21 -> 8750 | AE16: =$B16*Inputs!$B$15*Curves!$C$22 -> 8750 | AF16: =$B16*Inputs!$B$15*Curves!$C$23 -> 8750 | AG16: =$B16*Inputs!$B$15*Curves!$C$24 -> 8750 | AH16: =$B16*Inputs!$B$15*Curves!$C$25 -> 8750 | AI16: =$B16*Inputs!$B$15*Curves!$C$26 -> 8750 | AJ16: =$B16*Inputs!$B$15*Curves!$C$27 -> 8750 | AK16: =$B16*Inputs!$B$15*Curves!$C$28 -> 8750 | AL16: =$B16*Inputs!$B$15*Curves!$C$29 -> 8750
A17: =Acquisition_Plan!A16 -> 2027-01-27 | B17: =Acquisition_Plan!D16+Acquisition_Plan!F16+Acquisition_Plan!E16 -> 800000 | C17: 0 | D17: 0 | E17: 0 | F17: 0 | G17: 0 | H17: 0 | I17: 0 | J17: 0 | K17: 0 | L17: 0 | M17: 0 | N17: 0 | O17: =$B17*Inputs!$B$15*Curves!$C$5 -> 631870 | P17: =$B17*Inputs!$B$15*Curves!$C$6 -> 301297.26 | Q17: =$B17*Inputs!$B$15*Curves!$C$7 -> 193134.66 | R17: =$B17*Inputs!$B$15*Curves!$C$8 -> 135881.81 | S17: =$B17*Inputs!$B$15*Curves!$C$9 -> 80785.789 | T17: =$B17*Inputs!$B$15*Curves!$C$10 -> 72418.454 | U17: =$B17*Inputs!$B$15*Curves!$C$11 -> 62543.8 | V17: =$B17*Inputs!$B$15*Curves!$C$12 -> 55260.94 | W17: =$B17*Inputs!$B$15*Curves!$C$13 -> 49401.063 | X17: =$B17*Inputs!$B$15*Curves!$C$14 -> 57406.222 | Y17: =$B17*Inputs!$B$15*Curves!$C$15 -> 40000 | Z17: =$B17*Inputs!$B$15*Curves!$C$16 -> 40000 | AA17: =$B17*Inputs!$B$15*Curves!$C$17 -> 40000 | AB17: =$B17*Inputs!$B$15*Curves!$C$18 -> 10000 | AC17: =$B17*Inputs!$B$15*Curves!$C$19 -> 10000 | AD17: =$B17*Inputs!$B$15*Curves!$C$20 -> 10000 | AE17: =$B17*Inputs!$B$15*Curves!$C$21 -> 10000 | AF17: =$B17*Inputs!$B$15*Curves!$C$22 -> 10000 | AG17: =$B17*Inputs!$B$15*Curves!$C$23 -> 10000 | AH17: =$B17*Inputs!$B$15*Curves!$C$24 -> 10000 | AI17: =$B17*Inputs!$B$15*Curves!$C$25 -> 10000 | AJ17: =$B17*Inputs!$B$15*Curves!$C$26 -> 10000 | AK17: =$B17*Inputs!$B$15*Curves!$C$27 -> 10000 | AL17: =$B17*Inputs!$B$15*Curves!$C$28 -> 10000
A18: =Acquisition_Plan!A17 -> 2027-02-26 | B18: =Acquisition_Plan!D17+Acquisition_Plan!F17+Acquisition_Plan!E17 -> 800000 | C18: 0 | D18: 0 | E18: 0 | F18: 0 | G18: 0 | H18: 0 | I18: 0 | J18: 0 | K18: 0 | L18: 0 | M18: 0 | N18: 0 | O18: 0 | P18: =$B18*Inputs!$B$15*Curves!$C$5 -> 631870 | Q18: =$B18*Inputs!$B$15*Curves!$C$6 -> 301297.26 | R18: =$B18*Inputs!$B$15*Curves!$C$7 -> 193134.66 | S18: =$B18*Inputs!$B$15*Curves!$C$8 -> 135881.81 | T18: =$B18*Inputs!$B$15*Curves!$C$9 -> 80785.789 | U18: =$B18*Inputs!$B$15*Curves!$C$10 -> 72418.454 | V18: =$B18*Inputs!$B$15*Curves!$C$11 -> 62543.8 | W18: =$B18*Inputs!$B$15*Curves!$C$12 -> 55260.94 | X18: =$B18*Inputs!$B$15*Curves!$C$13 -> 49401.063 | Y18: =$B18*Inputs!$B$15*Curves!$C$14 -> 57406.222 | Z18: =$B18*Inputs!$B$15*Curves!$C$15 -> 40000 | AA18: =$B18*Inputs!$B$15*Curves!$C$16 -> 40000 | AB18: =$B18*Inputs!$B$15*Curves!$C$17 -> 40000 | AC18: =$B18*Inputs!$B$15*Curves!$C$18 -> 10000 | AD18: =$B18*Inputs!$B$15*Curves!$C$19 -> 10000 | AE18: =$B18*Inputs!$B$15*Curves!$C$20 -> 10000 | AF18: =$B18*Inputs!$B$15*Curves!$C$21 -> 10000 | AG18: =$B18*Inputs!$B$15*Curves!$C$22 -> 10000 | AH18: =$B18*Inputs!$B$15*Curves!$C$23 -> 10000 | AI18: =$B18*Inputs!$B$15*Curves!$C$24 -> 10000 | AJ18: =$B18*Inputs!$B$15*Curves!$C$25 -> 10000 | AK18: =$B18*Inputs!$B$15*Curves!$C$26 -> 10000 | AL18: =$B18*Inputs!$B$15*Curves!$C$27 -> 10000
A19: =Acquisition_Plan!A18 -> 2027-03-28 | B19: =Acquisition_Plan!D18+Acquisition_Plan!F18+Acquisition_Plan!E18 -> 800000 | C19: 0 | D19: 0 | E19: 0 | F19: 0 | G19: 0 | H19: 0 | I19: 0 | J19: 0 | K19: 0 | L19: 0 | M19: 0 | N19: 0 | O19: 0 | P19: 0 | Q19: =$B19*Inputs!$B$15*Curves!$C$5 -> 631870 | R19: =$B19*Inputs!$B$15*Curves!$C$6 -> 301297.26 | S19: =$B19*Inputs!$B$15*Curves!$C$7 -> 193134.66 | T19: =$B19*Inputs!$B$15*Curves!$C$8 -> 135881.81 | U19: =$B19*Inputs!$B$15*Curves!$C$9 -> 80785.789 | V19: =$B19*Inputs!$B$15*Curves!$C$10 -> 72418.454 | W19: =$B19*Inputs!$B$15*Curves!$C$11 -> 62543.8 | X19: =$B19*Inputs!$B$15*Curves!$C$12 -> 55260.94 | Y19: =$B19*Inputs!$B$15*Curves!$C$13 -> 49401.063 | Z19: =$B19*Inputs!$B$15*Curves!$C$14 -> 57406.222 | AA19: =$B19*Inputs!$B$15*Curves!$C$15 -> 40000 | AB19: =$B19*Inputs!$B$15*Curves!$C$16 -> 40000 | AC19: =$B19*Inputs!$B$15*Curves!$C$17 -> 40000 | AD19: =$B19*Inputs!$B$15*Curves!$C$18 -> 10000 | AE19: =$B19*Inputs!$B$15*Curves!$C$19 -> 10000 | AF19: =$B19*Inputs!$B$15*Curves!$C$20 -> 10000 | AG19: =$B19*Inputs!$B$15*Curves!$C$21 -> 10000 | AH19: =$B19*Inputs!$B$15*Curves!$C$22 -> 10000 | AI19: =$B19*Inputs!$B$15*Curves!$C$23 -> 10000 | AJ19: =$B19*Inputs!$B$15*Curves!$C$24 -> 10000 | AK19: =$B19*Inputs!$B$15*Curves!$C$25 -> 10000 | AL19: =$B19*Inputs!$B$15*Curves!$C$26 -> 10000
A20: =Acquisition_Plan!A19 -> 2027-04-27 | B20: =Acquisition_Plan!D19+Acquisition_Plan!F19+Acquisition_Plan!E19 -> 800000 | C20: 0 | D20: 0 | E20: 0 | F20: 0 | G20: 0 | H20: 0 | I20: 0 | J20: 0 | K20: 0 | L20: 0 | M20: 0 | N20: 0 | O20: 0 | P20: 0 | Q20: 0 | R20: =$B20*Inputs!$B$15*Curves!$C$5 -> 631870 | S20: =$B20*Inputs!$B$15*Curves!$C$6 -> 301297.26 | T20: =$B20*Inputs!$B$15*Curves!$C$7 -> 193134.66 | U20: =$B20*Inputs!$B$15*Curves!$C$8 -> 135881.81 | V20: =$B20*Inputs!$B$15*Curves!$C$9 -> 80785.789 | W20: =$B20*Inputs!$B$15*Curves!$C$10 -> 72418.454 | X20: =$B20*Inputs!$B$15*Curves!$C$11 -> 62543.8 | Y20: =$B20*Inputs!$B$15*Curves!$C$12 -> 55260.94 | Z20: =$B20*Inputs!$B$15*Curves!$C$13 -> 49401.063 | AA20: =$B20*Inputs!$B$15*Curves!$C$14 -> 57406.222 | AB20: =$B20*Inputs!$B$15*Curves!$C$15 -> 40000 | AC20: =$B20*Inputs!$B$15*Curves!$C$16 -> 40000 | AD20: =$B20*Inputs!$B$15*Curves!$C$17 -> 40000 | AE20: =$B20*Inputs!$B$15*Curves!$C$18 -> 10000 | AF20: =$B20*Inputs!$B$15*Curves!$C$19 -> 10000 | AG20: =$B20*Inputs!$B$15*Curves!$C$20 -> 10000 | AH20: =$B20*Inputs!$B$15*Curves!$C$21 -> 10000 | AI20: =$B20*Inputs!$B$15*Curves!$C$22 -> 10000 | AJ20: =$B20*Inputs!$B$15*Curves!$C$23 -> 10000 | AK20: =$B20*Inputs!$B$15*Curves!$C$24 -> 10000 | AL20: =$B20*Inputs!$B$15*Curves!$C$25 -> 10000
A21: =Acquisition_Plan!A20 -> 2027-05-27 | B21: =Acquisition_Plan!D20+Acquisition_Plan!F20+Acquisition_Plan!E20 -> 800000 | C21: 0 | D21: 0 | E21: 0 | F21: 0 | G21: 0 | H21: 0 | I21: 0 | J21: 0 | K21: 0 | L21: 0 | M21: 0 | N21: 0 | O21: 0 | P21: 0 | Q21: 0 | R21: 0 | S21: =$B21*Inputs!$B$15*Curves!$C$5 -> 631870 | T21: =$B21*Inputs!$B$15*Curves!$C$6 -> 301297.26 | U21: =$B21*Inputs!$B$15*Curves!$C$7 -> 193134.66 | V21: =$B21*Inputs!$B$15*Curves!$C$8 -> 135881.81 | W21: =$B21*Inputs!$B$15*Curves!$C$9 -> 80785.789 | X21: =$B21*Inputs!$B$15*Curves!$C$10 -> 72418.454 | Y21: =$B21*Inputs!$B$15*Curves!$C$11 -> 62543.8 | Z21: =$B21*Inputs!$B$15*Curves!$C$12 -> 55260.94 | AA21: =$B21*Inputs!$B$15*Curves!$C$13 -> 49401.063 | AB21: =$B21*Inputs!$B$15*Curves!$C$14 -> 57406.222 | AC21: =$B21*Inputs!$B$15*Curves!$C$15 -> 40000 | AD21: =$B21*Inputs!$B$15*Curves!$C$16 -> 40000 | AE21: =$B21*Inputs!$B$15*Curves!$C$17 -> 40000 | AF21: =$B21*Inputs!$B$15*Curves!$C$18 -> 10000 | AG21: =$B21*Inputs!$B$15*Curves!$C$19 -> 10000 | AH21: =$B21*Inputs!$B$15*Curves!$C$20 -> 10000 | AI21: =$B21*Inputs!$B$15*Curves!$C$21 -> 10000 | AJ21: =$B21*Inputs!$B$15*Curves!$C$22 -> 10000 | AK21: =$B21*Inputs!$B$15*Curves!$C$23 -> 10000 | AL21: =$B21*Inputs!$B$15*Curves!$C$24 -> 10000
A22: =Acquisition_Plan!A21 -> 2027-06-26 | B22: =Acquisition_Plan!D21+Acquisition_Plan!F21+Acquisition_Plan!E21 -> 800000 | C22: 0 | D22: 0 | E22: 0 | F22: 0 | G22: 0 | H22: 0 | I22: 0 | J22: 0 | K22: 0 | L22: 0 | M22: 0 | N22: 0 | O22: 0 | P22: 0 | Q22: 0 | R22: 0 | S22: 0 | T22: =$B22*Inputs!$B$15*Curves!$C$5 -> 631870 | U22: =$B22*Inputs!$B$15*Curves!$C$6 -> 301297.26 | V22: =$B22*Inputs!$B$15*Curves!$C$7 -> 193134.66 | W22: =$B22*Inputs!$B$15*Curves!$C$8 -> 135881.81 | X22: =$B22*Inputs!$B$15*Curves!$C$9 -> 80785.789 | Y22: =$B22*Inputs!$B$15*Curves!$C$10 -> 72418.454 | Z22: =$B22*Inputs!$B$15*Curves!$C$11 -> 62543.8 | AA22: =$B22*Inputs!$B$15*Curves!$C$12 -> 55260.94 | AB22: =$B22*Inputs!$B$15*Curves!$C$13 -> 49401.063 | AC22: =$B22*Inputs!$B$15*Curves!$C$14 -> 57406.222 | AD22: =$B22*Inputs!$B$15*Curves!$C$15 -> 40000 | AE22: =$B22*Inputs!$B$15*Curves!$C$16 -> 40000 | AF22: =$B22*Inputs!$B$15*Curves!$C$17 -> 40000 | AG22: =$B22*Inputs!$B$15*Curves!$C$18 -> 10000 | AH22: =$B22*Inputs!$B$15*Curves!$C$19 -> 10000 | AI22: =$B22*Inputs!$B$15*Curves!$C$20 -> 10000 | AJ22: =$B22*Inputs!$B$15*Curves!$C$21 -> 10000 | AK22: =$B22*Inputs!$B$15*Curves!$C$22 -> 10000 | AL22: =$B22*Inputs!$B$15*Curves!$C$23 -> 10000
A23: =Acquisition_Plan!A22 -> 2027-07-26 | B23: =Acquisition_Plan!D22+Acquisition_Plan!F22+Acquisition_Plan!E22 -> 800000 | C23: 0 | D23: 0 | E23: 0 | F23: 0 | G23: 0 | H23: 0 | I23: 0 | J23: 0 | K23: 0 | L23: 0 | M23: 0 | N23: 0 | O23: 0 | P23: 0 | Q23: 0 | R23: 0 | S23: 0 | T23: 0 | U23: =$B23*Inputs!$B$15*Curves!$C$5 -> 631870 | V23: =$B23*Inputs!$B$15*Curves!$C$6 -> 301297.26 | W23: =$B23*Inputs!$B$15*Curves!$C$7 -> 193134.66 | X23: =$B23*Inputs!$B$15*Curves!$C$8 -> 135881.81 | Y23: =$B23*Inputs!$B$15*Curves!$C$9 -> 80785.789 | Z23: =$B23*Inputs!$B$15*Curves!$C$10 -> 72418.454 | AA23: =$B23*Inputs!$B$15*Curves!$C$11 -> 62543.8 | AB23: =$B23*Inputs!$B$15*Curves!$C$12 -> 55260.94 | AC23: =$B23*Inputs!$B$15*Curves!$C$13 -> 49401.063 | AD23: =$B23*Inputs!$B$15*Curves!$C$14 -> 57406.222 | AE23: =$B23*Inputs!$B$15*Curves!$C$15 -> 40000 | AF23: =$B23*Inputs!$B$15*Curves!$C$16 -> 40000 | AG23: =$B23*Inputs!$B$15*Curves!$C$17 -> 40000 | AH23: =$B23*Inputs!$B$15*Curves!$C$18 -> 10000 | AI23: =$B23*Inputs!$B$15*Curves!$C$19 -> 10000 | AJ23: =$B23*Inputs!$B$15*Curves!$C$20 -> 10000 | AK23: =$B23*Inputs!$B$15*Curves!$C$21 -> 10000 | AL23: =$B23*Inputs!$B$15*Curves!$C$22 -> 10000
A24: =Acquisition_Plan!A23 -> 2027-08-25 | B24: =Acquisition_Plan!D23+Acquisition_Plan!F23+Acquisition_Plan!E23 -> 800000 | C24: 0 | D24: 0 | E24: 0 | F24: 0 | G24: 0 | H24: 0 | I24: 0 | J24: 0 | K24: 0 | L24: 0 | M24: 0 | N24: 0 | O24: 0 | P24: 0 | Q24: 0 | R24: 0 | S24: 0 | T24: 0 | U24: 0 | V24: =$B24*Inputs!$B$15*Curves!$C$5 -> 631870 | W24: =$B24*Inputs!$B$15*Curves!$C$6 -> 301297.26 | X24: =$B24*Inputs!$B$15*Curves!$C$7 -> 193134.66 | Y24: =$B24*Inputs!$B$15*Curves!$C$8 -> 135881.81 | Z24: =$B24*Inputs!$B$15*Curves!$C$9 -> 80785.789 | AA24: =$B24*Inputs!$B$15*Curves!$C$10 -> 72418.454 | AB24: =$B24*Inputs!$B$15*Curves!$C$11 -> 62543.8 | AC24: =$B24*Inputs!$B$15*Curves!$C$12 -> 55260.94 | AD24: =$B24*Inputs!$B$15*Curves!$C$13 -> 49401.063 | AE24: =$B24*Inputs!$B$15*Curves!$C$14 -> 57406.222 | AF24: =$B24*Inputs!$B$15*Curves!$C$15 -> 40000 | AG24: =$B24*Inputs!$B$15*Curves!$C$16 -> 40000 | AH24: =$B24*Inputs!$B$15*Curves!$C$17 -> 40000 | AI24: =$B24*Inputs!$B$15*Curves!$C$18 -> 10000 | AJ24: =$B24*Inputs!$B$15*Curves!$C$19 -> 10000 | AK24: =$B24*Inputs!$B$15*Curves!$C$20 -> 10000 | AL24: =$B24*Inputs!$B$15*Curves!$C$21 -> 10000
A25: =Acquisition_Plan!A24 -> 2027-09-24 | B25: =Acquisition_Plan!D24+Acquisition_Plan!F24+Acquisition_Plan!E24 -> 800000 | C25: 0 | D25: 0 | E25: 0 | F25: 0 | G25: 0 | H25: 0 | I25: 0 | J25: 0 | K25: 0 | L25: 0 | M25: 0 | N25: 0 | O25: 0 | P25: 0 | Q25: 0 | R25: 0 | S25: 0 | T25: 0 | U25: 0 | V25: 0 | W25: =$B25*Inputs!$B$15*Curves!$C$5 -> 631870 | X25: =$B25*Inputs!$B$15*Curves!$C$6 -> 301297.26 | Y25: =$B25*Inputs!$B$15*Curves!$C$7 -> 193134.66 | Z25: =$B25*Inputs!$B$15*Curves!$C$8 -> 135881.81 | AA25: =$B25*Inputs!$B$15*Curves!$C$9 -> 80785.789 | AB25: =$B25*Inputs!$B$15*Curves!$C$10 -> 72418.454 | AC25: =$B25*Inputs!$B$15*Curves!$C$11 -> 62543.8 | AD25: =$B25*Inputs!$B$15*Curves!$C$12 -> 55260.94 | AE25: =$B25*Inputs!$B$15*Curves!$C$13 -> 49401.063 | AF25: =$B25*Inputs!$B$15*Curves!$C$14 -> 57406.222 | AG25: =$B25*Inputs!$B$15*Curves!$C$15 -> 40000 | AH25: =$B25*Inputs!$B$15*Curves!$C$16 -> 40000 | AI25: =$B25*Inputs!$B$15*Curves!$C$17 -> 40000 | AJ25: =$B25*Inputs!$B$15*Curves!$C$18 -> 10000 | AK25: =$B25*Inputs!$B$15*Curves!$C$19 -> 10000 | AL25: =$B25*Inputs!$B$15*Curves!$C$20 -> 10000
A26: =Acquisition_Plan!A25 -> 2027-10-24 | B26: =Acquisition_Plan!D25+Acquisition_Plan!F25+Acquisition_Plan!E25 -> 800000 | C26: 0 | D26: 0 | E26: 0 | F26: 0 | G26: 0 | H26: 0 | I26: 0 | J26: 0 | K26: 0 | L26: 0 | M26: 0 | N26: 0 | O26: 0 | P26: 0 | Q26: 0 | R26: 0 | S26: 0 | T26: 0 | U26: 0 | V26: 0 | W26: 0 | X26: =$B26*Inputs!$B$15*Curves!$C$5 -> 631870 | Y26: =$B26*Inputs!$B$15*Curves!$C$6 -> 301297.26 | Z26: =$B26*Inputs!$B$15*Curves!$C$7 -> 193134.66 | AA26: =$B26*Inputs!$B$15*Curves!$C$8 -> 135881.81 | AB26: =$B26*Inputs!$B$15*Curves!$C$9 -> 80785.789 | AC26: =$B26*Inputs!$B$15*Curves!$C$10 -> 72418.454 | AD26: =$B26*Inputs!$B$15*Curves!$C$11 -> 62543.8 | AE26: =$B26*Inputs!$B$15*Curves!$C$12 -> 55260.94 | AF26: =$B26*Inputs!$B$15*Curves!$C$13 -> 49401.063 | AG26: =$B26*Inputs!$B$15*Curves!$C$14 -> 57406.222 | AH26: =$B26*Inputs!$B$15*Curves!$C$15 -> 40000 | AI26: =$B26*Inputs!$B$15*Curves!$C$16 -> 40000 | AJ26: =$B26*Inputs!$B$15*Curves!$C$17 -> 40000 | AK26: =$B26*Inputs!$B$15*Curves!$C$18 -> 10000 | AL26: =$B26*Inputs!$B$15*Curves!$C$19 -> 10000
A27: =Acquisition_Plan!A26 -> 2027-11-23 | B27: =Acquisition_Plan!D26+Acquisition_Plan!F26+Acquisition_Plan!E26 -> 800000 | C27: 0 | D27: 0 | E27: 0 | F27: 0 | G27: 0 | H27: 0 | I27: 0 | J27: 0 | K27: 0 | L27: 0 | M27: 0 | N27: 0 | O27: 0 | P27: 0 | Q27: 0 | R27: 0 | S27: 0 | T27: 0 | U27: 0 | V27: 0 | W27: 0 | X27: 0 | Y27: =$B27*Inputs!$B$15*Curves!$C$5 -> 631870 | Z27: =$B27*Inputs!$B$15*Curves!$C$6 -> 301297.26 | AA27: =$B27*Inputs!$B$15*Curves!$C$7 -> 193134.66 | AB27: =$B27*Inputs!$B$15*Curves!$C$8 -> 135881.81 | AC27: =$B27*Inputs!$B$15*Curves!$C$9 -> 80785.789 | AD27: =$B27*Inputs!$B$15*Curves!$C$10 -> 72418.454 | AE27: =$B27*Inputs!$B$15*Curves!$C$11 -> 62543.8 | AF27: =$B27*Inputs!$B$15*Curves!$C$12 -> 55260.94 | AG27: =$B27*Inputs!$B$15*Curves!$C$13 -> 49401.063 | AH27: =$B27*Inputs!$B$15*Curves!$C$14 -> 57406.222 | AI27: =$B27*Inputs!$B$15*Curves!$C$15 -> 40000 | AJ27: =$B27*Inputs!$B$15*Curves!$C$16 -> 40000 | AK27: =$B27*Inputs!$B$15*Curves!$C$17 -> 40000 | AL27: =$B27*Inputs!$B$15*Curves!$C$18 -> 10000
A28: =Acquisition_Plan!A27 -> 2027-12-23 | B28: =Acquisition_Plan!D27+Acquisition_Plan!F27+Acquisition_Plan!E27 -> 800000 | C28: 0 | D28: 0 | E28: 0 | F28: 0 | G28: 0 | H28: 0 | I28: 0 | J28: 0 | K28: 0 | L28: 0 | M28: 0 | N28: 0 | O28: 0 | P28: 0 | Q28: 0 | R28: 0 | S28: 0 | T28: 0 | U28: 0 | V28: 0 | W28: 0 | X28: 0 | Y28: 0 | Z28: =$B28*Inputs!$B$15*Curves!$C$5 -> 631870 | AA28: =$B28*Inputs!$B$15*Curves!$C$6 -> 301297.26 | AB28: =$B28*Inputs!$B$15*Curves!$C$7 -> 193134.66 | AC28: =$B28*Inputs!$B$15*Curves!$C$8 -> 135881.81 | AD28: =$B28*Inputs!$B$15*Curves!$C$9 -> 80785.789 | AE28: =$B28*Inputs!$B$15*Curves!$C$10 -> 72418.454 | AF28: =$B28*Inputs!$B$15*Curves!$C$11 -> 62543.8 | AG28: =$B28*Inputs!$B$15*Curves!$C$12 -> 55260.94 | AH28: =$B28*Inputs!$B$15*Curves!$C$13 -> 49401.063 | AI28: =$B28*Inputs!$B$15*Curves!$C$14 -> 57406.222 | AJ28: =$B28*Inputs!$B$15*Curves!$C$15 -> 40000 | AK28: =$B28*Inputs!$B$15*Curves!$C$16 -> 40000 | AL28: =$B28*Inputs!$B$15*Curves!$C$17 -> 40000
A29: =Acquisition_Plan!A28 -> 2028-01-22 | B29: =Acquisition_Plan!D28+Acquisition_Plan!F28+Acquisition_Plan!E28 -> 800000 | C29: 0 | D29: 0 | E29: 0 | F29: 0 | G29: 0 | H29: 0 | I29: 0 | J29: 0 | K29: 0 | L29: 0 | M29: 0 | N29: 0 | O29: 0 | P29: 0 | Q29: 0 | R29: 0 | S29: 0 | T29: 0 | U29: 0 | V29: 0 | W29: 0 | X29: 0 | Y29: 0 | Z29: 0 | AA29: =$B29*Inputs!$B$15*Curves!$C$5 -> 631870 | AB29: =$B29*Inputs!$B$15*Curves!$C$6 -> 301297.26 | AC29: =$B29*Inputs!$B$15*Curves!$C$7 -> 193134.66 | AD29: =$B29*Inputs!$B$15*Curves!$C$8 -> 135881.81 | AE29: =$B29*Inputs!$B$15*Curves!$C$9 -> 80785.789 | AF29: =$B29*Inputs!$B$15*Curves!$C$10 -> 72418.454 | AG29: =$B29*Inputs!$B$15*Curves!$C$11 -> 62543.8 | AH29: =$B29*Inputs!$B$15*Curves!$C$12 -> 55260.94 | AI29: =$B29*Inputs!$B$15*Curves!$C$13 -> 49401.063 | AJ29: =$B29*Inputs!$B$15*Curves!$C$14 -> 57406.222 | AK29: =$B29*Inputs!$B$15*Curves!$C$15 -> 40000 | AL29: =$B29*Inputs!$B$15*Curves!$C$16 -> 40000
A30: =Acquisition_Plan!A29 -> 2028-02-21 | B30: =Acquisition_Plan!D29+Acquisition_Plan!F29+Acquisition_Plan!E29 -> 800000 | C30: 0 | D30: 0 | E30: 0 | F30: 0 | G30: 0 | H30: 0 | I30: 0 | J30: 0 | K30: 0 | L30: 0 | M30: 0 | N30: 0 | O30: 0 | P30: 0 | Q30: 0 | R30: 0 | S30: 0 | T30: 0 | U30: 0 | V30: 0 | W30: 0 | X30: 0 | Y30: 0 | Z30: 0 | AA30: 0 | AB30: =$B30*Inputs!$B$15*Curves!$C$5 -> 631870 | AC30: =$B30*Inputs!$B$15*Curves!$C$6 -> 301297.26 | AD30: =$B30*Inputs!$B$15*Curves!$C$7 -> 193134.66 | AE30: =$B30*Inputs!$B$15*Curves!$C$8 -> 135881.81 | AF30: =$B30*Inputs!$B$15*Curves!$C$9 -> 80785.789 | AG30: =$B30*Inputs!$B$15*Curves!$C$10 -> 72418.454 | AH30: =$B30*Inputs!$B$15*Curves!$C$11 -> 62543.8 | AI30: =$B30*Inputs!$B$15*Curves!$C$12 -> 55260.94 | AJ30: =$B30*Inputs!$B$15*Curves!$C$13 -> 49401.063 | AK30: =$B30*Inputs!$B$15*Curves!$C$14 -> 57406.222 | AL30: =$B30*Inputs!$B$15*Curves!$C$15 -> 40000
A31: =Acquisition_Plan!A30 -> 2028-03-22 | B31: =Acquisition_Plan!D30+Acquisition_Plan!F30+Acquisition_Plan!E30 -> 800000 | C31: 0 | D31: 0 | E31: 0 | F31: 0 | G31: 0 | H31: 0 | I31: 0 | J31: 0 | K31: 0 | L31: 0 | M31: 0 | N31: 0 | O31: 0 | P31: 0 | Q31: 0 | R31: 0 | S31: 0 | T31: 0 | U31: 0 | V31: 0 | W31: 0 | X31: 0 | Y31: 0 | Z31: 0 | AA31: 0 | AB31: 0 | AC31: =$B31*Inputs!$B$15*Curves!$C$5 -> 631870 | AD31: =$B31*Inputs!$B$15*Curves!$C$6 -> 301297.26 | AE31: =$B31*Inputs!$B$15*Curves!$C$7 -> 193134.66 | AF31: =$B31*Inputs!$B$15*Curves!$C$8 -> 135881.81 | AG31: =$B31*Inputs!$B$15*Curves!$C$9 -> 80785.789 | AH31: =$B31*Inputs!$B$15*Curves!$C$10 -> 72418.454 | AI31: =$B31*Inputs!$B$15*Curves!$C$11 -> 62543.8 | AJ31: =$B31*Inputs!$B$15*Curves!$C$12 -> 55260.94 | AK31: =$B31*Inputs!$B$15*Curves!$C$13 -> 49401.063 | AL31: =$B31*Inputs!$B$15*Curves!$C$14 -> 57406.222
A32: =Acquisition_Plan!A31 -> 2028-04-21 | B32: =Acquisition_Plan!D31+Acquisition_Plan!F31+Acquisition_Plan!E31 -> 800000 | C32: 0 | D32: 0 | E32: 0 | F32: 0 | G32: 0 | H32: 0 | I32: 0 | J32: 0 | K32: 0 | L32: 0 | M32: 0 | N32: 0 | O32: 0 | P32: 0 | Q32: 0 | R32: 0 | S32: 0 | T32: 0 | U32: 0 | V32: 0 | W32: 0 | X32: 0 | Y32: 0 | Z32: 0 | AA32: 0 | AB32: 0 | AC32: 0 | AD32: =$B32*Inputs!$B$15*Curves!$C$5 -> 631870 | AE32: =$B32*Inputs!$B$15*Curves!$C$6 -> 301297.26 | AF32: =$B32*Inputs!$B$15*Curves!$C$7 -> 193134.66 | AG32: =$B32*Inputs!$B$15*Curves!$C$8 -> 135881.81 | AH32: =$B32*Inputs!$B$15*Curves!$C$9 -> 80785.789 | AI32: =$B32*Inputs!$B$15*Curves!$C$10 -> 72418.454 | AJ32: =$B32*Inputs!$B$15*Curves!$C$11 -> 62543.8 | AK32: =$B32*Inputs!$B$15*Curves!$C$12 -> 55260.94 | AL32: =$B32*Inputs!$B$15*Curves!$C$13 -> 49401.063
A33: =Acquisition_Plan!A32 -> 2028-05-21 | B33: =Acquisition_Plan!D32+Acquisition_Plan!F32+Acquisition_Plan!E32 -> 800000 | C33: 0 | D33: 0 | E33: 0 | F33: 0 | G33: 0 | H33: 0 | I33: 0 | J33: 0 | K33: 0 | L33: 0 | M33: 0 | N33: 0 | O33: 0 | P33: 0 | Q33: 0 | R33: 0 | S33: 0 | T33: 0 | U33: 0 | V33: 0 | W33: 0 | X33: 0 | Y33: 0 | Z33: 0 | AA33: 0 | AB33: 0 | AC33: 0 | AD33: 0 | AE33: =$B33*Inputs!$B$15*Curves!$C$5 -> 631870 | AF33: =$B33*Inputs!$B$15*Curves!$C$6 -> 301297.26 | AG33: =$B33*Inputs!$B$15*Curves!$C$7 -> 193134.66 | AH33: =$B33*Inputs!$B$15*Curves!$C$8 -> 135881.81 | AI33: =$B33*Inputs!$B$15*Curves!$C$9 -> 80785.789 | AJ33: =$B33*Inputs!$B$15*Curves!$C$10 -> 72418.454 | AK33: =$B33*Inputs!$B$15*Curves!$C$11 -> 62543.8 | AL33: =$B33*Inputs!$B$15*Curves!$C$12 -> 55260.94
A34: =Acquisition_Plan!A33 -> 2028-06-20 | B34: =Acquisition_Plan!D33+Acquisition_Plan!F33+Acquisition_Plan!E33 -> 800000 | C34: 0 | D34: 0 | E34: 0 | F34: 0 | G34: 0 | H34: 0 | I34: 0 | J34: 0 | K34: 0 | L34: 0 | M34: 0 | N34: 0 | O34: 0 | P34: 0 | Q34: 0 | R34: 0 | S34: 0 | T34: 0 | U34: 0 | V34: 0 | W34: 0 | X34: 0 | Y34: 0 | Z34: 0 | AA34: 0 | AB34: 0 | AC34: 0 | AD34: 0 | AE34: 0 | AF34: =$B34*Inputs!$B$15*Curves!$C$5 -> 631870 | AG34: =$B34*Inputs!$B$15*Curves!$C$6 -> 301297.26 | AH34: =$B34*Inputs!$B$15*Curves!$C$7 -> 193134.66 | AI34: =$B34*Inputs!$B$15*Curves!$C$8 -> 135881.81 | AJ34: =$B34*Inputs!$B$15*Curves!$C$9 -> 80785.789 | AK34: =$B34*Inputs!$B$15*Curves!$C$10 -> 72418.454 | AL34: =$B34*Inputs!$B$15*Curves!$C$11 -> 62543.8
A35: =Acquisition_Plan!A34 -> 2028-07-20 | B35: =Acquisition_Plan!D34+Acquisition_Plan!F34+Acquisition_Plan!E34 -> 800000 | C35: 0 | D35: 0 | E35: 0 | F35: 0 | G35: 0 | H35: 0 | I35: 0 | J35: 0 | K35: 0 | L35: 0 | M35: 0 | N35: 0 | O35: 0 | P35: 0 | Q35: 0 | R35: 0 | S35: 0 | T35: 0 | U35: 0 | V35: 0 | W35: 0 | X35: 0 | Y35: 0 | Z35: 0 | AA35: 0 | AB35: 0 | AC35: 0 | AD35: 0 | AE35: 0 | AF35: 0 | AG35: =$B35*Inputs!$B$15*Curves!$C$5 -> 631870 | AH35: =$B35*Inputs!$B$15*Curves!$C$6 -> 301297.26 | AI35: =$B35*Inputs!$B$15*Curves!$C$7 -> 193134.66 | AJ35: =$B35*Inputs!$B$15*Curves!$C$8 -> 135881.81 | AK35: =$B35*Inputs!$B$15*Curves!$C$9 -> 80785.789 | AL35: =$B35*Inputs!$B$15*Curves!$C$10 -> 72418.454
A36: =Acquisition_Plan!A35 -> 2028-08-19 | B36: =Acquisition_Plan!D35+Acquisition_Plan!F35+Acquisition_Plan!E35 -> 800000 | C36: 0 | D36: 0 | E36: 0 | F36: 0 | G36: 0 | H36: 0 | I36: 0 | J36: 0 | K36: 0 | L36: 0 | M36: 0 | N36: 0 | O36: 0 | P36: 0 | Q36: 0 | R36: 0 | S36: 0 | T36: 0 | U36: 0 | V36: 0 | W36: 0 | X36: 0 | Y36: 0 | Z36: 0 | AA36: 0 | AB36: 0 | AC36: 0 | AD36: 0 | AE36: 0 | AF36: 0 | AG36: 0 | AH36: =$B36*Inputs!$B$15*Curves!$C$5 -> 631870 | AI36: =$B36*Inputs!$B$15*Curves!$C$6 -> 301297.26 | AJ36: =$B36*Inputs!$B$15*Curves!$C$7 -> 193134.66 | AK36: =$B36*Inputs!$B$15*Curves!$C$8 -> 135881.81 | AL36: =$B36*Inputs!$B$15*Curves!$C$9 -> 80785.789
A37: =Acquisition_Plan!A36 -> 2028-09-18 | B37: =Acquisition_Plan!D36+Acquisition_Plan!F36+Acquisition_Plan!E36 -> 800000 | C37: 0 | D37: 0 | E37: 0 | F37: 0 | G37: 0 | H37: 0 | I37: 0 | J37: 0 | K37: 0 | L37: 0 | M37: 0 | N37: 0 | O37: 0 | P37: 0 | Q37: 0 | R37: 0 | S37: 0 | T37: 0 | U37: 0 | V37: 0 | W37: 0 | X37: 0 | Y37: 0 | Z37: 0 | AA37: 0 | AB37: 0 | AC37: 0 | AD37: 0 | AE37: 0 | AF37: 0 | AG37: 0 | AH37: 0 | AI37: =$B37*Inputs!$B$15*Curves!$C$5 -> 631870 | AJ37: =$B37*Inputs!$B$15*Curves!$C$6 -> 301297.26 | AK37: =$B37*Inputs!$B$15*Curves!$C$7 -> 193134.66 | AL37: =$B37*Inputs!$B$15*Curves!$C$8 -> 135881.81
A38: =Acquisition_Plan!A37 -> 2028-10-18 | B38: =Acquisition_Plan!D37+Acquisition_Plan!F37+Acquisition_Plan!E37 -> 800000 | C38: 0 | D38: 0 | E38: 0 | F38: 0 | G38: 0 | H38: 0 | I38: 0 | J38: 0 | K38: 0 | L38: 0 | M38: 0 | N38: 0 | O38: 0 | P38: 0 | Q38: 0 | R38: 0 | S38: 0 | T38: 0 | U38: 0 | V38: 0 | W38: 0 | X38: 0 | Y38: 0 | Z38: 0 | AA38: 0 | AB38: 0 | AC38: 0 | AD38: 0 | AE38: 0 | AF38: 0 | AG38: 0 | AH38: 0 | AI38: 0 | AJ38: =$B38*Inputs!$B$15*Curves!$C$5 -> 631870 | AK38: =$B38*Inputs!$B$15*Curves!$C$6 -> 301297.26 | AL38: =$B38*Inputs!$B$15*Curves!$C$7 -> 193134.66
A39: =Acquisition_Plan!A38 -> 2028-11-17 | B39: =Acquisition_Plan!D38+Acquisition_Plan!F38+Acquisition_Plan!E38 -> 800000 | C39: 0 | D39: 0 | E39: 0 | F39: 0 | G39: 0 | H39: 0 | I39: 0 | J39: 0 | K39: 0 | L39: 0 | M39: 0 | N39: 0 | O39: 0 | P39: 0 | Q39: 0 | R39: 0 | S39: 0 | T39: 0 | U39: 0 | V39: 0 | W39: 0 | X39: 0 | Y39: 0 | Z39: 0 | AA39: 0 | AB39: 0 | AC39: 0 | AD39: 0 | AE39: 0 | AF39: 0 | AG39: 0 | AH39: 0 | AI39: 0 | AJ39: 0 | AK39: =$B39*Inputs!$B$15*Curves!$C$5 -> 631870 | AL39: =$B39*Inputs!$B$15*Curves!$C$6 -> 301297.26
A40: =Acquisition_Plan!A39 -> 2028-12-17 | B40: =Acquisition_Plan!D39+Acquisition_Plan!F39+Acquisition_Plan!E39 -> 800000 | C40: 0 | D40: 0 | E40: 0 | F40: 0 | G40: 0 | H40: 0 | I40: 0 | J40: 0 | K40: 0 | L40: 0 | M40: 0 | N40: 0 | O40: 0 | P40: 0 | Q40: 0 | R40: 0 | S40: 0 | T40: 0 | U40: 0 | V40: 0 | W40: 0 | X40: 0 | Y40: 0 | Z40: 0 | AA40: 0 | AB40: 0 | AC40: 0 | AD40: 0 | AE40: 0 | AF40: 0 | AG40: 0 | AH40: 0 | AI40: 0 | AJ40: 0 | AK40: 0 | AL40: =$B40*Inputs!$B$15*Curves!$C$5 -> 631870
A41: TOTAL | C41: =SUM(C5:C40) -> 157967.5 | D41: =SUM(D5:D40) -> 272783.69 | E41: =SUM(E5:E40) -> 379390.31 | F41: =SUM(F5:F40) -> 444262.76 | G41: =SUM(G5:G40) -> 564006.48 | H41: =SUM(H5:H40) -> 633314.98 | I41: =SUM(I5:I40) -> 761651.78 | J41: =SUM(J5:J40) -> 838549.54 | ... AL41: =SUM(AL5:AL40) -> 1938125

Sheet New_Cohort_WD
A1: New Cohort Withdrawals (All Sources)
A2: Spend = CC + Cash + PVX
A4: Cohort | B4: Spend | C4: M0 | D4: M1 | E4: M2 | F4: M3 | G4: M4 | H4: M5 | I4: M6 | J4: M7 | K4: M8 | L4: M9 | M4: M10 | N4: M11 | O4: M12 | P4: M13 | Q4: M14 | R4: M15 | S4: M16 | T4: M17 | U4: M18 | V4: M19 | W4: M20 | X4: M21 | Y4: M22 | Z4: M23 | AA4: M24 | AB4: M25 | AC4: M26 | AD4: M27 | AE4: M28 | AF4: M29 | AG4: M30 | AH4: M31 | AI4: M32 | AJ4: M33 | AK4: M34 | AL4: M35
A5: =Acquisition_Plan!A4 -> 2026-02-01 | B5: =Acquisition_Plan!D4+Acquisition_Plan!F4+Acquisition_Plan!E4 -> 200000 | C5: =$B5*Inputs!$B$15*Inputs!$B$16*Curves!$E$5 -> 21388.026 | D5: =$B5*Inputs!$B$15*Inputs!$B$16*Curves!$E$6 -> 23533.985 | E5: =$B5*Inputs!$B$15*Inputs!$B$16*Curves!$E$7 -> 13209.701 | F5: =$B5*Inputs!$B$15*Inputs!$B$16*Curves!$E$8 -> 14254.595 | G5: =$B5*Inputs!$B$15*Inputs!$B$16*Curves!$E$9 -> 14323.857 | H5: =$B5*Inputs!$B$15*Inputs!$B$16*Curves!$E$10 -> 10549.744 | I5: =$B5*Inputs!$B$15*Inputs!$B$16*Curves!$E$11 -> 13887.837 | J5: =$B5*Inputs!$B$15*Inputs!$B$16*Curves!$E$12 -> 6095.2553 | K5: =$B5*Inputs!$B$15*Inputs!$B$16*Curves!$E$13 -> 3939.9265 | L5: =$B5*Inputs!$B$15*Inputs!$B$16*Curves!$E$14 -> 5917.0736 | M5: =$B5*Inputs!$B$15*Inputs!$B$16*Curves!$E$15 -> 3100 | N5: =$B5*Inputs!$B$15*Inputs!$B$16*Curves!$E$16 -> 3100 | O5: =$B5*Inputs!$B$15*Inputs!$B$16*Curves!$E$17 -> 3100 | P5: =$B5*Inputs!$B$15*Inputs!$B$16*Curves!$E$18 -> 775 | Q5: =$B5*Inputs!$B$15*Inputs!$B$16*Curves!$E$19 -> 775 | R5: =$B5*Inputs!$B$15*Inputs!$B$16*Curves!$E$20 -> 775 | S5: =$B5*Inputs!$B$15*Inputs!$B$16*Curves!$E$21 -> 775 | T5: =$B5*Inputs!$B$15*Inputs!$B$16*Curves!$E$22 -> 775 | U5: =$B5*Inputs!$B$15*Inputs!$B$16*Curves!$E$23 -> 775 | V5: =$B5*Inputs!$B$15*Inputs!$B$16*Curves!$E$24 -> 775 | W5: =$B5*Inputs!$B$15*Inputs!$B$16*Curves!$E$25 -> 775 | X5: =$B5*Inputs!$B$15*Inputs!$B$16*Curves!$E$26 -> 775 | Y5: =$B5*Inputs!$B$15*Inputs!$B$16*Curves!$E$27 -> 775 | Z5: =$B5*Inputs!$B$15*Inputs!$B$16*Curves!$E$28 -> 775 | AA5: =$B5*Inputs!$B$15*Inputs!$B$16*Curves!$E$29 -> 775 | AB5: =$B5*Inputs!$B$15*Inputs!$B$16*Curves!$E$30 -> 775 | AC5: =$B5*Inputs!$B$15*Inputs!$B$16*Curves!$E$31 -> 775 | AD5: =$B5*Inputs!$B$15*Inputs!$B$16*Curves!$E$32 -> 775 | AE5: =$B5*Inputs!$B$15*Inputs!$B$16*Curves!$E$33 -> 775 | AF5: =$B5*Inputs!$B$15*Inputs!$B$16*Curves!$E$34 -> 775 | AG5: =$B5*Inputs!$B$15*Inputs!$B$16*Curves!$E$35 -> 775 | AH5: =$B5*Inputs!$B$15*Inputs!$B$16*Curves!$E$36 -> 775 | AI5: =$B5*Inputs!$B$15*Inputs!$B$16*Curves!$E$37 -> 775 | AJ5: =$B5*Inputs!$B$15*Inputs!$B$16*Curves!$E$38 -> 775 | AK5: =$B5*Inputs!$B$15*Inputs!$B$16*Curves!$E$39 -> 775 | AL5: =$B5*Inputs!$B$15*Inputs!$B$16*Curves!$E$40 -> 775
A6: =Acquisition_Plan!A5 -> 2026-03-03 | B6: =Acquisition_Plan!D5+Acquisition_Plan!F5+Acquisition_Plan!E5 -> 250000 | C6: 0 | D6: =$B6*Inputs!$B$15*Inputs!$B$16*Curves!$E$5 -> 26735.032 | E6: =$B6*Inputs!$B$15*Inputs!$B$16*Curves!$E$6 -> 29417.481 | F6: =$B6*Inputs!$B$15*Inputs!$B$16*Curves!$E$7 -> 16512.126 | G6: =$B6*Inputs!$B$15*Inputs!$B$16*Curves!$E$8 -> 17818.244 | H6: =$B6*Inputs!$B$15*Inputs!$B$16*Curves!$E$9 -> 17904.822 | I6: =$B6*Inputs!$B$15*Inputs!$B$16*Curves!$E$10 -> 13187.18 | J6: =$B6*Inputs!$B$15*Inputs!$B$16*Curves!$E$11 -> 17359.797 | K6: =$B6*Inputs!$B$15*Inputs!$B$16*Curves!$E$12 -> 7619.0692 | L6: =$B6*Inputs!$B$15*Inputs!$B$16*Curves!$E$13 -> 4924.9081 | M6: =$B6*Inputs!$B$15*Inputs!$B$16*Curves!$E$14 -> 7396.342 | N6: =$B6*Inputs!$B$15*Inputs!$B$16*Curves!$E$15 -> 3875 | O6: =$B6*Inputs!$B$15*Inputs!$B$16*Curves!$E$16 -> 3875 | P6: =$B6*Inputs!$B$15*Inputs!$B$16*Curves!$E$17 -> 3875 | Q6: =$B6*Inputs!$B$15*Inputs!$B$16*Curves!$E$18 -> 968.75 | R6: =$B6*Inputs!$B$15*Inputs!$B$16*Curves!$E$19 -> 968.75 | S6: =$B6*Inputs!$B$15*Inputs!$B$16*Curves!$E$20 -> 968.75 | T6: =$B6*Inputs!$B$15*Inputs!$B$16*Curves!$E$21 -> 968.75 | U6: =$B6*Inputs!$B$15*Inputs!$B$16*Curves!$E$22 -> 968.75 | V6: =$B6*Inputs!$B$15*Inputs!$B$16*Curves!$E$23 -> 968.75 | W6: =$B6*Inputs!$B$15*Inputs!$B$16*Curves!$E$24 -> 968.75 | X6: =$B6*Inputs!$B$15*Inputs!$B$16*Curves!$E$25 -> 968.75 | Y6: =$B6*Inputs!$B$15*Inputs!$B$16*Curves!$E$26 -> 968.75 | Z6: =$B6*Inputs!$B$15*Inputs!$B$16*Curves!$E$27 -> 968.75 | AA6: =$B6*Inputs!$B$15*Inputs!$B$16*Curves!$E$28 -> 968.75 | AB6: =$B6*Inputs!$B$15*Inputs!$B$16*Curves!$E$29 -> 968.75 | AC6: =$B6*Inputs!$B$15*Inputs!$B$16*Curves!$E$30 -> 968.75 | AD6: =$B6*Inputs!$B$15*Inputs!$B$16*Curves!$E$31 -> 968.75 | AE6: =$B6*Inputs!$B$15*Inputs!$B$16*Curves!$E$32 -> 968.75 | AF6: =$B6*Inputs!$B$15*Inputs!$B$16*Curves!$E$33 -> 968.75 | AG6: =$B6*Inputs!$B$15*Inputs!$B$16*Curves!$E$34 -> 968.75 | AH6: =$B6*Inputs!$B$15*Inputs!$B$16*Curves!$E$35 -> 968.75 | AI6: =$B6*Inputs!$B$15*Inputs!$B$16*Curves!$E$36 -> 968.75 | AJ6: =$B6*Inputs!$B$15*Inputs!$B$16*Curves!$E$37 -> 968.75 | AK6: =$B6*Inputs!$B$15*Inputs!$B$16*Curves!$E$38 -> 968.75 | AL6: =$B6*Inputs!$B$15*Inputs!$B$16*Curves!$E$39 -> 968.75
A7: =Acquisition_Plan!A6 -> 2026-04-02 | B7: =Acquisition_Plan!D6+Acquisition_Plan!F6+Acquisition_Plan!E6 -> 300000 | C7: 0 | D7: 0 | E7: =$B7*Inputs!$B$15*Inputs!$B$16*Curves!$E$5 -> 32082.039 | F7: =$B7*Inputs!$B$15*Inputs!$B$16*Curves!$E$6 -> 35300.977 | G7: =$B7*Inputs!$B$15*Inputs!$B$16*Curves!$E$7 -> 19814.551 | H7: =$B7*Inputs!$B$15*Inputs!$B$16*Curves!$E$8 -> 21381.892 | I7: =$B7*Inputs!$B$15*Inputs!$B$16*Curves!$E$9 -> 21485.786 | J7: =$B7*Inputs!$B$15*Inputs!$B$16*Curves!$E$10 -> 15824.616 | K7: =$B7*Inputs!$B$15*Inputs!$B$16*Curves!$E$11 -> 20831.756 | L7: =$B7*Inputs!$B$15*Inputs!$B$16*Curves!$E$12 -> 9142.883 | M7: =$B7*Inputs!$B$15*Inputs!$B$16*Curves!$E$13 -> 5909.8897 | N7: =$B7*Inputs!$B$15*Inputs!$B$16*Curves!$E$14 -> 8875.6104 | O7: =$B7*Inputs!$B$15*Inputs!$B$16*Curves!$E$15 -> 4650 | P7: =$B7*Inputs!$B$15*Inputs!$B$16*Curves!$E$16 -> 4650 | Q7: =$B7*Inputs!$B$15*Inputs!$B$16*Curves!$E$17 -> 4650 | R7: =$B7*Inputs!$B$15*Inputs!$B$16*Curves!$E$18 -> 1162.5 | S7: =$B7*Inputs!$B$15*Inputs!$B$16*Curves!$E$19 -> 1162.5 | T7: =$B7*Inputs!$B$15*Inputs!$B$16*Curves!$E$20 -> 1162.5 | U7: =$B7*Inputs!$B$15*Inputs!$B$16*Curves!$E$21 -> 1162.5 | V7: =$B7*Inputs!$B$15*Inputs!$B$16*Curves!$E$22 -> 1162.5 | W7: =$B7*Inputs!$B$15*Inputs!$B$16*Curves!$E$23 -> 1162.5 | X7: =$B7*Inputs!$B$15*Inputs!$B$16*Curves!$E$24 -> 1162.5 | Y7: =$B7*Inputs!$B$15*Inputs!$B$16*Curves!$E$25 -> 1162.5 | Z7: =$B7*Inputs!$B$15*Inputs!$B$16*Curves!$E$26 -> 1162.5 | AA7: =$B7*Inputs!$B$15*Inputs!$B$16*Curves!$E$27 -> 1162.5 | AB7: =$B7*Inputs!$B$15*Inputs!$B$16*Curves!$E$28 -> 1162.5 | AC7: =$B7*Inputs!$B$15*Inputs!$B$16*Curves!$E$29 -> 1162.5 | AD7: =$B7*Inputs!$B$15*Inputs!$B$16*Curves!$E$30 -> 1162.5 | AE7: =$B7*Inputs!$B$15*Inputs!$B$16*Curves!$E$31 -> 1162.5 | AF7: =$B7*Inputs!$B$15*Inputs!$B$16*Curves!$E$32 -> 1162.5 | AG7: =$B7*Inputs!$B$15*Inputs!$B$16*Curves!$E$33 -> 1162.5 | AH7: =$B7*Inputs!$B$15*Inputs!$B$16*Curves!$E$34 -> 1162.5 | AI7: =$B7*Inputs!$B$15*Inputs!$B$16*Curves!$E$35 -> 1162.5 | AJ7: =$B7*Inputs!$B$15*Inputs!$B$16*Curves!$E$36 -> 1162.5 | AK7: =$B7*Inputs!$B$15*Inputs!$B$16*Curves!$E$37 -> 1162.5 | AL7: =$B7*Inputs!$B$15*Inputs!$B$16*Curves!$E$38 -> 1162.5
A8: =Acquisition_Plan!A7 -> 2026-05-02 | B8: =Acquisition_Plan!D7+Acquisition_Plan!F7+Acquisition_Plan!E7 -> 300000 | C8: 0 | D8: 0 | E8: 0 | F8: =$B8*Inputs!$B$15*Inputs!$B$16*Curves!$E$5 -> 32082.039 | G8: =$B8*Inputs!$B$15*Inputs!$B$16*Curves!$E$6 -> 35300.977 | H8: =$B8*Inputs!$B$15*Inputs!$B$16*Curves!$E$7 -> 19814.551 | I8: =$B8*Inputs!$B$15*Inputs!$B$16*Curves!$E$8 -> 21381.892 | J8: =$B8*Inputs!$B$15*Inputs!$B$16*Curves!$E$9 -> 21485.786 | K8: =$B8*Inputs!$B$15*Inputs!$B$16*Curves!$E$10 -> 15824.616 | L8: =$B8*Inputs!$B$15*Inputs!$B$16*Curves!$E$11 -> 20831.756 | M8: =$B8*Inputs!$B$15*Inputs!$B$16*Curves!$E$12 -> 9142.883 | N8: =$B8*Inputs!$B$15*Inputs!$B$16*Curves!$E$13 -> 5909.8897 | O8: =$B8*Inputs!$B$15*Inputs!$B$16*Curves!$E$14 -> 8875.6104 | P8: =$B8*Inputs!$B$15*Inputs!$B$16*Curves!$E$15 -> 4650 | Q8: =$B8*Inputs!$B$15*Inputs!$B$16*Curves!$E$16 -> 4650 | R8: =$B8*Inputs!$B$15*Inputs!$B$16*Curves!$E$17 -> 4650 | S8: =$B8*Inputs!$B$15*Inputs!$B$16*Curves!$E$18 -> 1162.5 | T8: =$B8*Inputs!$B$15*Inputs!$B$16*Curves!$E$19 -> 1162.5 | U8: =$B8*Inputs!$B$15*Inputs!$B$16*Curves!$E$20 -> 1162.5 | V8: =$B8*Inputs!$B$15*Inputs!$B$16*Curves!$E$21 -> 1162.5 | W8: =$B8*Inputs!$B$15*Inputs!$B$16*Curves!$E$22 -> 1162.5 | X8: =$B8*Inputs!$B$15*Inputs!$B$16*Curves!$E$23 -> 1162.5 | Y8: =$B8*Inputs!$B$15*Inputs!$B$16*Curves!$E$24 -> 1162.5 | Z8: =$B8*Inputs!$B$15*Inputs!$B$16*Curves!$E$25 -> 1162.5 | AA8: =$B8*Inputs!$B$15*Inputs!$B$16*Curves!$E$26 -> 1162.5 | AB8: =$B8*Inputs!$B$15*Inputs!$B$16*Curves!$E$27 -> 1162.5 | AC8: =$B8*Inputs!$B$15*Inputs!$B$16*Curves!$E$28 -> 1162.5 | AD8: =$B8*Inputs!$B$15*Inputs!$B$16*Curves!$E$29 -> 1162.5 | AE8: =$B8*Inputs!$B$15*Inputs!$B$16*Curves!$E$30 -> 1162.5 | AF8: =$B8*Inputs!$B$15*Inputs!$B$16*Curves!$E$31 -> 1162.5 | AG8: =$B8*Inputs!$B$15*Inputs!$B$16*Curves!$E$32 -> 1162.5 | AH8: =$B8*Inputs!$B$15*Inputs!$B$16*Curves!$E$33 -> 1162.5 | AI8: =$B8*Inputs!$B$15*Inputs!$B$16*Curves!$E$34 -> 1162.5 | AJ8: =$B8*Inputs!$B$15*Inputs!$B$16*Curves!$E$35 -> 1162.5 | AK8: =$B8*Inputs!$B$15*Inputs!$B$16*Curves!$E$36 -> 1162.5 | AL8: =$B8*Inputs!$B$15*Inputs!$B$16*Curves!$E$37 -> 1162.5
A9: =Acquisition_Plan!A8 -> 2026-06-01 | B9: =Acquisition_Plan!D8+Acquisition_Plan!F8+Acquisition_Plan!E8 -> 400000 | C9: 0 | D9: 0 | E9: 0 | F9: 0 | G9: =$B9*Inputs!$B$15*Inputs!$B$16*Curves!$E$5 -> 42776.052 | H9: =$B9*Inputs!$B$15*Inputs!$B$16*Curves!$E$6 -> 47067.969 | I9: =$B9*Inputs!$B$15*Inputs!$B$16*Curves!$E$7 -> 26419.401 | J9: =$B9*Inputs!$B$15*Inputs!$B$16*Curves!$E$8 -> 28509.19 | K9: =$B9*Inputs!$B$15*Inputs!$B$16*Curves!$E$9 -> 28647.714 | L9: =$B9*Inputs!$B$15*Inputs!$B$16*Curves!$E$10 -> 21099.488 | M9: =$B9*Inputs!$B$15*Inputs!$B$16*Curves!$E$11 -> 27775.675 | N9: =$B9*Inputs!$B$15*Inputs!$B$16*Curves!$E$12 -> 12190.511 | O9: =$B9*Inputs!$B$15*Inputs!$B$16*Curves!$E$13 -> 7879.853 | P9: =$B9*Inputs!$B$15*Inputs!$B$16*Curves!$E$14 -> 11834.147 | Q9: =$B9*Inputs!$B$15*Inputs!$B$16*Curves!$E$15 -> 6200 | R9: =$B9*Inputs!$B$15*Inputs!$B$16*Curves!$E$16 -> 6200 | S9: =$B9*Inputs!$B$15*Inputs!$B$16*Curves!$E$17 -> 6200 | T9: =$B9*Inputs!$B$15*Inputs!$B$16*Curves!$E$18 -> 1550 | U9: =$B9*Inputs!$B$15*Inputs!$B$16*Curves!$E$19 -> 1550 | V9: =$B9*Inputs!$B$15*Inputs!$B$16*Curves!$E$20 -> 1550 | W9: =$B9*Inputs!$B$15*Inputs!$B$16*Curves!$E$21 -> 1550 | X9: =$B9*Inputs!$B$15*Inputs!$B$16*Curves!$E$22 -> 1550 | Y9: =$B9*Inputs!$B$15*Inputs!$B$16*Curves!$E$23 -> 1550 | Z9: =$B9*Inputs!$B$15*Inputs!$B$16*Curves!$E$24 -> 1550 | AA9: =$B9*Inputs!$B$15*Inputs!$B$16*Curves!$E$25 -> 1550 | AB9: =$B9*Inputs!$B$15*Inputs!$B$16*Curves!$E$26 -> 1550 | AC9: =$B9*Inputs!$B$15*Inputs!$B$16*Curves!$E$27 -> 1550 | AD9: =$B9*Inputs!$B$15*Inputs!$B$16*Curves!$E$28 -> 1550 | AE9: =$B9*Inputs!$B$15*Inputs!$B$16*Curves!$E$29 -> 1550 | AF9: =$B9*Inputs!$B$15*Inputs!$B$16*Curves!$E$30 -> 1550 | AG9: =$B9*Inputs!$B$15*Inputs!$B$16*Curves!$E$31 -> 1550 | AH9: =$B9*Inputs!$B$15*Inputs!$B$16*Curves!$E$32 -> 1550 | AI9: =$B9*Inputs!$B$15*Inputs!$B$16*Curves!$E$33 -> 1550 | AJ9: =$B9*Inputs!$B$15*Inputs!$B$16*Curves!$E$34 -> 1550 | AK9: =$B9*Inputs!$B$15*Inputs!$B$16*Curves!$E$35 -> 1550 | AL9: =$B9*Inputs!$B$15*Inputs!$B$16*Curves!$E$36 -> 1550
A10: =Acquisition_Plan!A9 -> 2026-07-01 | B10: =Acquisition_Plan!D9+Acquisition_Plan!F9+Acquisition_Plan!E9 -> 400000 | C10: 0 | D10: 0 | E10: 0 | F10: 0 | G10: 0 | H10: =$B10*Inputs!$B$15*Inputs!$B$16*Curves!$E$5 -> 42776.052 | I10: =$B10*Inputs!$B$15*Inputs!$B$16*Curves!$E$6 -> 47067.969 | J10: =$B10*Inputs!$B$15*Inputs!$B$16*Curves!$E$7 -> 26419.401 | K10: =$B10*Inputs!$B$15*Inputs!$B$16*Curves!$E$8 -> 28509.19 | L10: =$B10*Inputs!$B$15*Inputs!$B$16*Curves!$E$9 -> 28647.714 | M10: =$B10*Inputs!$B$15*Inputs!$B$16*Curves!$E$10 -> 21099.488 | N10: =$B10*Inputs!$B$15*Inputs!$B$16*Curves!$E$11 -> 27775.675 | O10: =$B10*Inputs!$B$15*Inputs!$B$16*Curves!$E$12 -> 12190.511 | P10: =$B10*Inputs!$B$15*Inputs!$B$16*Curves!$E$13 -> 7879.853 | Q10: =$B10*Inputs!$B$15*Inputs!$B$16*Curves!$E$14 -> 11834.147 | R10: =$B10*Inputs!$B$15*Inputs!$B$16*Curves!$E$15 -> 6200 | S10: =$B10*Inputs!$B$15*Inputs!$B$16*Curves!$E$16 -> 6200 | T10: =$B10*Inputs!$B$15*Inputs!$B$16*Curves!$E$17 -> 6200 | U10: =$B10*Inputs!$B$15*Inputs!$B$16*Curves!$E$18 -> 1550 | V10: =$B10*Inputs!$B$15*Inputs!$B$16*Curves!$E$19 -> 1550 | W10: =$B10*Inputs!$B$15*Inputs!$B$16*Curves!$E$20 -> 1550 | X10: =$B10*Inputs!$B$15*Inputs!$B$16*Curves!$E$21 -> 1550 | Y10: =$B10*Inputs!$B$15*Inputs!$B$16*Curves!$E$22 -> 1550 | Z10: =$B10*Inputs!$B$15*Inputs!$B$16*Curves!$E$23 -> 1550 | AA10: =$B10*Inputs!$B$15*Inputs!$B$16*Curves!$E$24 -> 1550 | AB10: =$B10*Inputs!$B$15*Inputs!$B$16*Curves!$E$25 -> 1550 | AC10: =$B10*Inputs!$B$15*Inputs!$B$16*Curves!$E$26 -> 1550 | AD10: =$B10*Inputs!$B$15*Inputs!$B$16*Curves!$E$27 -> 1550 | AE10: =$B10*Inputs!$B$15*Inputs!$B$16*Curves!$E$28 -> 1550 | AF10: =$B10*Inputs!$B$15*Inputs!$B$16*Curves!$E$29 -> 1550 | AG10: =$B10*Inputs!$B$15*Inputs!$B$16*Curves!$E$30 -> 1550 | AH10: =$B10*Inputs!$B$15*Inputs!$B$16*Curves!$E$31 -> 1550 | AI10: =$B10*Inputs!$B$15*Inputs!$B$16*Curves!$E$32 -> 1550 | AJ10: =$B10*Inputs!$B$15*Inputs!$B$16*Curves!$E$33 -> 1550 | AK10: =$B10*Inputs!$B$15*Inputs!$B$16*Curves!$E$34 -> 1550 | AL10: =$B10*Inputs!$B$15*Inputs!$B$16*Curves!$E$35 -> 1550
A11: =Acquisition_Plan!A10 -> 2026-07-31 | B11: =Acquisition_Plan!D10+Acquisition_Plan!F10+Acquisition_Plan!E10 -> 500000 | C11: 0 | D11: 0 | E11: 0 | F11: 0 | G11: 0 | H11: 0 | I11: =$B11*Inputs!$B$15*Inputs!$B$16*Curves!$E$5 -> 53470.065 | J11: =$B11*Inputs!$B$15*Inputs!$B$16*Curves!$E$6 -> 58834.962 | K11: =$B11*Inputs!$B$15*Inputs!$B$16*Curves!$E$7 -> 33024.252 | L11: =$B11*Inputs!$B$15*Inputs!$B$16*Curves!$E$8 -> 35636.487 | M11: =$B11*Inputs!$B$15*Inputs!$B$16*Curves!$E$9 -> 35809.643 | N11: =$B11*Inputs!$B$15*Inputs!$B$16*Curves!$E$10 -> 26374.36 | O11: =$B11*Inputs!$B$15*Inputs!$B$16*Curves!$E$11 -> 34719.593 | P11: =$B11*Inputs!$B$15*Inputs!$B$16*Curves!$E$12 -> 15238.138 | Q11: =$B11*Inputs!$B$15*Inputs!$B$16*Curves!$E$13 -> 9849.8162 | R11: =$B11*Inputs!$B$15*Inputs!$B$16*Curves!$E$14 -> 14792.684 | S11: =$B11*Inputs!$B$15*Inputs!$B$16*Curves!$E$15 -> 7750 | T11: =$B11*Inputs!$B$15*Inputs!$B$16*Curves!$E$16 -> 7750 | U11: =$B11*Inputs!$B$15*Inputs!$B$16*Curves!$E$17 -> 7750 | V11: =$B11*Inputs!$B$15*Inputs!$B$16*Curves!$E$18 -> 1937.5 | W11: =$B11*Inputs!$B$15*Inputs!$B$16*Curves!$E$19 -> 1937.5 | X11: =$B11*Inputs!$B$15*Inputs!$B$16*Curves!$E$20 -> 1937.5 | Y11: =$B11*Inputs!$B$15*Inputs!$B$16*Curves!$E$21 -> 1937.5 | Z11: =$B11*Inputs!$B$15*Inputs!$B$16*Curves!$E$22 -> 1937.5 | AA11: =$B11*Inputs!$B$15*Inputs!$B$16*Curves!$E$23 -> 1937.5 | AB11: =$B11*Inputs!$B$15*Inputs!$B$16*Curves!$E$24 -> 1937.5 | AC11: =$B11*Inputs!$B$15*Inputs!$B$16*Curves!$E$25 -> 1937.5 | AD11: =$B11*Inputs!$B$15*Inputs!$B$16*Curves!$E$26 -> 1937.5 | AE11: =$B11*Inputs!$B$15*Inputs!$B$16*Curves!$E$27 -> 1937.5 | AF11: =$B11*Inputs!$B$15*Inputs!$B$16*Curves!$E$28 -> 1937.5 | AG11: =$B11*Inputs!$B$15*Inputs!$B$16*Curves!$E$29 -> 1937.5 | AH11: =$B11*Inputs!$B$15*Inputs!$B$16*Curves!$E$30 -> 1937.5 | AI11: =$B11*Inputs!$B$15*Inputs!$B$16*Curves!$E$31 -> 1937.5 | AJ11: =$B11*Inputs!$B$15*Inputs!$B$16*Curves!$E$32 -> 1937.5 | AK11: =$B11*Inputs!$B$15*Inputs!$B$16*Curves!$E$33 -> 1937.5 | AL11: =$B11*Inputs!$B$15*Inputs!$B$16*Curves!$E$34 -> 1937.5
A12: =Acquisition_Plan!A11 -> 2026-08-30 | B12: =Acquisition_Plan!D11+Acquisition_Plan!F11+Acquisition_Plan!E11 -> 500000 | C12: 0 | D12: 0 | E12: 0 | F12: 0 | G12: 0 | H12: 0 | I12: 0 | J12: =$B12*Inputs!$B$15*Inputs!$B$16*Curves!$E$5 -> 53470.065 | K12: =$B12*Inputs!$B$15*Inputs!$B$16*Curves!$E$6 -> 58834.962 | L12: =$B12*Inputs!$B$15*Inputs!$B$16*Curves!$E$7 -> 33024.252 | M12: =$B12*Inputs!$B$15*Inputs!$B$16*Curves!$E$8 -> 35636.487 | N12: =$B12*Inputs!$B$15*Inputs!$B$16*Curves!$E$9 -> 35809.643 | O12: =$B12*Inputs!$B$15*Inputs!$B$16*Curves!$E$10 -> 26374.36 | P12: =$B12*Inputs!$B$15*Inputs!$B$16*Curves!$E$11 -> 34719.593 | Q12: =$B12*Inputs!$B$15*Inputs!$B$16*Curves!$E$12 -> 15238.138 | R12: =$B12*Inputs!$B$15*Inputs!$B$16*Curves!$E$13 -> 9849.8162 | S12: =$B12*Inputs!$B$15*Inputs!$B$16*Curves!$E$14 -> 14792.684 | T12: =$B12*Inputs!$B$15*Inputs!$B$16*Curves!$E$15 -> 7750 | U12: =$B12*Inputs!$B$15*Inputs!$B$16*Curves!$E$16 -> 7750 | V12: =$B12*Inputs!$B$15*Inputs!$B$16*Curves!$E$17 -> 7750 | W12: =$B12*Inputs!$B$15*Inputs!$B$16*Curves!$E$18 -> 1937.5 | X12: =$B12*Inputs!$B$15*Inputs!$B$16*Curves!$E$19 -> 1937.5 | Y12: =$B12*Inputs!$B$15*Inputs!$B$16*Curves!$E$20 -> 1937.5 | Z12: =$B12*Inputs!$B$15*Inputs!$B$16*Curves!$E$21 -> 1937.5 | AA12: =$B12*Inputs!$B$15*Inputs!$B$16*Curves!$E$22 -> 1937.5 | AB12: =$B12*Inputs!$B$15*Inputs!$B$16*Curves!$E$23 -> 1937.5 | AC12: =$B12*Inputs!$B$15*Inputs!$B$16*Curves!$E$24 -> 1937.5 | AD12: =$B12*Inputs!$B$15*Inputs!$B$16*Curves!$E$25 -> 1937.5 | AE12: =$B12*Inputs!$B$15*Inputs!$B$16*Curves!$E$26 -> 1937.5 | AF12: =$B12*Inputs!$B$15*Inputs!$B$16*Curves!$E$27 -> 1937.5 | AG12: =$B12*Inputs!$B$15*Inputs!$B$16*Curves!$E$28 -> 1937.5 | AH12: =$B12*Inputs!$B$15*Inputs!$B$16*Curves!$E$29 -> 1937.5 | AI12: =$B12*Inputs!$B$15*Inputs!$B$16*Curves!$E$30 -> 1937.5 | AJ12: =$B12*Inputs!$B$15*Inputs!$B$16*Curves!$E$31 -> 1937.5 | AK12: =$B12*Inputs!$B$15*Inputs!$B$16*Curves!$E$32 -> 1937.5 | AL12: =$B12*Inputs!$B$15*Inputs!$B$16*Curves!$E$33 -> 1937.5
A13: =Acquisition_Plan!A12 -> 2026-09-29 | B13: =Acquisition_Plan!D12+Acquisition_Plan!F12+Acquisition_Plan!E12 -> 600000 | C13: 0 | D13: 0 | E13: 0 | F13: 0 | G13: 0 | H13: 0 | I13: 0 | J13: 0 | K13: =$B13*Inputs!$B$15*Inputs!$B$16*Curves!$E$5 -> 64164.078 | L13: =$B13*Inputs!$B$15*Inputs!$B$16*Curves!$E$6 -> 70601.954 | M13: =$B13*Inputs!$B$15*Inputs!$B$16*Curves!$E$7 -> 39629.102 | N13: =$B13*Inputs!$B$15*Inputs!$B$16*Curves!$E$8 -> 42763.784 | O13: =$B13*Inputs!$B$15*Inputs!$B$16*Curves!$E$9 -> 42971.572 | P13: =$B13*Inputs!$B$15*Inputs!$B$16*Curves!$E$10 -> 31649.232 | Q13: =$B13*Inputs!$B$15*Inputs!$B$16*Curves!$E$11 -> 41663.512 | R13: =$B13*Inputs!$B$15*Inputs!$B$16*Curves!$E$12 -> 18285.766 | S13: =$B13*Inputs!$B$15*Inputs!$B$16*Curves!$E$13 -> 11819.779 | T13: =$B13*Inputs!$B$15*Inputs!$B$16*Curves!$E$14 -> 17751.221 | U13: =$B13*Inputs!$B$15*Inputs!$B$16*Curves!$E$15 -> 9300 | V13: =$B13*Inputs!$B$15*Inputs!$B$16*Curves!$E$16 -> 9300 | W13: =$B13*Inputs!$B$15*Inputs!$B$16*Curves!$E$17 -> 9300 | X13: =$B13*Inputs!$B$15*Inputs!$B$16*Curves!$E$18 -> 2325 | Y13: =$B13*Inputs!$B$15*Inputs!$B$16*Curves!$E$19 -> 2325 | Z13: =$B13*Inputs!$B$15*Inputs!$B$16*Curves!$E$20 -> 2325 | AA13: =$B13*Inputs!$B$15*Inputs!$B$16*Curves!$E$21 -> 2325 | AB13: =$B13*Inputs!$B$15*Inputs!$B$16*Curves!$E$22 -> 2325 | AC13: =$B13*Inputs!$B$15*Inputs!$B$16*Curves!$E$23 -> 2325 | AD13: =$B13*Inputs!$B$15*Inputs!$B$16*Curves!$E$24 -> 2325 | AE13: =$B13*Inputs!$B$15*Inputs!$B$16*Curves!$E$25 -> 2325 | AF13: =$B13*Inputs!$B$15*Inputs!$B$16*Curves!$E$26 -> 2325 | AG13: =$B13*Inputs!$B$15*Inputs!$B$16*Curves!$E$27 -> 2325 | AH13: =$B13*Inputs!$B$15*Inputs!$B$16*Curves!$E$28 -> 2325 | AI13: =$B13*Inputs!$B$15*Inputs!$B$16*Curves!$E$29 -> 2325 | AJ13: =$B13*Inputs!$B$15*Inputs!$B$16*Curves!$E$30 -> 2325 | AK13: =$B13*Inputs!$B$15*Inputs!$B$16*Curves!$E$31 -> 2325 | AL13: =$B13*Inputs!$B$15*Inputs!$B$16*Curves!$E$32 -> 2325
A14: =Acquisition_Plan!A13 -> 2026-10-29 | B14: =Acquisition_Plan!D13+Acquisition_Plan!F13+Acquisition_Plan!E13 -> 600000 | C14: 0 | D14: 0 | E14: 0 | F14: 0 | G14: 0 | H14: 0 | I14: 0 | J14: 0 | K14: 0 | L14: =$B14*Inputs!$B$15*Inputs!$B$16*Curves!$E$5 -> 64164.078 | M14: =$B14*Inputs!$B$15*Inputs!$B$16*Curves!$E$6 -> 70601.954 | N14: =$B14*Inputs!$B$15*Inputs!$B$16*Curves!$E$7 -> 39629.102 | O14: =$B14*Inputs!$B$15*Inputs!$B$16*Curves!$E$8 -> 42763.784 | P14: =$B14*Inputs!$B$15*Inputs!$B$16*Curves!$E$9 -> 42971.572 | Q14: =$B14*Inputs!$B$15*Inputs!$B$16*Curves!$E$10 -> 31649.232 | R14: =$B14*Inputs!$B$15*Inputs!$B$16*Curves!$E$11 -> 41663.512 | S14: =$B14*Inputs!$B$15*Inputs!$B$16*Curves!$E$12 -> 18285.766 | T14: =$B14*Inputs!$B$15*Inputs!$B$16*Curves!$E$13 -> 11819.779 | U14: =$B14*Inputs!$B$15*Inputs!$B$16*Curves!$E$14 -> 17751.221 | V14: =$B14*Inputs!$B$15*Inputs!$B$16*Curves!$E$15 -> 9300 | W14: =$B14*Inputs!$B$15*Inputs!$B$16*Curves!$E$16 -> 9300 | X14: =$B14*Inputs!$B$15*Inputs!$B$16*Curves!$E$17 -> 9300 | Y14: =$B14*Inputs!$B$15*Inputs!$B$16*Curves!$E$18 -> 2325 | Z14: =$B14*Inputs!$B$15*Inputs!$B$16*Curves!$E$19 -> 2325 | AA14: =$B14*Inputs!$B$15*Inputs!$B$16*Curves!$E$20 -> 2325 | AB14: =$B14*Inputs!$B$15*Inputs!$B$16*Curves!$E$21 -> 2325 | AC14: =$B14*Inputs!$B$15*Inputs!$B$16*Curves!$E$22 -> 2325 | AD14: =$B14*Inputs!$B$15*Inputs!$B$16*Curves!$E$23 -> 2325 | AE14: =$B14*Inputs!$B$15*Inputs!$B$16*Curves!$E$24 -> 2325 | AF14: =$B14*Inputs!$B$15*Inputs!$B$16*Curves!$E$25 -> 2325 | AG14: =$B14*Inputs!$B$15*Inputs!$B$16*Curves!$E$26 -> 2325 | AH14: =$B14*Inputs!$B$15*Inputs!$B$16*Curves!$E$27 -> 2325 | AI14: =$B14*Inputs!$B$15*Inputs!$B$16*Curves!$E$28 -> 2325 | AJ14: =$B14*Inputs!$B$15*Inputs!$B$16*Curves!$E$29 -> 2325 | AK14: =$B14*Inputs!$B$15*Inputs!$B$16*Curves!$E$30 -> 2325 | AL14: =$B14*Inputs!$B$15*Inputs!$B$16*Curves!$E$31 -> 2325
A15: =Acquisition_Plan!A14 -> 2026-11-28 | B15: =Acquisition_Plan!D14+Acquisition_Plan!F14+Acquisition_Plan!E14 -> 700000 | C15: 0 | D15: 0 | E15: 0 | F15: 0 | G15: 0 | H15: 0 | I15: 0 | J15: 0 | K15: 0 | L15: 0 | M15: =$B15*Inputs!$B$15*Inputs!$B$16*Curves!$E$5 -> 74858.091 | N15: =$B15*Inputs!$B$15*Inputs!$B$16*Curves!$E$6 -> 82368.946 | O15: =$B15*Inputs!$B$15*Inputs!$B$16*Curves!$E$7 -> 46233.952 | P15: =$B15*Inputs!$B$15*Inputs!$B$16*Curves!$E$8 -> 49891.082 | Q15: =$B15*Inputs!$B$15*Inputs!$B$16*Curves!$E$9 -> 50133.5 | R15: =$B15*Inputs!$B$15*Inputs!$B$16*Curves!$E$10 -> 36924.104 | S15: =$B15*Inputs!$B$15*Inputs!$B$16*Curves!$E$11 -> 48607.431 | T15: =$B15*Inputs!$B$15*Inputs!$B$16*Curves!$E$12 -> 21333.394 | U15: =$B15*Inputs!$B$15*Inputs!$B$16*Curves!$E$13 -> 13789.743 | V15: =$B15*Inputs!$B$15*Inputs!$B$16*Curves!$E$14 -> 20709.758 | W15: =$B15*Inputs!$B$15*Inputs!$B$16*Curves!$E$15 -> 10850 | X15: =$B15*Inputs!$B$15*Inputs!$B$16*Curves!$E$16 -> 10850 | Y15: =$B15*Inputs!$B$15*Inputs!$B$16*Curves!$E$17 -> 10850 | Z15: =$B15*Inputs!$B$15*Inputs!$B$16*Curves!$E$18 -> 2712.5 | AA15: =$B15*Inputs!$B$15*Inputs!$B$16*Curves!$E$19 -> 2712.5 | AB15: =$B15*Inputs!$B$15*Inputs!$B$16*Curves!$E$20 -> 2712.5 | AC15: =$B15*Inputs!$B$15*Inputs!$B$16*Curves!$E$21 -> 2712.5 | AD15: =$B15*Inputs!$B$15*Inputs!$B$16*Curves!$E$22 -> 2712.5 | AE15: =$B15*Inputs!$B$15*Inputs!$B$16*Curves!$E$23 -> 2712.5 | AF15: =$B15*Inputs!$B$15*Inputs!$B$16*Curves!$E$24 -> 2712.5 | AG15: =$B15*Inputs!$B$15*Inputs!$B$16*Curves!$E$25 -> 2712.5 | AH15: =$B15*Inputs!$B$15*Inputs!$B$16*Curves!$E$26 -> 2712.5 | AI15: =$B15*Inputs!$B$15*Inputs!$B$16*Curves!$E$27 -> 2712.5 | AJ15: =$B15*Inputs!$B$15*Inputs!$B$16*Curves!$E$28 -> 2712.5 | AK15: =$B15*Inputs!$B$15*Inputs!$B$16*Curves!$E$29 -> 2712.5 | AL15: =$B15*Inputs!$B$15*Inputs!$B$16*Curves!$E$30 -> 2712.5
A16: =Acquisition_Plan!A15 -> 2026-12-28 | B16: =Acquisition_Plan!D15+Acquisition_Plan!F15+Acquisition_Plan!E15 -> 700000 | C16: 0 | D16: 0 | E16: 0 | F16: 0 | G16: 0 | H16: 0 | I16: 0 | J16: 0 | K16: 0 | L16: 0 | M16: 0 | N16: =$B16*Inputs!$B$15*Inputs!$B$16*Curves!$E$5 -> 74858.091 | O16: =$B16*Inputs!$B$15*Inputs!$B$16*Curves!$E$6 -> 82368.946 | P16: =$B16*Inputs!$B$15*Inputs!$B$16*Curves!$E$7 -> 46233.952 | Q16: =$B16*Inputs!$B$15*Inputs!$B$16*Curves!$E$8 -> 49891.082 | R16: =$B16*Inputs!$B$15*Inputs!$B$16*Curves!$E$9 -> 50133.5 | S16: =$B16*Inputs!$B$15*Inputs!$B$16*Curves!$E$10 -> 36924.104 | T16: =$B16*Inputs!$B$15*Inputs!$B$16*Curves!$E$11 -> 48607.431 | U16: =$B16*Inputs!$B$15*Inputs!$B$16*Curves!$E$12 -> 21333.394 | V16: =$B16*Inputs!$B$15*Inputs!$B$16*Curves!$E$13 -> 13789.743 | W16: =$B16*Inputs!$B$15*Inputs!$B$16*Curves!$E$14 -> 20709.758 | X16: =$B16*Inputs!$B$15*Inputs!$B$16*Curves!$E$15 -> 10850 | Y16: =$B16*Inputs!$B$15*Inputs!$B$16*Curves!$E$16 -> 10850 | Z16: =$B16*Inputs!$B$15*Inputs!$B$16*Curves!$E$17 -> 10850 | AA16: =$B16*Inputs!$B$15*Inputs!$B$16*Curves!$E$18 -> 2712.5 | AB16: =$B16*Inputs!$B$15*Inputs!$B$16*Curves!$E$19 -> 2712.5 | AC16: =$B16*Inputs!$B$15*Inputs!$B$16*Curves!$E$20 -> 2712.5 | AD16: =$B16*Inputs!$B$15*Inputs!$B$16*Curves!$E$21 -> 2712.5 | AE16: =$B16*Inputs!$B$15*Inputs!$B$16*Curves!$E$22 -> 2712.5 | AF16: =$B16*Inputs!$B$15*Inputs!$B$16*Curves!$E$23 -> 2712.5 | AG16: =$B16*Inputs!$B$15*Inputs!$B$16*Curves!$E$24 -> 2712.5 | AH16: =$B16*Inputs!$B$15*Inputs!$B$16*Curves!$E$25 -> 2712.5 | AI16: =$B16*Inputs!$B$15*Inputs!$B$16*Curves!$E$26 -> 2712.5 | AJ16: =$B16*Inputs!$B$15*Inputs!$B$16*Curves!$E$27 -> 2712.5 | AK16: =$B16*Inputs!$B$15*Inputs!$B$16*Curves!$E$28 -> 2712.5 | AL16: =$B16*Inputs!$B$15*Inputs!$B$16*Curves!$E$29 -> 2712.5
A17: =Acquisition_Plan!A16 -> 2027-01-27 | B17: =Acquisition_Plan!D16+Acquisition_Plan!F16+Acquisition_Plan!E16 -> 800000 | C17: 0 | D17: 0 | E17: 0 | F17: 0 | G17: 0 | H17: 0 | I17: 0 | J17: 0 | K17: 0 | L17: 0 | M17: 0 | N17: 0 | O17: =$B17*Inputs!$B$15*Inputs!$B$16*Curves!$E$5 -> 85552.104 | P17: =$B17*Inputs!$B$15*Inputs!$B$16*Curves!$E$6 -> 94135.938 | Q17: =$B17*Inputs!$B$15*Inputs!$B$16*Curves!$E$7 -> 52838.803 | R17: =$B17*Inputs!$B$15*Inputs!$B$16*Curves!$E$8 -> 57018.379 | S17: =$B17*Inputs!$B$15*Inputs!$B$16*Curves!$E$9 -> 57295.429 | T17: =$B17*Inputs!$B$15*Inputs!$B$16*Curves!$E$10 -> 42198.976 | U17: =$B17*Inputs!$B$15*Inputs!$B$16*Curves!$E$11 -> 55551.349 | V17: =$B17*Inputs!$B$15*Inputs!$B$16*Curves!$E$12 -> 24381.021 | W17: =$B17*Inputs!$B$15*Inputs!$B$16*Curves!$E$13 -> 15759.706 | X17: =$B17*Inputs!$B$15*Inputs!$B$16*Curves!$E$14 -> 23668.294 | Y17: =$B17*Inputs!$B$15*Inputs!$B$16*Curves!$E$15 -> 12400 | Z17: =$B17*Inputs!$B$15*Inputs!$B$16*Curves!$E$16 -> 12400 | AA17: =$B17*Inputs!$B$15*Inputs!$B$16*Curves!$E$17 -> 12400 | AB17: =$B17*Inputs!$B$15*Inputs!$B$16*Curves!$E$18 -> 3100 | AC17: =$B17*Inputs!$B$15*Inputs!$B$16*Curves!$E$19 -> 3100 | AD17: =$B17*Inputs!$B$15*Inputs!$B$16*Curves!$E$20 -> 3100 | AE17: =$B17*Inputs!$B$15*Inputs!$B$16*Curves!$E$21 -> 3100 | AF17: =$B17*Inputs!$B$15*Inputs!$B$16*Curves!$E$22 -> 3100 | AG17: =$B17*Inputs!$B$15*Inputs!$B$16*Curves!$E$23 -> 3100 | AH17: =$B17*Inputs!$B$15*Inputs!$B$16*Curves!$E$24 -> 3100 | AI17: =$B17*Inputs!$B$15*Inputs!$B$16*Curves!$E$25 -> 3100 | AJ17: =$B17*Inputs!$B$15*Inputs!$B$16*Curves!$E$26 -> 3100 | AK17: =$B17*Inputs!$B$15*Inputs!$B$16*Curves!$E$27 -> 3100 | AL17: =$B17*Inputs!$B$15*Inputs!$B$16*Curves!$E$28 -> 3100
A18: =Acquisition_Plan!A17 -> 2027-02-26 | B18: =Acquisition_Plan!D17+Acquisition_Plan!F17+Acquisition_Plan!E17 -> 800000 | C18: 0 | D18: 0 | E18: 0 | F18: 0 | G18: 0 | H18: 0 | I18: 0 | J18: 0 | K18: 0 | L18: 0 | M18: 0 | N18: 0 | O18: 0 | P18: =$B18*Inputs!$B$15*Inputs!$B$16*Curves!$E$5 -> 85552.104 | Q18: =$B18*Inputs!$B$15*Inputs!$B$16*Curves!$E$6 -> 94135.938 | R18: =$B18*Inputs!$B$15*Inputs!$B$16*Curves!$E$7 -> 52838.803 | S18: =$B18*Inputs!$B$15*Inputs!$B$16*Curves!$E$8 -> 57018.379 | T18: =$B18*Inputs!$B$15*Inputs!$B$16*Curves!$E$9 -> 57295.429 | U18: =$B18*Inputs!$B$15*Inputs!$B$16*Curves!$E$10 -> 42198.976 | V18: =$B18*Inputs!$B$15*Inputs!$B$16*Curves!$E$11 -> 55551.349 | W18: =$B18*Inputs!$B$15*Inputs!$B$16*Curves!$E$12 -> 24381.021 | X18: =$B18*Inputs!$B$15*Inputs!$B$16*Curves!$E$13 -> 15759.706 | Y18: =$B18*Inputs!$B$15*Inputs!$B$16*Curves!$E$14 -> 23668.294 | Z18: =$B18*Inputs!$B$15*Inputs!$B$16*Curves!$E$15 -> 12400 | AA18: =$B18*Inputs!$B$15*Inputs!$B$16*Curves!$E$16 -> 12400 | AB18: =$B18*Inputs!$B$15*Inputs!$B$16*Curves!$E$17 -> 12400 | AC18: =$B18*Inputs!$B$15*Inputs!$B$16*Curves!$E$18 -> 3100 | AD18: =$B18*Inputs!$B$15*Inputs!$B$16*Curves!$E$19 -> 3100 | AE18: =$B18*Inputs!$B$15*Inputs!$B$16*Curves!$E$20 -> 3100 | AF18: =$B18*Inputs!$B$15*Inputs!$B$16*Curves!$E$21 -> 3100 | AG18: =$B18*Inputs!$B$15*Inputs!$B$16*Curves!$E$22 -> 3100 | AH18: =$B18*Inputs!$B$15*Inputs!$B$16*Curves!$E$23 -> 3100 | AI18: =$B18*Inputs!$B$15*Inputs!$B$16*Curves!$E$24 -> 3100 | AJ18: =$B18*Inputs!$B$15*Inputs!$B$16*Curves!$E$25 -> 3100 | AK18: =$B18*Inputs!$B$15*Inputs!$B$16*Curves!$E$26 -> 3100 | AL18: =$B18*Inputs!$B$15*Inputs!$B$16*Curves!$E$27 -> 3100
A19: =Acquisition_Plan!A18 -> 2027-03-28 | B19: =Acquisition_Plan!D18+Acquisition_Plan!F18+Acquisition_Plan!E18 -> 800000 | C19: 0 | D19: 0 | E19: 0 | F19: 0 | G19: 0 | H19: 0 | I19: 0 | J19: 0 | K19: 0 | L19: 0 | M19: 0 | N19: 0 | O19: 0 | P19: 0 | Q19: =$B19*Inputs!$B$15*Inputs!$B$16*Curves!$E$5 -> 85552.104 | R19: =$B19*Inputs!$B$15*Inputs!$B$16*Curves!$E$6 -> 94135.938 | S19: =$B19*Inputs!$B$15*Inputs!$B$16*Curves!$E$7 -> 52838.803 | T19: =$B19*Inputs!$B$15*Inputs!$B$16*Curves!$E$8 -> 57018.379 | U19: =$B19*Inputs!$B$15*Inputs!$B$16*Curves!$E$9 -> 57295.429 | V19: =$B19*Inputs!$B$15*Inputs!$B$16*Curves!$E$10 -> 42198.976 | W19: =$B19*Inputs!$B$15*Inputs!$B$16*Curves!$E$11 -> 55551.349 | X19: =$B19*Inputs!$B$15*Inputs!$B$16*Curves!$E$12 -> 24381.021 | Y19: =$B19*Inputs!$B$15*Inputs!$B$16*Curves!$E$13 -> 15759.706 | Z19: =$B19*Inputs!$B$15*Inputs!$B$16*Curves!$E$14 -> 23668.294 | AA19: =$B19*Inputs!$B$15*Inputs!$B$16*Curves!$E$15 -> 12400 | AB19: =$B19*Inputs!$B$15*Inputs!$B$16*Curves!$E$16 -> 12400 | AC19: =$B19*Inputs!$B$15*Inputs!$B$16*Curves!$E$17 -> 12400 | AD19: =$B19*Inputs!$B$15*Inputs!$B$16*Curves!$E$18 -> 3100 | AE19: =$B19*Inputs!$B$15*Inputs!$B$16*Curves!$E$19 -> 3100 | AF19: =$B19*Inputs!$B$15*Inputs!$B$16*Curves!$E$20 -> 3100 | AG19: =$B19*Inputs!$B$15*Inputs!$B$16*Curves!$E$21 -> 3100 | AH19: =$B19*Inputs!$B$15*Inputs!$B$16*Curves!$E$22 -> 3100 | AI19: =$B19*Inputs!$B$15*Inputs!$B$16*Curves!$E$23 -> 3100 | AJ19: =$B19*Inputs!$B$15*Inputs!$B$16*Curves!$E$24 -> 3100 | AK19: =$B19*Inputs!$B$15*Inputs!$B$16*Curves!$E$25 -> 3100 | AL19: =$B19*Inputs!$B$15*Inputs!$B$16*Curves!$E$26 -> 3100
A20: =Acquisition_Plan!A19 -> 2027-04-27 | B20: =Acquisition_Plan!D19+Acquisition_Plan!F19+Acquisition_Plan!E19 -> 800000 | C20: 0 | D20: 0 | E20: 0 | F20: 0 | G20: 0 | H20: 0 | I20: 0 | J20: 0 | K20: 0 | L20: 0 | M20: 0 | N20: 0 | O20: 0 | P20: 0 | Q20: 0 | R20: =$B20*Inputs!$B$15*Inputs!$B$16*Curves!$E$5 -> 85552.104 | S20: =$B20*Inputs!$B$15*Inputs!$B$16*Curves!$E$6 -> 94135.938 | T20: =$B20*Inputs!$B$15*Inputs!$B$16*Curves!$E$7 -> 52838.803 | U20: =$B20*Inputs!$B$15*Inputs!$B$16*Curves!$E$8 -> 57018.379 | V20: =$B20*Inputs!$B$15*Inputs!$B$16*Curves!$E$9 -> 57295.429 | W20: =$B20*Inputs!$B$15*Inputs!$B$16*Curves!$E$10 -> 42198.976 | X20: =$B20*Inputs!$B$15*Inputs!$B$16*Curves!$E$11 -> 55551.349 | Y20: =$B20*Inputs!$B$15*Inputs!$B$16*Curves!$E$12 -> 24381.021 | Z20: =$B20*Inputs!$B$15*Inputs!$B$16*Curves!$E$13 -> 15759.706 | AA20: =$B20*Inputs!$B$15*Inputs!$B$16*Curves!$E$14 -> 23668.294 | AB20: =$B20*Inputs!$B$15*Inputs!$B$16*Curves!$E$15 -> 12400 | AC20: =$B20*Inputs!$B$15*Inputs!$B$16*Curves!$E$16 -> 12400 | AD20: =$B20*Inputs!$B$15*Inputs!$B$16*Curves!$E$17 -> 12400 | AE20: =$B20*Inputs!$B$15*Inputs!$B$16*Curves!$E$18 -> 3100 | AF20: =$B20*Inputs!$B$15*Inputs!$B$16*Curves!$E$19 -> 3100 | AG20: =$B20*Inputs!$B$15*Inputs!$B$16*Curves!$E$20 -> 3100 | AH20: =$B20*Inputs!$B$15*Inputs!$B$16*Curves!$E$21 -> 3100 | AI20: =$B20*Inputs!$B$15*Inputs!$B$16*Curves!$E$22 -> 3100 | AJ20: =$B20*Inputs!$B$15*Inputs!$B$16*Curves!$E$23 -> 3100 | AK20: =$B20*Inputs!$B$15*Inputs!$B$16*Curves!$E$24 -> 3100 | AL20: =$B20*Inputs!$B$15*Inputs!$B$16*Curves!$E$25 -> 3100
A21: =Acquisition_Plan!A20 -> 2027-05-27 | B21: =Acquisition_Plan!D20+Acquisition_Plan!F20+Acquisition_Plan!E20 -> 800000 | C21: 0 | D21: 0 | E21: 0 | F21: 0 | G21: 0 | H21: 0 | I21: 0 | J21: 0 | K21: 0 | L21: 0 | M21: 0 | N21: 0 | O21: 0 | P21: 0 | Q21: 0 | R21: 0 | S21: =$B21*Inputs!$B$15*Inputs!$B$16*Curves!$E$5 -> 85552.104 | T21: =$B21*Inputs!$B$15*Inputs!$B$16*Curves!$E$6 -> 94135.938 | U21: =$B21*Inputs!$B$15*Inputs!$B$16*Curves!$E$7 -> 52838.803 | V21: =$B21*Inputs!$B$15*Inputs!$B$16*Curves!$E$8 -> 57018.379 | W21: =$B21*Inputs!$B$15*Inputs!$B$16*Curves!$E$9 -> 57295.429 | X21: =$B21*Inputs!$B$15*Inputs!$B$16*Curves!$E$10 -> 42198.976 | Y21: =$B21*Inputs!$B$15*Inputs!$B$16*Curves!$E$11 -> 55551.349 | Z21: =$B21*Inputs!$B$15*Inputs!$B$16*Curves!$E$12 -> 24381.021 | AA21: =$B21*Inputs!$B$15*Inputs!$B$16*Curves!$E$13 -> 15759.706 | AB21: =$B21*Inputs!$B$15*Inputs!$B$16*Curves!$E$14 -> 23668.294 | AC21: =$B21*Inputs!$B$15*Inputs!$B$16*Curves!$E$15 -> 12400 | AD21: =$B21*Inputs!$B$15*Inputs!$B$16*Curves!$E$16 -> 12400 | AE21: =$B21*Inputs!$B$15*Inputs!$B$16*Curves!$E$17 -> 12400 | AF21: =$B21*Inputs!$B$15*Inputs!$B$16*Curves!$E$18 -> 3100 | AG21: =$B21*Inputs!$B$15*Inputs!$B$16*Curves!$E$19 -> 3100 | AH21: =$B21*Inputs!$B$15*Inputs!$B$16*Curves!$E$20 -> 3100 | AI21: =$B21*Inputs!$B$15*Inputs!$B$16*Curves!$E$21 -> 3100 | AJ21: =$B21*Inputs!$B$15*Inputs!$B$16*Curves!$E$22 -> 3100 | AK21: =$B21*Inputs!$B$15*Inputs!$B$16*Curves!$E$23 -> 3100 | AL21: =$B21*Inputs!$B$15*Inputs!$B$16*Curves!$E$24 -> 3100
A22: =Acquisition_Plan!A21 -> 2027-06-26 | B22: =Acquisition_Plan!D21+Acquisition_Plan!F21+Acquisition_Plan!E21 -> 800000 | C22: 0 | D22: 0 | E22: 0 | F22: 0 | G22: 0 | H22: 0 | I22: 0 | J22: 0 | K22: 0 | L22: 0 | M22: 0 | N22: 0 | O22: 0 | P22: 0 | Q22: 0 | R22: 0 | S22: 0 | T22: =$B22*Inputs!$B$15*Inputs!$B$16*Curves!$E$5 -> 85552.104 | U22: =$B22*Inputs!$B$15*Inputs!$B$16*Curves!$E$6 -> 94135.938 | V22: =$B22*Inputs!$B$15*Inputs!$B$16*Curves!$E$7 -> 52838.803 | W22: =$B22*Inputs!$B$15*Inputs!$B$16*Curves!$E$8 -> 57018.379 | X22: =$B22*Inputs!$B$15*Inputs!$B$16*Curves!$E$9 -> 57295.429 | Y22: =$B22*Inputs!$B$15*Inputs!$B$16*Curves!$E$10 -> 42198.976 | Z22: =$B22*Inputs!$B$15*Inputs!$B$16*Curves!$E$11 -> 55551.349 | AA22: =$B22*Inputs!$B$15*Inputs!$B$16*Curves!$E$12 -> 24381.021 | AB22: =$B22*Inputs!$B$15*Inputs!$B$16*Curves!$E$13 -> 15759.706 | AC22: =$B22*Inputs!$B$15*Inputs!$B$16*Curves!$E$14 -> 23668.294 | AD22: =$B22*Inputs!$B$15*Inputs!$B$16*Curves!$E$15 -> 12400 | AE22: =$B22*Inputs!$B$15*Inputs!$B$16*Curves!$E$16 -> 12400 | AF22: =$B22*Inputs!$B$15*Inputs!$B$16*Curves!$E$17 -> 12400 | AG22: =$B22*Inputs!$B$15*Inputs!$B$16*Curves!$E$18 -> 3100 | AH22: =$B22*Inputs!$B$15*Inputs!$B$16*Curves!$E$19 -> 3100 | AI22: =$B22*Inputs!$B$15*Inputs!$B$16*Curves!$E$20 -> 3100 | AJ22: =$B22*Inputs!$B$15*Inputs!$B$16*Curves!$E$21 -> 3100 | AK22: =$B22*Inputs!$B$15*Inputs!$B$16*Curves!$E$22 -> 3100 | AL22: =$B22*Inputs!$B$15*Inputs!$B$16*Curves!$E$23 -> 3100
A23: =Acquisition_Plan!A22 -> 2027-07-26 | B23: =Acquisition_Plan!D22+Acquisition_Plan!F22+Acquisition_Plan!E22 -> 800000 | C23: 0 | D23: 0 | E23: 0 | F23: 0 | G23: 0 | H23: 0 | I23: 0 | J23: 0 | K23: 0 | L23: 0 | M23: 0 | N23: 0 | O23: 0 | P23: 0 | Q23: 0 | R23: 0 | S23: 0 | T23: 0 | U23: =$B23*Inputs!$B$15*Inputs!$B$16*Curves!$E$5 -> 85552.104 | V23: =$B23*Inputs!$B$15*Inputs!$B$16*Curves!$E$6 -> 94135.938 | W23: =$B23*Inputs!$B$15*Inputs!$B$16*Curves!$E$7 -> 52838.803 | X23: =$B23*Inputs!$B$15*Inputs!$B$16*Curves!$E$8 -> 57018.379 | Y23: =$B23*Inputs!$B$15*Inputs!$B$16*Curves!$E$9 -> 57295.429 | Z23: =$B23*Inputs!$B$15*Inputs!$B$16*Curves!$E$10 -> 42198.976 | AA23: =$B23*Inputs!$B$15*Inputs!$B$16*Curves!$E$11 -> 55551.349 | AB23: =$B23*Inputs!$B$15*Inputs!$B$16*Curves!$E$12 -> 24381.021 | AC23: =$B23*Inputs!$B$15*Inputs!$B$16*Curves!$E$13 -> 15759.706 | AD23: =$B23*Inputs!$B$15*Inputs!$B$16*Curves!$E$14 -> 23668.294 | AE23: =$B23*Inputs!$B$15*Inputs!$B$16*Curves!$E$15 -> 12400 | AF23: =$B23*Inputs!$B$15*Inputs!$B$16*Curves!$E$16 -> 12400 | AG23: =$B23*Inputs!$B$15*Inputs!$B$16*Curves!$E$17 -> 12400 | AH23: =$B23*Inputs!$B$15*Inputs!$B$16*Curves!$E$18 -> 3100 | AI23: =$B23*Inputs!$B$15*Inputs!$B$16*Curves!$E$19 -> 3100 | AJ23: =$B23*Inputs!$B$15*Inputs!$B$16*Curves!$E$20 -> 3100 | AK23: =$B23*Inputs!$B$15*Inputs!$B$16*Curves!$E$21 -> 3100 | AL23: =$B23*Inputs!$B$15*Inputs!$B$16*Curves!$E$22 -> 3100
A24: =Acquisition_Plan!A23 -> 2027-08-25 | B24: =Acquisition_Plan!D23+Acquisition_Plan!F23+Acquisition_Plan!E23 -> 800000 | C24: 0 | D24: 0 | E24: 0 | F24: 0 | G24: 0 | H24: 0 | I24: 0 | J24: 0 | K24: 0 | L24: 0 | M24: 0 | N24: 0 | O24: 0 | P24: 0 | Q24: 0 | R24: 0 | S24: 0 | T24: 0 | U24: 0 | V24: =$B24*Inputs!$B$15*Inputs!$B$16*Curves!$E$5 -> 85552.104 | W24: =$B24*Inputs!$B$15*Inputs!$B$16*Curves!$E$6 -> 94135.938 | X24: =$B24*Inputs!$B$15*Inputs!$B$16*Curves!$E$7 -> 52838.803 | Y24: =$B24*Inputs!$B$15*Inputs!$B$16*Curves!$E$8 -> 57018.379 | Z24: =$B24*Inputs!$B$15*Inputs!$B$16*Curves!$E$9 -> 57295.429 | AA24: =$B24*Inputs!$B$15*Inputs!$B$16*Curves!$E$10 -> 42198.976 | AB24: =$B24*Inputs!$B$15*Inputs!$B$16*Curves!$E$11 -> 55551.349 | AC24: =$B24*Inputs!$B$15*Inputs!$B$16*Curves!$E$12 -> 24381.021 | AD24: =$B24*Inputs!$B$15*Inputs!$B$16*Curves!$E$13 -> 15759.706 | AE24: =$B24*Inputs!$B$15*Inputs!$B$16*Curves!$E$14 -> 23668.294 | AF24: =$B24*Inputs!$B$15*Inputs!$B$16*Curves!$E$15 -> 12400 | AG24: =$B24*Inputs!$B$15*Inputs!$B$16*Curves!$E$16 -> 12400 | AH24: =$B24*Inputs!$B$15*Inputs!$B$16*Curves!$E$17 -> 12400 | AI24: =$B24*Inputs!$B$15*Inputs!$B$16*Curves!$E$18 -> 3100 | AJ24: =$B24*Inputs!$B$15*Inputs!$B$16*Curves!$E$19 -> 3100 | AK24: =$B24*Inputs!$B$15*Inputs!$B$16*Curves!$E$20 -> 3100 | AL24: =$B24*Inputs!$B$15*Inputs!$B$16*Curves!$E$21 -> 3100
A25: =Acquisition_Plan!A24 -> 2027-09-24 | B25: =Acquisition_Plan!D24+Acquisition_Plan!F24+Acquisition_Plan!E24 -> 800000 | C25: 0 | D25: 0 | E25: 0 | F25: 0 | G25: 0 | H25: 0 | I25: 0 | J25: 0 | K25: 0 | L25: 0 | M25: 0 | N25: 0 | O25: 0 | P25: 0 | Q25: 0 | R25: 0 | S25: 0 | T25: 0 | U25: 0 | V25: 0 | W25: =$B25*Inputs!$B$15*Inputs!$B$16*Curves!$E$5 -> 85552.104 | X25: =$B25*Inputs!$B$15*Inputs!$B$16*Curves!$E$6 -> 94135.938 | Y25: =$B25*Inputs!$B$15*Inputs!$B$16*Curves!$E$7 -> 52838.803 | Z25: =$B25*Inputs!$B$15*Inputs!$B$16*Curves!$E$8 -> 57018.379 | AA25: =$B25*Inputs!$B$15*Inputs!$B$16*Curves!$E$9 -> 57295.429 | AB25: =$B25*Inputs!$B$15*Inputs!$B$16*Curves!$E$10 -> 42198.976 | AC25: =$B25*Inputs!$B$15*Inputs!$B$16*Curves!$E$11 -> 55551.349 | AD25: =$B25*Inputs!$B$15*Inputs!$B$16*Curves!$E$12 -> 24381.021 | AE25: =$B25*Inputs!$B$15*Inputs!$B$16*Curves!$E$13 -> 15759.706 | AF25: =$B25*Inputs!$B$15*Inputs!$B$16*Curves!$E$14 -> 23668.294 | AG25: =$B25*Inputs!$B$15*Inputs!$B$16*Curves!$E$15 -> 12400 | AH25: =$B25*Inputs!$B$15*Inputs!$B$16*Curves!$E$16 -> 12400 | AI25: =$B25*Inputs!$B$15*Inputs!$B$16*Curves!$E$17 -> 12400 | AJ25: =$B25*Inputs!$B$15*Inputs!$B$16*Curves!$E$18 -> 3100 | AK25: =$B25*Inputs!$B$15*Inputs!$B$16*Curves!$E$19 -> 3100 | AL25: =$B25*Inputs!$B$15*Inputs!$B$16*Curves!$E$20 -> 3100
A26: =Acquisition_Plan!A25 -> 2027-10-24 | B26: =Acquisition_Plan!D25+Acquisition_Plan!F25+Acquisition_Plan!E25 -> 800000 | C26: 0 | D26: 0 | E26: 0 | F26: 0 | G26: 0 | H26: 0 | I26: 0 | J26: 0 | K26: 0 | L26: 0 | M26: 0 | N26: 0 | O26: 0 | P26: 0 | Q26: 0 | R26: 0 | S26: 0 | T26: 0 | U26: 0 | V26: 0 | W26: 0 | X26: =$B26*Inputs!$B$15*Inputs!$B$16*Curves!$E$5 -> 85552.104 | Y26: =$B26*Inputs!$B$15*Inputs!$B$16*Curves!$E$6 -> 94135.938 | Z26: =$B26*Inputs!$B$15*Inputs!$B$16*Curves!$E$7 -> 52838.803 | AA26: =$B26*Inputs!$B$15*Inputs!$B$16*Curves!$E$8 -> 57018.379 | AB26: =$B26*Inputs!$B$15*Inputs!$B$16*Curves!$E$9 -> 57295.429 | AC26: =$B26*Inputs!$B$15*Inputs!$B$16*Curves!$E$10 -> 42198.976 | AD26: =$B26*Inputs!$B$15*Inputs!$B$16*Curves!$E$11 -> 55551.349 | AE26: =$B26*Inputs!$B$15*Inputs!$B$16*Curves!$E$12 -> 24381.021 | AF26: =$B26*Inputs!$B$15*Inputs!$B$16*Curves!$E$13 -> 15759.706 | AG26: =$B26*Inputs!$B$15*Inputs!$B$16*Curves!$E$14 -> 23668.294 | AH26: =$B26*Inputs!$B$15*Inputs!$B$16*Curves!$E$15 -> 12400 | AI26: =$B26*Inputs!$B$15*Inputs!$B$16*Curves!$E$16 -> 12400 | AJ26: =$B26*Inputs!$B$15*Inputs!$B$16*Curves!$E$17 -> 12400 | AK26: =$B26*Inputs!$B$15*Inputs!$B$16*Curves!$E$18 -> 3100 | AL26: =$B26*Inputs!$B$15*Inputs!$B$16*Curves!$E$19 -> 3100
A27: =Acquisition_Plan!A26 -> 2027-11-23 | B27: =Acquisition_Plan!D26+Acquisition_Plan!F26+Acquisition_Plan!E26 -> 800000 | C27: 0 | D27: 0 | E27: 0 | F27: 0 | G27: 0 | H27: 0 | I27: 0 | J27: 0 | K27: 0 | L27: 0 | M27: 0 | N27: 0 | O27: 0 | P27: 0 | Q27: 0 | R27: 0 | S27: 0 | T27: 0 | U27: 0 | V27: 0 | W27: 0 | X27: 0 | Y27: =$B27*Inputs!$B$15*Inputs!$B$16*Curves!$E$5 -> 85552.104 | Z27: =$B27*Inputs!$B$15*Inputs!$B$16*Curves!$E$6 -> 94135.938 | AA27: =$B27*Inputs!$B$15*Inputs!$B$16*Curves!$E$7 -> 52838.803 | AB27: =$B27*Inputs!$B$15*Inputs!$B$16*Curves!$E$8 -> 57018.379 | AC27: =$B27*Inputs!$B$15*Inputs!$B$16*Curves!$E$9 -> 57295.429 | AD27: =$B27*Inputs!$B$15*Inputs!$B$16*Curves!$E$10 -> 42198.976 | AE27: =$B27*Inputs!$B$15*Inputs!$B$16*Curves!$E$11 -> 55551.349 | AF27: =$B27*Inputs!$B$15*Inputs!$B$16*Curves!$E$12 -> 24381.021 | AG27: =$B27*Inputs!$B$15*Inputs!$B$16*Curves!$E$13 -> 15759.706 | AH27: =$B27*Inputs!$B$15*Inputs!$B$16*Curves!$E$14 -> 23668.294 | AI27: =$B27*Inputs!$B$15*Inputs!$B$16*Curves!$E$15 -> 12400 | AJ27: =$B27*Inputs!$B$15*Inputs!$B$16*Curves!$E$16 -> 12400 | AK27: =$B27*Inputs!$B$15*Inputs!$B$16*Curves!$E$17 -> 12400 | AL27: =$B27*Inputs!$B$15*Inputs!$B$16*Curves!$E$18 -> 3100
A28: =Acquisition_Plan!A27 -> 2027-12-23 | B28: =Acquisition_Plan!D27+Acquisition_Plan!F27+Acquisition_Plan!E27 -> 800000 | C28: 0 | D28: 0 | E28: 0 | F28: 0 | G28: 0 | H28: 0 | I28: 0 | J28: 0 | K28: 0 | L28: 0 | M28: 0 | N28: 0 | O28: 0 | P28: 0 | Q28: 0 | R28: 0 | S28: 0 | T28: 0 | U28: 0 | V28: 0 | W28: 0 | X28: 0 | Y28: 0 | Z28: =$B28*Inputs!$B$15*Inputs!$B$16*Curves!$E$5 -> 85552.104 | AA28: =$B28*Inputs!$B$15*Inputs!$B$16*Curves!$E$6 -> 94135.938 | AB28: =$B28*Inputs!$B$15*Inputs!$B$16*Curves!$E$7 -> 52838.803 | AC28: =$B28*Inputs!$B$15*Inputs!$B$16*Curves!$E$8 -> 57018.379 | AD28: =$B28*Inputs!$B$15*Inputs!$B$16*Curves!$E$9 -> 57295.429 | AE28: =$B28*Inputs!$B$15*Inputs!$B$16*Curves!$E$10 -> 42198.976 | AF28: =$B28*Inputs!$B$15*Inputs!$B$16*Curves!$E$11 -> 55551.349 | AG28: =$B28*Inputs!$B$15*Inputs!$B$16*Curves!$E$12 -> 24381.021 | AH28: =$B28*Inputs!$B$15*Inputs!$B$16*Curves!$E$13 -> 15759.706 | AI28: =$B28*Inputs!$B$15*Inputs!$B$16*Curves!$E$14 -> 23668.294 | AJ28: =$B28*Inputs!$B$15*Inputs!$B$16*Curves!$E$15 -> 12400 | AK28: =$B28*Inputs!$B$15*Inputs!$B$16*Curves!$E$16 -> 12400 | AL28: =$B28*Inputs!$B$15*Inputs!$B$16*Curves!$E$17 -> 12400
A29: =Acquisition_Plan!A28 -> 2028-01-22 | B29: =Acquisition_Plan!D28+Acquisition_Plan!F28+Acquisition_Plan!E28 -> 800000 | C29: 0 | D29: 0 | E29: 0 | F29: 0 | G29: 0 | H29: 0 | I29: 0 | J29: 0 | K29: 0 | L29: 0 | M29: 0 | N29: 0 | O29: 0 | P29: 0 | Q29: 0 | R29: 0 | S29: 0 | T29: 0 | U29: 0 | V29: 0 | W29: 0 | X29: 0 | Y29: 0 | Z29: 0 | AA29: =$B29*Inputs!$B$15*Inputs!$B$16*Curves!$E$5 -> 85552.104 | AB29: =$B29*Inputs!$B$15*Inputs!$B$16*Curves!$E$6 -> 94135.938 | AC29: =$B29*Inputs!$B$15*Inputs!$B$16*Curves!$E$7 -> 52838.803 | AD29: =$B29*Inputs!$B$15*Inputs!$B$16*Curves!$E$8 -> 57018.379 | AE29: =$B29*Inputs!$B$15*Inputs!$B$16*Curves!$E$9 -> 57295.429 | AF29: =$B29*Inputs!$B$15*Inputs!$B$16*Curves!$E$10 -> 42198.976 | AG29: =$B29*Inputs!$B$15*Inputs!$B$16*Curves!$E$11 -> 55551.349 | AH29: =$B29*Inputs!$B$15*Inputs!$B$16*Curves!$E$12 -> 24381.021 | AI29: =$B29*Inputs!$B$15*Inputs!$B$16*Curves!$E$13 -> 15759.706 | AJ29: =$B29*Inputs!$B$15*Inputs!$B$16*Curves!$E$14 -> 23668.294 | AK29: =$B29*Inputs!$B$15*Inputs!$B$16*Curves!$E$15 -> 12400 | AL29: =$B29*Inputs!$B$15*Inputs!$B$16*Curves!$E$16 -> 12400
A30: =Acquisition_Plan!A29 -> 2028-02-21 | B30: =Acquisition_Plan!D29+Acquisition_Plan!F29+Acquisition_Plan!E29 -> 800000 | C30: 0 | D30: 0 | E30: 0 | F30: 0 | G30: 0 | H30: 0 | I30: 0 | J30: 0 | K30: 0 | L30: 0 | M30: 0 | N30: 0 | O30: 0 | P30: 0 | Q30: 0 | R30: 0 | S30: 0 | T30: 0 | U30: 0 | V30: 0 | W30: 0 | X30: 0 | Y30: 0 | Z30: 0 | AA30: 0 | AB30: =$B30*Inputs!$B$15*Inputs!$B$16*Curves!$E$5 -> 85552.104 | AC30: =$B30*Inputs!$B$15*Inputs!$B$16*Curves!$E$6 -> 94135.938 | AD30: =$B30*Inputs!$B$15*Inputs!$B$16*Curves!$E$7 -> 52838.803 | AE30: =$B30*Inputs!$B$15*Inputs!$B$16*Curves!$E$8 -> 57018.379 | AF30: =$B30*Inputs!$B$15*Inputs!$B$16*Curves!$E$9 -> 57295.429 | AG30: =$B30*Inputs!$B$15*Inputs!$B$16*Curves!$E$10 -> 42198.976 | AH30: =$B30*Inputs!$B$15*Inputs!$B$16*Curves!$E$11 -> 55551.349 | AI30: =$B30*Inputs!$B$15*Inputs!$B$16*Curves!$E$12 -> 24381.021 | AJ30: =$B30*Inputs!$B$15*Inputs!$B$16*Curves!$E$13 -> 15759.706 | AK30: =$B30*Inputs!$B$15*Inputs!$B$16*Curves!$E$14 -> 23668.294 | AL30: =$B30*Inputs!$B$15*Inputs!$B$16*Curves!$E$15 -> 12400
A31: =Acquisition_Plan!A30 -> 2028-03-22 | B31: =Acquisition_Plan!D30+Acquisition_Plan!F30+Acquisition_Plan!E30 -> 800000 | C31: 0 | D31: 0 | E31: 0 | F31: 0 | G31: 0 | H31: 0 | I31: 0 | J31: 0 | K31: 0 | L31: 0 | M31: 0 | N31: 0 | O31: 0 | P31: 0 | Q31: 0 | R31: 0 | S31: 0 | T31: 0 | U31: 0 | V31: 0 | W31: 0 | X31: 0 | Y31: 0 | Z31: 0 | AA31: 0 | AB31: 0 | AC31: =$B31*Inputs!$B$15*Inputs!$B$16*Curves!$E$5 -> 85552.104 | AD31: =$B31*Inputs!$B$15*Inputs!$B$16*Curves!$E$6 -> 94135.938 | AE31: =$B31*Inputs!$B$15*Inputs!$B$16*Curves!$E$7 -> 52838.803 | AF31: =$B31*Inputs!$B$15*Inputs!$B$16*Curves!$E$8 -> 57018.379 | AG31: =$B31*Inputs!$B$15*Inputs!$B$16*Curves!$E$9 -> 57295.429 | AH31: =$B31*Inputs!$B$15*Inputs!$B$16*Curves!$E$10 -> 42198.976 | AI31: =$B31*Inputs!$B$15*Inputs!$B$16*Curves!$E$11 -> 55551.349 | AJ31: =$B31*Inputs!$B$15*Inputs!$B$16*Curves!$E$12 -> 24381.021 | AK31: =$B31*Inputs!$B$15*Inputs!$B$16*Curves!$E$13 -> 15759.706 | AL31: =$B31*Inputs!$B$15*Inputs!$B$16*Curves!$E$14 -> 23668.294
A32: =Acquisition_Plan!A31 -> 2028-04-21 | B32: =Acquisition_Plan!D31+Acquisition_Plan!F31+Acquisition_Plan!E31 -> 800000 | C32: 0 | D32: 0 | E32: 0 | F32: 0 | G32: 0 | H32: 0 | I32: 0 | J32: 0 | K32: 0 | L32: 0 | M32: 0 | N32: 0 | O32: 0 | P32: 0 | Q32: 0 | R32: 0 | S32: 0 | T32: 0 | U32: 0 | V32: 0 | W32: 0 | X32: 0 | Y32: 0 | Z32: 0 | AA32: 0 | AB32: 0 | AC32: 0 | AD32: =$B32*Inputs!$B$15*Inputs!$B$16*Curves!$E$5 -> 85552.104 | AE32: =$B32*Inputs!$B$15*Inputs!$B$16*Curves!$E$6 -> 94135.938 | AF32: =$B32*Inputs!$B$15*Inputs!$B$16*Curves!$E$7 -> 52838.803 | AG32: =$B32*Inputs!$B$15*Inputs!$B$16*Curves!$E$8 -> 57018.379 | AH32: =$B32*Inputs!$B$15*Inputs!$B$16*Curves!$E$9 -> 57295.429 | AI32: =$B32*Inputs!$B$15*Inputs!$B$16*Curves!$E$10 -> 42198.976 | AJ32: =$B32*Inputs!$B$15*Inputs!$B$16*Curves!$E$11 -> 55551.349 | AK32: =$B32*Inputs!$B$15*Inputs!$B$16*Curves!$E$12 -> 24381.021 | AL32: =$B32*Inputs!$B$15*Inputs!$B$16*Curves!$E$13 -> 15759.706
A33: =Acquisition_Plan!A32 -> 2028-05-21 | B33: =Acquisition_Plan!D32+Acquisition_Plan!F32+Acquisition_Plan!E32 -> 800000 | C33: 0 | D33: 0 | E33: 0 | F33: 0 | G33: 0 | H33: 0 | I33: 0 | J33: 0 | K33: 0 | L33: 0 | M33: 0 | N33: 0 | O33: 0 | P33: 0 | Q33: 0 | R33: 0 | S33: 0 | T33: 0 | U33: 0 | V33: 0 | W33: 0 | X33: 0 | Y33: 0 | Z33: 0 | AA33: 0 | AB33: 0 | AC33: 0 | AD33: 0 | AE33: =$B33*Inputs!$B$15*Inputs!$B$16*Curves!$E$5 -> 85552.104 | AF33: =$B33*Inputs!$B$15*Inputs!$B$16*Curves!$E$6 -> 94135.938 | AG33: =$B33*Inputs!$B$15*Inputs!$B$16*Curves!$E$7 -> 52838.803 | AH33: =$B33*Inputs!$B$15*Inputs!$B$16*Curves!$E$8 -> 57018.379 | AI33: =$B33*Inputs!$B$15*Inputs!$B$16*Curves!$E$9 -> 57295.429 | AJ33: =$B33*Inputs!$B$15*Inputs!$B$16*Curves!$E$10 -> 42198.976 | AK33: =$B33*Inputs!$B$15*Inputs!$B$16*Curves!$E$11 -> 55551.349 | AL33: =$B33*Inputs!$B$15*Inputs!$B$16*Curves!$E$12 -> 24381.021
A34: =Acquisition_Plan!A33 -> 2028-06-20 | B34: =Acquisition_Plan!D33+Acquisition_Plan!F33+Acquisition_Plan!E33 -> 800000 | C34: 0 | D34: 0 | E34: 0 | F34: 0 | G34: 0 | H34: 0 | I34: 0 | J34: 0 | K34: 0 | L34: 0 | M34: 0 | N34: 0 | O34: 0 | P34: 0 | Q34: 0 | R34: 0 | S34: 0 | T34: 0 | U34: 0 | V34: 0 | W34: 0 | X34: 0 | Y34: 0 | Z34: 0 | AA34: 0 | AB34: 0 | AC34: 0 | AD34: 0 | AE34: 0 | AF34: =$B34*Inputs!$B$15*Inputs!$B$16*Curves!$E$5 -> 85552.104 | AG34: =$B34*Inputs!$B$15*Inputs!$B$16*Curves!$E$6 -> 94135.938 | AH34: =$B34*Inputs!$B$15*Inputs!$B$16*Curves!$E$7 -> 52838.803 | AI34: =$B34*Inputs!$B$15*Inputs!$B$16*Curves!$E$8 -> 57018.379 | AJ34: =$B34*Inputs!$B$15*Inputs!$B$16*Curves!$E$9 -> 57295.429 | AK34: =$B34*Inputs!$B$15*Inputs!$B$16*Curves!$E$10 -> 42198.976 | AL34: =$B34*Inputs!$B$15*Inputs!$B$16*Curves!$E$11 -> 55551.349
A35: =Acquisition_Plan!A34 -> 2028-07-20 | B35: =Acquisition_Plan!D34+Acquisition_Plan!F34+Acquisition_Plan!E34 -> 800000 | C35: 0 | D35: 0 | E35: 0 | F35: 0 | G35: 0 | H35: 0 | I35: 0 | J35: 0 | K35: 0 | L35: 0 | M35: 0 | N35: 0 | O35: 0 | P35: 0 | Q35: 0 | R35: 0 | S35: 0 | T35: 0 | U35: 0 | V35: 0 | W35: 0 | X35: 0 | Y35: 0 | Z35: 0 | AA35: 0 | AB35: 0 | AC35: 0 | AD35: 0 | AE35: 0 | AF35: 0 | AG35: =$B35*Inputs!$B$15*Inputs!$B$16*Curves!$E$5 -> 85552.104 | AH35: =$B35*Inputs!$B$15*Inputs!$B$16*Curves!$E$6 -> 94135.938 | AI35: =$B35*Inputs!$B$15*Inputs!$B$16*Curves!$E$7 -> 52838.803 | AJ35: =$B35*Inputs!$B$15*Inputs!$B$16*Curves!$E$8 -> 57018.379 | AK35: =$B35*Inputs!$B$15*Inputs!$B$16*Curves!$E$9 -> 57295.429 | AL35: =$B35*Inputs!$B$15*Inputs!$B$16*Curves!$E$10 -> 42198.976
A36: =Acquisition_Plan!A35 -> 2028-08-19 | B36: =Acquisition_Plan!D35+Acquisition_Plan!F35+Acquisition_Plan!E35 -> 800000 | C36: 0 | D36: 0 | E36: 0 | F36: 0 | G36: 0 | H36: 0 | I36: 0 | J36: 0 | K36: 0 | L36: 0 | M36: 0 | N36: 0 | O36: 0 | P36: 0 | Q36: 0 | R36: 0 | S36: 0 | T36: 0 | U36: 0 | V36: 0 | W36: 0 | X36: 0 | Y36: 0 | Z36: 0 | AA36: 0 | AB36: 0 | AC36: 0 | AD36: 0 | AE36: 0 | AF36: 0 | AG36: 0 | AH36: =$B36*Inputs!$B$15*Inputs!$B$16*Curves!$E$5 -> 85552.104 | AI36: =$B36*Inputs!$B$15*Inputs!$B$16*Curves!$E$6 -> 94135.938 | AJ36: =$B36*Inputs!$B$15*Inputs!$B$16*Curves!$E$7 -> 52838.803 | AK36: =$B36*Inputs!$B$15*Inputs!$B$16*Curves!$E$8 -> 57018.379 | AL36: =$B36*Inputs!$B$15*Inputs!$B$16*Curves!$E$9 -> 57295.429
A37: =Acquisition_Plan!A36 -> 2028-09-18 | B37: =Acquisition_Plan!D36+Acquisition_Plan!F36+Acquisition_Plan!E36 -> 800000 | C37: 0 | D37: 0 | E37: 0 | F37: 0 | G37: 0 | H37: 0 | I37: 0 | J37: 0 | K37: 0 | L37: 0 | M37: 0 | N37: 0 | O37: 0 | P37: 0 | Q37: 0 | R37: 0 | S37: 0 | T37: 0 | U37: 0 | V37: 0 | W37: 0 | X37: 0 | Y37: 0 | Z37: 0 | AA37: 0 | AB37: 0 | AC37: 0 | AD37: 0 | AE37: 0 | AF37: 0 | AG37: 0 | AH37: 0 | AI37: =$B37*Inputs!$B$15*Inputs!$B$16*Curves!$E$5 -> 85552.104 | AJ37: =$B37*Inputs!$B$15*Inputs!$B$16*Curves!$E$6 -> 94135.938 | AK37: =$B37*Inputs!$B$15*Inputs!$B$16*Curves!$E$7 -> 52838.803 | AL37: =$B37*Inputs!$B$15*Inputs!$B$16*Curves!$E$8 -> 57018.379
A38: =Acquisition_Plan!A37 -> 2028-10-18 | B38: =Acquisition_Plan!D37+Acquisition_Plan!F37+Acquisition_Plan!E37 -> 800000 | C38: 0 | D38: 0 | E38: 0 | F38: 0 | G38: 0 | H38: 0 | I38: 0 | J38: 0 | K38: 0 | L38: 0 | M38: 0 | N38: 0 | O38: 0 | P38: 0 | Q38: 0 | R38: 0 | S38: 0 | T38: 0 | U38: 0 | V38: 0 | W38: 0 | X38: 0 | Y38: 0 | Z38: 0 | AA38: 0 | AB38: 0 | AC38: 0 | AD38: 0 | AE38: 0 | AF38: 0 | AG38: 0 | AH38: 0 | AI38: 0 | AJ38: =$B38*Inputs!$B$15*Inputs!$B$16*Curves!$E$5 -> 85552.104 | AK38: =$B38*Inputs!$B$15*Inputs!$B$16*Curves!$E$6 -> 94135.938 | AL38: =$B38*Inputs!$B$15*Inputs!$B$16*Curves!$E$7 -> 52838.803
A39: =Acquisition_Plan!A38 -> 2028-11-17 | B39: =Acquisition_Plan!D38+Acquisition_Plan!F38+Acquisition_Plan!E38 -> 800000 | C39: 0 | D39: 0 | E39: 0 | F39: 0 | G39: 0 | H39: 0 | I39: 0 | J39: 0 | K39: 0 | L39: 0 | M39: 0 | N39: 0 | O39: 0 | P39: 0 | Q39: 0 | R39: 0 | S39: 0 | T39: 0 | U39: 0 | V39: 0 | W39: 0 | X39: 0 | Y39: 0 | Z39: 0 | AA39: 0 | AB39: 0 | AC39: 0 | AD39: 0 | AE39: 0 | AF39: 0 | AG39: 0 | AH39: 0 | AI39: 0 | AJ39: 0 | AK39: =$B39*Inputs!$B$15*Inputs!$B$16*Curves!$E$5 -> 85552.104 | AL39: =$B39*Inputs!$B$15*Inputs!$B$16*Curves!$E$6 -> 94135.938
A40: =Acquisition_Plan!A39 -> 2028-12-17 | B40: =Acquisition_Plan!D39+Acquisition_Plan!F39+Acquisition_Plan!E39 -> 800000 | C40: 0 | D40: 0 | E40: 0 | F40: 0 | G40: 0 | H40: 0 | I40: 0 | J40: 0 | K40: 0 | L40: 0 | M40: 0 | N40: 0 | O40: 0 | P40: 0 | Q40: 0 | R40: 0 | S40: 0 | T40: 0 | U40: 0 | V40: 0 | W40: 0 | X40: 0 | Y40: 0 | Z40: 0 | AA40: 0 | AB40: 0 | AC40: 0 | AD40: 0 | AE40: 0 | AF40: 0 | AG40: 0 | AH40: 0 | AI40: 0 | AJ40: 0 | AK40: 0 | AL40: =$B40*Inputs!$B$15*Inputs!$B$16*Curves!$E$5 -> 85552.104
A41: TOTAL | C41: =SUM(C5:C40) -> 21388.026 | D41: =SUM(D5:D40) -> 50269.017 | E41: =SUM(E5:E40) -> 74709.22 | F41: =SUM(F5:F40) -> 98149.736 | G41: =SUM(G5:G40) -> 130033.68 | H41: =SUM(H5:H40) -> 159495.03 | I41: =SUM(I5:I40) -> 196900.13 | J41: =SUM(J5:J40) -> 227999.07 | ... AL41: =SUM(AL5:AL40) -> 600818.75

Sheet PVX_Detail
A1: PVX Cohort Waterfall
A2: Before payback: PVX gets 100% of net rev
A3: After payback: PVX gets 50% of net + interest, until cap
A4: Cap = Draw × (1 + Interest Rate). After cap: Company keeps 100%
A6: Cohort | B6: PVX Draw | C6: Cap | D6: M0 | E6: M1 | F6: M2 | G6: M3 | H6: M4 | I6: M5 | J6: M6 | K6: M7 | L6: M8 | M6: M9 | N6: M10 | O6: M11 | P6: M12 | Q6: M13 | R6: M14 | S6: M15 | T6: M16 | U6: M17 | V6: M18 | W6: M19 | X6: M20 | Y6: M21 | Z6: M22 | AA6: M23 | AB6: M24 | AC6: M25 | AD6: M26 | AE6: M27 | AF6: M28 | AG6: M29 | AH6: M30 | AI6: M31 | AJ6: M32 | AK6: M33 | AL6: M34 | AM6: M35
A7: =Acquisition_Plan!A4 -> 2026-02-01 | B7: =Acquisition_Plan!E4 -> 0 | C7: =B7*(1+Inputs!$B$12) -> 0
A8: This Mo Net | D8: =$B7*Inputs!$B$15*Curves!C5*(1-Inputs!$B$16) -> 0 | E8: =$B7*Inputs!$B$15*Curves!C6*(1-Inputs!$B$16) -> 0 | F8: =$B7*Inputs!$B$15*Curves!C7*(1-Inputs!$B$16) -> 0 | G8: =$B7*Inputs!$B$15*Curves!C8*(1-Inputs!$B$16) -> 0 | H8: =$B7*Inputs!$B$15*Curves!C9*(1-Inputs!$B$16) -> 0 | I8: =$B7*Inputs!$B$15*Curves!C10*(1-Inputs!$B$16) -> 0 | J8: =$B7*Inputs!$B$15*Curves!C11*(1-Inputs!$B$16) -> 0 | K8: =$B7*Inputs!$B$15*Curves!C12*(1-Inputs!$B$16) -> 0 | L8: =$B7*Inputs!$B$15*Curves!C13*(1-Inputs!$B$16) -> 0 | M8: =$B7*Inputs!$B$15*Curves!C14*(1-Inputs!$B$16) -> 0 | N8: =$B7*Inputs!$B$15*Curves!C15*(1-Inputs!$B$16) -> 0 | O8: =$B7*Inputs!$B$15*Curves!C16*(1-Inputs!$B$16) -> 0 | P8: =$B7*Inputs!$B$15*Curves!C17*(1-Inputs!$B$16) -> 0 | Q8: =$B7*Inputs!$B$15*Curves!C18*(1-Inputs!$B$16) -> 0 | R8: =$B7*Inputs!$B$15*Curves!C19*(1-Inputs!$B$16) -> 0 | S8: =$B7*Inputs!$B$15*Curves!C20*(1-Inputs!$B$16) -> 0 | T8: =$B7*Inputs!$B$15*Curves!C21*(1-Inputs!$B$16) -> 0 | U8: =$B7*Inputs!$B$15*Curves!C22*(1-Inputs!$B$16) -> 0 | V8: =$B7*Inputs!$B$15*Curves!C23*(1-Inputs!$B$16) -> 0 | W8: =$B7*Inputs!$B$15*Curves!C24*(1-Inputs!$B$16) -> 0 | X8: =$B7*Inputs!$B$15*Curves!C25*(1-Inputs!$B$16) -> 0 | Y8: =$B7*Inputs!$B$15*Curves!C26*(1-Inputs!$B$16) -> 0 | Z8: =$B7*Inputs!$B$15*Curves!C27*(1-Inputs!$B$16) -> 0 | AA8: =$B7*Inputs!$B$15*Curves!C28*(1-Inputs!$B$16) -> 0 | AB8: =$B7*Inputs!$B$15*Curves!C29*(1-Inputs!$B$16) -> 0 | AC8: =$B7*Inputs!$B$15*Curves!C30*(1-Inputs!$B$16) -> 0 | AD8: =$B7*Inputs!$B$15*Curves!C31*(1-Inputs!$B$16) -> 0 | AE8: =$B7*Inputs!$B$15*Curves!C32*(1-Inputs!$B$16) -> 0 | AF8: =$B7*Inputs!$B$15*Curves!C33*(1-Inputs!$B$16) -> 0 | AG8: =$B7*Inputs!$B$15*Curves!C34*(1-Inputs!$B$16) -> 0 | AH8: =$B7*Inputs!$B$15*Curves!C35*(1-Inputs!$B$16) -> 0 | AI8: =$B7*Inputs!$B$15*Curves!C36*(1-Inputs!$B$16) -> 0 | AJ8: =$B7*Inputs!$B$15*Curves!C37*(1-Inputs!$B$16) -> 0 | AK8: =$B7*Inputs!$B$15*Curves!C38*(1-Inputs!$B$16) -> 0 | AL8: =$B7*Inputs!$B$15*Curves!C39*(1-Inputs!$B$16) -> 0 | AM8: =$B7*Inputs!$B$15*Curves!C40*(1-Inputs!$B$16) -> 0
A9: Payback? | D9: "N" | E9: =IF($B7=0, "N", IF(D12>=$B7, "Y", "N")) -> N | F9: =IF($B7=0, "N", IF(E12>=$B7, "Y", "N")) -> N | G9: =IF($B7=0, "N", IF(F12>=$B7, "Y", "N")) -> N | H9: =IF($B7=0, "N", IF(G12>=$B7, "Y", "N")) -> N | I9: =IF($B7=0, "N", IF(H12>=$B7, "Y", "N")) -> N | J9: =IF($B7=0, "N", IF(I12>=$B7, "Y", "N")) -> N | K9: =IF($B7=0, "N", IF(J12>=$B7, "Y", "N")) -> N | L9: =IF($B7=0, "N", IF(K12>=$B7, "Y", "N")) -> N | ... AM9: =IF($B7=0, "N", IF(AL12>=$B7, "Y", "N")) -> N
A10: Interest | D10: 0 | E10: =IF(AND(E9="Y", D13="N"), $B7*Inputs!$B$12/12, 0) -> 0 | F10: =IF(AND(F9="Y", E13="N"), $B7*Inputs!$B$12/12, 0) -> 0 | G10: =IF(AND(G9="Y", F13="N"), $B7*Inputs!$B$12/12, 0) -> 0 | H10: =IF(AND(H9="Y", G13="N"), $B7*Inputs!$B$12/12, 0) -> 0 | I10: =IF(AND(I9="Y", H13="N"), $B7*Inputs!$B$12/12, 0) -> 0 | J10: =IF(AND(J9="Y", I13="N"), $B7*Inputs!$B$12/12, 0) -> 0 | K10: =IF(AND(K9="Y", J13="N"), $B7*Inputs!$B$12/12, 0) -> 0 | L10: =IF(AND(L9="Y", K13="N"), $B7*Inputs!$B$12/12, 0) -> 0 | ... AM10: =IF(AND(AM9="Y", AL13="N"), $B7*Inputs!$B$12/12, 0) -> 0
A11: PVX Gets | D11: =IF($B7=0, 0, MIN(D8, $C7)) -> 0 | E11: =IF($B7=0, 0, IF(D13="Y", 0, IF(E9="N", MIN(E8, $C7-D12), MIN(E8*0.5+E10, $C7-D12)))) -> 0 | F11: =IF($B7=0, 0, IF(E13="Y", 0, IF(F9="N", MIN(F8, $C7-E12), MIN(F8*0.5+F10, $C7-E12)))) -> 0 | G11: =IF($B7=0, 0, IF(F13="Y", 0, IF(G9="N", MIN(G8, $C7-F12), MIN(G8*0.5+G10, $C7-F12)))) -> 0 | H11: =IF($B7=0, 0, IF(G13="Y", 0, IF(H9="N", MIN(H8, $C7-G12), MIN(H8*0.5+H10, $C7-G12)))) -> 0 | I11: =IF($B7=0, 0, IF(H13="Y", 0, IF(I9="N", MIN(I8, $C7-H12), MIN(I8*0.5+I10, $C7-H12)))) -> 0 | J11: =IF($B7=0, 0, IF(I13="Y", 0, IF(J9="N", MIN(J8, $C7-I12), MIN(J8*0.5+J10, $C7-I12)))) -> 0 | K11: =IF($B7=0, 0, IF(J13="Y", 0, IF(K9="N", MIN(K8, $C7-J12), MIN(K8*0.5+K10, $C7-J12)))) -> 0 | L11: =IF($B7=0, 0, IF(K13="Y", 0, IF(L9="N", MIN(L8, $C7-K12), MIN(L8*0.5+L10, $C7-K12)))) -> 0 | ... AM11: =IF($B7=0, 0, IF(AL13="Y", 0, IF(AM9="N", MIN(AM8, $C7-AL12), MIN(AM8*0.5+AM10, $C7-AL12)))) -> 0
A12: Cum Paid | D12: =D11 -> 0 | E12: =D12+E11 -> 0 | F12: =E12+F11 -> 0 | G12: =F12+G11 -> 0 | H12: =G12+H11 -> 0 | I12: =H12+I11 -> 0 | J12: =I12+J11 -> 0 | K12: =J12+K11 -> 0 | L12: =K12+L11 -> 0 | ... AM12: =AL12+AM11 -> 0
A13: Cap Hit? | D13: =IF(D12>=$C7, "Y", "N") -> Y | E13: =IF(E12>=$C7, "Y", "N") -> Y | F13: =IF(F12>=$C7, "Y", "N") -> Y | G13: =IF(G12>=$C7, "Y", "N") -> Y | H13: =IF(H12>=$C7, "Y", "N") -> Y | I13: =IF(I12>=$C7, "Y", "N") -> Y | J13: =IF(J12>=$C7, "Y", "N") -> Y | K13: =IF(K12>=$C7, "Y", "N") -> Y | ... AM13: =IF(AM12>=$C7, "Y", "N") -> Y
A14: Co Gets | D14: =D8-D11 -> 0 | E14: =E8-E11 -> 0 | F14: =F8-F11 -> 0 | G14: =G8-G11 -> 0 | H14: =H8-H11 -> 0 | I14: =I8-I11 -> 0 | J14: =J8-J11 -> 0 | K14: =K8-K11 -> 0 | ... AM14: =AM8-AM11 -> 0
A16: =Acquisition_Plan!A5 -> 2026-03-03 | B16: =Acquisition_Plan!E5 -> 0 | C16: =B16*(1+Inputs!$B$12) -> 0
A17: This Mo Net | D17: 0 | E17: =$B16*Inputs!$B$15*Curves!C5*(1-Inputs!$B$16) -> 0 | F17: =$B16*Inputs!$B$15*Curves!C6*(1-Inputs!$B$16) -> 0 | G17: =$B16*Inputs!$B$15*Curves!C7*(1-Inputs!$B$16) -> 0 | H17: =$B16*Inputs!$B$15*Curves!C8*(1-Inputs!$B$16) -> 0 | I17: =$B16*Inputs!$B$15*Curves!C9*(1-Inputs!$B$16) -> 0 | J17: =$B16*Inputs!$B$15*Curves!C10*(1-Inputs!$B$16) -> 0 | K17: =$B16*Inputs!$B$15*Curves!C11*(1-Inputs!$B$16) -> 0 | L17: =$B16*Inputs!$B$15*Curves!C12*(1-Inputs!$B$16) -> 0 | M17: =$B16*Inputs!$B$15*Curves!C13*(1-Inputs!$B$16) -> 0 | N17: =$B16*Inputs!$B$15*Curves!C14*(1-Inputs!$B$16) -> 0 | O17: =$B16*Inputs!$B$15*Curves!C15*(1-Inputs!$B$16) -> 0 | P17: =$B16*Inputs!$B$15*Curves!C16*(1-Inputs!$B$16) -> 0 | Q17: =$B16*Inputs!$B$15*Curves!C17*(1-Inputs!$B$16) -> 0 | R17: =$B16*Inputs!$B$15*Curves!C18*(1-Inputs!$B$16) -> 0 | S17: =$B16*Inputs!$B$15*Curves!C19*(1-Inputs!$B$16) -> 0 | T17: =$B16*Inputs!$B$15*Curves!C20*(1-Inputs!$B$16) -> 0 | U17: =$B16*Inputs!$B$15*Curves!C21*(1-Inputs!$B$16) -> 0 | V17: =$B16*Inputs!$B$15*Curves!C22*(1-Inputs!$B$16) -> 0 | W17: =$B16*Inputs!$B$15*Curves!C23*(1-Inputs!$B$16) -> 0 | X17: =$B16*Inputs!$B$15*Curves!C24*(1-Inputs!$B$16) -> 0 | Y17: =$B16*Inputs!$B$15*Curves!C25*(1-Inputs!$B$16) -> 0 | Z17: =$B16*Inputs!$B$15*Curves!C26*(1-Inputs!$B$16) -> 0 | AA17: =$B16*Inputs!$B$15*Curves!C27*(1-Inputs!$B$16) -> 0 | AB17: =$B16*Inputs!$B$15*Curves!C28*(1-Inputs!$B$16) -> 0 | AC17: =$B16*Inputs!$B$15*Curves!C29*(1-Inputs!$B$16) -> 0 | AD17: =$B16*Inputs!$B$15*Curves!C30*(1-Inputs!$B$16) -> 0 | AE17: =$B16*Inputs!$B$15*Curves!C31*(1-Inputs!$B$16) -> 0 | AF17: =$B16*Inputs!$B$15*Curves!C32*(1-Inputs!$B$16) -> 0 | AG17: =$B16*Inputs!$B$15*Curves!C33*(1-Inputs!$B$16) -> 0 | AH17: =$B16*Inputs!$B$15*Curves!C34*(1-Inputs!$B$16) -> 0 | AI17: =$B16*Inputs!$B$15*Curves!C35*(1-Inputs!$B$16) -> 0 | AJ17: =$B16*Inputs!$B$15*Curves!C36*(1-Inputs!$B$16) -> 0 | AK17: =$B16*Inputs!$B$15*Curves!C37*(1-Inputs!$B$16) -> 0 | AL17: =$B16*Inputs!$B$15*Curves!C38*(1-Inputs!$B$16) -> 0 | AM17: =$B16*Inputs!$B$15*Curves!C39*(1-Inputs!$B$16) -> 0
A18: Payback? | D18: 0 | E18: "N" | F18: =IF($B16=0, "N", IF(E21>=$B16, "Y", "N")) -> N | G18: =IF($B16=0, "N", IF(F21>=$B16, "Y", "N")) -> N | H18: =IF($B16=0, "N", IF(G21>=$B16, "Y", "N")) -> N | I18: =IF($B16=0, "N", IF(H21>=$B16, "Y", "N")) -> N | J18: =IF($B16=0, "N", IF(I21>=$B16, "Y", "N")) -> N | K18: =IF($B16=0, "N", IF(J21>=$B16, "Y", "N")) -> N | L18: =IF($B16=0, "N", IF(K21>=$B16, "Y", "N")) -> N | M18: =IF($B16=0, "N", IF(L21>=$B16, "Y", "N")) -> N | ... AM18: =IF($B16=0, "N", IF(AL21>=$B16, "Y", "N")) -> N
A19: Interest | D19: 0 | E19: 0 | F19: =IF(AND(F18="Y", E22="N"), $B16*Inputs!$B$12/12, 0) -> 0 | G19: =IF(AND(G18="Y", F22="N"), $B16*Inputs!$B$12/12, 0) -> 0 | H19: =IF(AND(H18="Y", G22="N"), $B16*Inputs!$B$12/12, 0) -> 0 | I19: =IF(AND(I18="Y", H22="N"), $B16*Inputs!$B$12/12, 0) -> 0 | J19: =IF(AND(J18="Y", I22="N"), $B16*Inputs!$B$12/12, 0) -> 0 | K19: =IF(AND(K18="Y", J22="N"), $B16*Inputs!$B$12/12, 0) -> 0 | L19: =IF(AND(L18="Y", K22="N"), $B16*Inputs!$B$12/12, 0) -> 0 | M19: =IF(AND(M18="Y", L22="N"), $B16*Inputs!$B$12/12, 0) -> 0 | ... AM19: =IF(AND(AM18="Y", AL22="N"), $B16*Inputs!$B$12/12, 0) -> 0
A20: PVX Gets | D20: 0 | E20: =IF($B16=0, 0, MIN(E17, $C16)) -> 0 | F20: =IF($B16=0, 0, IF(E22="Y", 0, IF(F18="N", MIN(F17, $C16-E21), MIN(F17*0.5+F19, $C16-E21)))) -> 0 | G20: =IF($B16=0, 0, IF(F22="Y", 0, IF(G18="N", MIN(G17, $C16-F21), MIN(G17*0.5+G19, $C16-F21)))) -> 0 | H20: =IF($B16=0, 0, IF(G22="Y", 0, IF(H18="N", MIN(H17, $C16-G21), MIN(H17*0.5+H19, $C16-G21)))) -> 0 | I20: =IF($B16=0, 0, IF(H22="Y", 0, IF(I18="N", MIN(I17, $C16-H21), MIN(I17*0.5+I19, $C16-H21)))) -> 0 | J20: =IF($B16=0, 0, IF(I22="Y", 0, IF(J18="N", MIN(J17, $C16-I21), MIN(J17*0.5+J19, $C16-I21)))) -> 0 | K20: =IF($B16=0, 0, IF(J22="Y", 0, IF(K18="N", MIN(K17, $C16-J21), MIN(K17*0.5+K19, $C16-J21)))) -> 0 | L20: =IF($B16=0, 0, IF(K22="Y", 0, IF(L18="N", MIN(L17, $C16-K21), MIN(L17*0.5+L19, $C16-K21)))) -> 0 | M20: =IF($B16=0, 0, IF(L22="Y", 0, IF(M18="N", MIN(M17, $C16-L21), MIN(M17*0.5+M19, $C16-L21)))) -> 0 | ... AM20: =IF($B16=0, 0, IF(AL22="Y", 0, IF(AM18="N", MIN(AM17, $C16-AL21), MIN(AM17*0.5+AM19, $C16-AL21)))) -> 0
A21: Cum Paid | D21: 0 | E21: =E20 -> 0 | F21: =E21+F20 -> 0 | G21: =F21+G20 -> 0 | H21: =G21+H20 -> 0 | I21: =H21+I20 -> 0 | J21: =I21+J20 -> 0 | K21: =J21+K20 -> 0 | L21: =K21+L20 -> 0 | M21: =L21+M20 -> 0 | ... AM21: =AL21+AM20 -> 0
A22: Cap Hit? | D22: 0 | E22: =IF(E21>=$C16, "Y", "N") -> Y | F22: =IF(F21>=$C16, "Y", "N") -> Y | G22: =IF(G21>=$C16, "Y", "N") -> Y | H22: =IF(H21>=$C16, "Y", "N") -> Y | I22: =IF(I21>=$C16, "Y", "N") -> Y | J22: =IF(J21>=$C16, "Y", "N") -> Y | K22: =IF(K21>=$C16, "Y", "N") -> Y | L22: =IF(L21>=$C16, "Y", "N") -> Y | ... AM22: =IF(AM21>=$C16, "Y", "N") -> Y
A23: Co Gets | D23: 0 | E23: =E17-E20 -> 0 | F23: =F17-F20 -> 0 | G23: =G17-G20 -> 0 | H23: =H17-H20 -> 0 | I23: =I17-I20 -> 0 | J23: =J17-J20 -> 0 | K23: =K17-K20 -> 0 | L23: =L17-L20 -> 0 | ... AM23: =AM17-AM20 -> 0
A25: =Acquisition_Plan!A6 -> 2026-04-02 | B25: =Acquisition_Plan!E6 -> 150000 | C25: =B25*(1+Inputs!$B$12) -> 157500
A26: This Mo Net | D26: 0 | E26: 0 | F26: =$B25*Inputs!$B$15*Curves!C5*(1-Inputs!$B$16) -> 81748.181 | G26: =$B25*Inputs!$B$15*Curves!C6*(1-Inputs!$B$16) -> 38980.333 | H26: =$B25*Inputs!$B$15*Curves!C7*(1-Inputs!$B$16) -> 24986.796 | I26: =$B25*Inputs!$B$15*Curves!C8*(1-Inputs!$B$16) -> 17579.709 | J26: =$B25*Inputs!$B$15*Curves!C9*(1-Inputs!$B$16) -> 10451.661 | K26: =$B25*Inputs!$B$15*Curves!C10*(1-Inputs!$B$16) -> 9369.1374 | L26: =$B25*Inputs!$B$15*Curves!C11*(1-Inputs!$B$16) -> 8091.6041 | M26: =$B25*Inputs!$B$15*Curves!C12*(1-Inputs!$B$16) -> 7149.3841 | N26: =$B25*Inputs!$B$15*Curves!C13*(1-Inputs!$B$16) -> 6391.2626 | O26: =$B25*Inputs!$B$15*Curves!C14*(1-Inputs!$B$16) -> 7426.93 | P26: =$B25*Inputs!$B$15*Curves!C15*(1-Inputs!$B$16) -> 5175 | Q26: =$B25*Inputs!$B$15*Curves!C16*(1-Inputs!$B$16) -> 5175 | R26: =$B25*Inputs!$B$15*Curves!C17*(1-Inputs!$B$16) -> 5175 | S26: =$B25*Inputs!$B$15*Curves!C18*(1-Inputs!$B$16) -> 1293.75 | T26: =$B25*Inputs!$B$15*Curves!C19*(1-Inputs!$B$16) -> 1293.75 | U26: =$B25*Inputs!$B$15*Curves!C20*(1-Inputs!$B$16) -> 1293.75 | V26: =$B25*Inputs!$B$15*Curves!C21*(1-Inputs!$B$16) -> 1293.75 | W26: =$B25*Inputs!$B$15*Curves!C22*(1-Inputs!$B$16) -> 1293.75 | X26: =$B25*Inputs!$B$15*Curves!C23*(1-Inputs!$B$16) -> 1293.75 | Y26: =$B25*Inputs!$B$15*Curves!C24*(1-Inputs!$B$16) -> 1293.75 | Z26: =$B25*Inputs!$B$15*Curves!C25*(1-Inputs!$B$16) -> 1293.75 | AA26: =$B25*Inputs!$B$15*Curves!C26*(1-Inputs!$B$16) -> 1293.75 | AB26: =$B25*Inputs!$B$15*Curves!C27*(1-Inputs!$B$16) -> 1293.75 | AC26: =$B25*Inputs!$B$15*Curves!C28*(1-Inputs!$B$16) -> 1293.75 | AD26: =$B25*Inputs!$B$15*Curves!C29*(1-Inputs!$B$16) -> 1293.75 | AE26: =$B25*Inputs!$B$15*Curves!C30*(1-Inputs!$B$16) -> 1293.75 | AF26: =$B25*Inputs!$B$15*Curves!C31*(1-Inputs!$B$16) -> 1293.75 | AG26: =$B25*Inputs!$B$15*Curves!C32*(1-Inputs!$B$16) -> 1293.75 | AH26: =$B25*Inputs!$B$15*Curves!C33*(1-Inputs!$B$16) -> 1293.75 | AI26: =$B25*Inputs!$B$15*Curves!C34*(1-Inputs!$B$16) -> 1293.75 | AJ26: =$B25*Inputs!$B$15*Curves!C35*(1-Inputs!$B$16) -> 1293.75 | AK26: =$B25*Inputs!$B$15*Curves!C36*(1-Inputs!$B$16) -> 1293.75 | AL26: =$B25*Inputs!$B$15*Curves!C37*(1-Inputs!$B$16) -> 1293.75 | AM26: =$B25*Inputs!$B$15*Curves!C38*(1-Inputs!$B$16) -> 1293.75
A27: Payback? | D27: 0 | E27: 0 | F27: "N" | G27: =IF($B25=0, "N", IF(F30>=$B25, "Y", "N")) -> N | H27: =IF($B25=0, "N", IF(G30>=$B25, "Y", "N")) -> N | I27: =IF($B25=0, "N", IF(H30>=$B25, "Y", "N")) -> N | J27: =IF($B25=0, "N", IF(I30>=$B25, "Y", "N")) -> Y | K27: =IF($B25=0, "N", IF(J30>=$B25, "Y", "N")) -> Y | L27: =IF($B25=0, "N", IF(K30>=$B25, "Y", "N")) -> Y | M27: =IF($B25=0, "N", IF(L30>=$B25, "Y", "N")) -> Y | N27: =IF($B25=0, "N", IF(M30>=$B25, "Y", "N")) -> Y | ... AM27: =IF($B25=0, "N", IF(AL30>=$B25, "Y", "N")) -> Y
A28: Interest | D28: 0 | E28: 0 | F28: 0 | G28: =IF(AND(G27="Y", F31="N"), $B25*Inputs!$B$12/12, 0) -> 0 | H28: =IF(AND(H27="Y", G31="N"), $B25*Inputs!$B$12/12, 0) -> 0 | I28: =IF(AND(I27="Y", H31="N"), $B25*Inputs!$B$12/12, 0) -> 0 | J28: =IF(AND(J27="Y", I31="N"), $B25*Inputs!$B$12/12, 0) -> 0 | K28: =IF(AND(K27="Y", J31="N"), $B25*Inputs!$B$12/12, 0) -> 0 | L28: =IF(AND(L27="Y", K31="N"), $B25*Inputs!$B$12/12, 0) -> 0 | M28: =IF(AND(M27="Y", L31="N"), $B25*Inputs!$B$12/12, 0) -> 0 | N28: =IF(AND(N27="Y", M31="N"), $B25*Inputs!$B$12/12, 0) -> 0 | ... AM28: =IF(AND(AM27="Y", AL31="N"), $B25*Inputs!$B$12/12, 0) -> 0
A29: PVX Gets | D29: 0 | E29: 0 | F29: =IF($B25=0, 0, MIN(F26, $C25)) -> 81748.181 | G29: =IF($B25=0, 0, IF(F31="Y", 0, IF(G27="N", MIN(G26, $C25-F30), MIN(G26*0.5+G28, $C25-F30)))) -> 38980.333 | H29: =IF($B25=0, 0, IF(G31="Y", 0, IF(H27="N", MIN(H26, $C25-G30), MIN(H26*0.5+H28, $C25-G30)))) -> 24986.796 | I29: =IF($B25=0, 0, IF(H31="Y", 0, IF(I27="N", MIN(I26, $C25-H30), MIN(I26*0.5+I28, $C25-H30)))) -> 11784.689 | J29: =IF($B25=0, 0, IF(I31="Y", 0, IF(J27="N", MIN(J26, $C25-I30), MIN(J26*0.5+J28, $C25-I30)))) -> 0 | K29: =IF($B25=0, 0, IF(J31="Y", 0, IF(K27="N", MIN(K26, $C25-J30), MIN(K26*0.5+K28, $C25-J30)))) -> 0 | L29: =IF($B25=0, 0, IF(K31="Y", 0, IF(L27="N", MIN(L26, $C25-K30), MIN(L26*0.5+L28, $C25-K30)))) -> 0 | M29: =IF($B25=0, 0, IF(L31="Y", 0, IF(M27="N", MIN(M26, $C25-L30), MIN(M26*0.5+M28, $C25-L30)))) -> 0 | N29: =IF($B25=0, 0, IF(M31="Y", 0, IF(N27="N", MIN(N26, $C25-M30), MIN(N26*0.5+N28, $C25-M30)))) -> 0 | ... AM29: =IF($B25=0, 0, IF(AL31="Y", 0, IF(AM27="N", MIN(AM26, $C25-AL30), MIN(AM26*0.5+AM28, $C25-AL30)))) -> 0
A30: Cum Paid | D30: 0 | E30: 0 | F30: =F29 -> 81748.181 | G30: =F30+G29 -> 120728.51 | H30: =G30+H29 -> 145715.31 | I30: =H30+I29 -> 157500 | J30: =I30+J29 -> 157500 | K30: =J30+K29 -> 157500 | L30: =K30+L29 -> 157500 | M30: =L30+M29 -> 157500 | N30: =M30+N29 -> 157500 | ... AM30: =AL30+AM29 -> 157500
A31: Cap Hit? | D31: 0 | E31: 0 | F31: =IF(F30>=$C25, "Y", "N") -> N | G31: =IF(G30>=$C25, "Y", "N") -> N | H31: =IF(H30>=$C25, "Y", "N") -> N | I31: =IF(I30>=$C25, "Y", "N") -> Y | J31: =IF(J30>=$C25, "Y", "N") -> Y | K31: =IF(K30>=$C25, "Y", "N") -> Y | L31: =IF(L30>=$C25, "Y", "N") -> Y | M31: =IF(M30>=$C25, "Y", "N") -> Y | ... AM31: =IF(AM30>=$C25, "Y", "N") -> Y
A32: Co Gets | D32: 0 | E32: 0 | F32: =F26-F29 -> 0 | G32: =G26-G29 -> 0 | H32: =H26-H29 -> 0 | I32: =I26-I29 -> 5795.0205 | J32: =J26-J29 -> 10451.661 | K32: =K26-K29 -> 9369.1374 | L32: =L26-L29 -> 8091.6041 | M32: =M26-M29 -> 7149.3841 | ... AM32: =AM26-AM29 -> 1293.75
A34: =Acquisition_Plan!A7 -> 2026-05-02 | B34: =Acquisition_Plan!E7 -> 150000 | C34: =B34*(1+Inputs!$B$12) -> 157500
A35: This Mo Net | D35: 0 | E35: 0 | F35: 0 | G35: =$B34*Inputs!$B$15*Curves!C5*(1-Inputs!$B$16) -> 81748.181 | H35: =$B34*Inputs!$B$15*Curves!C6*(1-Inputs!$B$16) -> 38980.333 | I35: =$B34*Inputs!$B$15*Curves!C7*(1-Inputs!$B$16) -> 24986.796 | J35: =$B34*Inputs!$B$15*Curves!C8*(1-Inputs!$B$16) -> 17579.709 | K35: =$B34*Inputs!$B$15*Curves!C9*(1-Inputs!$B$16) -> 10451.661 | L35: =$B34*Inputs!$B$15*Curves!C10*(1-Inputs!$B$16) -> 9369.1374 | M35: =$B34*Inputs!$B$15*Curves!C11*(1-Inputs!$B$16) -> 8091.6041 | N35: =$B34*Inputs!$B$15*Curves!C12*(1-Inputs!$B$16) -> 7149.3841 | O35: =$B34*Inputs!$B$15*Curves!C13*(1-Inputs!$B$16) -> 6391.2626 | P35: =$B34*Inputs!$B$15*Curves!C14*(1-Inputs!$B$16) -> 7426.93 | Q35: =$B34*Inputs!$B$15*Curves!C15*(1-Inputs!$B$16) -> 5175 | R35: =$B34*Inputs!$B$15*Curves!C16*(1-Inputs!$B$16) -> 5175 | S35: =$B34*Inputs!$B$15*Curves!C17*(1-Inputs!$B$16) -> 5175 | T35: =$B34*Inputs!$B$15*Curves!C18*(1-Inputs!$B$16) -> 1293.75 | U35: =$B34*Inputs!$B$15*Curves!C19*(1-Inputs!$B$16) -> 1293.75 | V35: =$B34*Inputs!$B$15*Curves!C20*(1-Inputs!$B$16) -> 1293.75 | W35: =$B34*Inputs!$B$15*Curves!C21*(1-Inputs!$B$16) -> 1293.75 | X35: =$B34*Inputs!$B$15*Curves!C22*(1-Inputs!$B$16) -> 1293.75 | Y35: =$B34*Inputs!$B$15*Curves!C23*(1-Inputs!$B$16) -> 1293.75 | Z35: =$B34*Inputs!$B$15*Curves!C24*(1-Inputs!$B$16) -> 1293.75 | AA35: =$B34*Inputs!$B$15*Curves!C25*(1-Inputs!$B$16) -> 1293.75 | AB35: =$B34*Inputs!$B$15*Curves!C26*(1-Inputs!$B$16) -> 1293.75 | AC35: =$B34*Inputs!$B$15*Curves!C27*(1-Inputs!$B$16) -> 1293.75 | AD35: =$B34*Inputs!$B$15*Curves!C28*(1-Inputs!$B$16) -> 1293.75 | AE35: =$B34*Inputs!$B$15*Curves!C29*(1-Inputs!$B$16) -> 1293.75 | AF35: =$B34*Inputs!$B$15*Curves!C30*(1-Inputs!$B$16) -> 1293.75 | AG35: =$B34*Inputs!$B$15*Curves!C31*(1-Inputs!$B$16) -> 1293.75 | AH35: =$B34*Inputs!$B$15*Curves!C32*(1-Inputs!$B$16) -> 1293.75 | AI35: =$B34*Inputs!$B$15*Curves!C33*(1-Inputs!$B$16) -> 1293.75 | AJ35: =$B34*Inputs!$B$15*Curves!C34*(1-Inputs!$B$16) -> 1293.75 | AK35: =$B34*Inputs!$B$15*Curves!C35*(1-Inputs!$B$16) -> 1293.75 | AL35: =$B34*Inputs!$B$15*Curves!C36*(1-Inputs!$B$16) -> 1293.75 | AM35: =$B34*Inputs!$B$15*Curves!C37*(1-Inputs!$B$16) -> 1293.75
A36: Payback? | D36: 0 | E36: 0 | F36: 0 | G36: "N" | H36: =IF($B34=0, "N", IF(G39>=$B34, "Y", "N")) -> N | I36: =IF($B34=0, "N", IF(H39>=$B34, "Y", "N")) -> N | J36: =IF($B34=0, "N", IF(I39>=$B34, "Y", "N")) -> N | K36: =IF($B34=0, "N", IF(J39>=$B34, "Y", "N")) -> Y | L36: =IF($B34=0, "N", IF(K39>=$B34, "Y", "N")) -> Y | M36: =IF($B34=0, "N", IF(L39>=$B34, "Y", "N")) -> Y | N36: =IF($B34=0, "N", IF(M39>=$B34, "Y", "N")) -> Y | O36: =IF($B34=0, "N", IF(N39>=$B34, "Y", "N")) -> Y | ... AM36: =IF($B34=0, "N", IF(AL39>=$B34, "Y", "N")) -> Y
A37: Interest | D37: 0 | E37: 0 | F37: 0 | G37: 0 | H37: =IF(AND(H36="Y", G40="N"), $B34*Inputs!$B$12/12, 0) -> 0 | I37: =IF(AND(I36="Y", H40="N"), $B34*Inputs!$B$12/12, 0) -> 0 | J37: =IF(AND(J36="Y", I40="N"), $B34*Inputs!$B$12/12, 0) -> 0 | K37: =IF(AND(K36="Y", J40="N"), $B34*Inputs!$B$12/12, 0) -> 0 | L37: =IF(AND(L36="Y", K40="N"), $B34*Inputs!$B$12/12, 0) -> 0 | M37: =IF(AND(M36="Y", L40="N"), $B34*Inputs!$B$12/12, 0) -> 0 | N37: =IF(AND(N36="Y", M40="N"), $B34*Inputs!$B$12/12, 0) -> 0 | O37: =IF(AND(O36="Y", N40="N"), $B34*Inputs!$B$12/12, 0) -> 0 | ... AM37: =IF(AND(AM36="Y", AL40="N"), $B34*Inputs!$B$12/12, 0) -> 0
A38: PVX Gets | D38: 0 | E38: 0 | F38: 0 | G38: =IF($B34=0, 0, MIN(G35, $C34)) -> 81748.181 | H38: =IF($B34=0, 0, IF(G40="Y", 0, IF(H36="N", MIN(H35, $C34-G39), MIN(H35*0.5+H37, $C34-G39)))) -> 38980.333 | I38: =IF($B34=0, 0, IF(H40="Y", 0, IF(I36="N", MIN(I35, $C34-H39), MIN(I35*0.5+I37, $C34-H39)))) -> 24986.796 | J38: =IF($B34=0, 0, IF(I40="Y", 0, IF(J36="N", MIN(J35, $C34-I39), MIN(J35*0.5+J37, $C34-I39)))) -> 11784.689 | K38: =IF($B34=0, 0, IF(J40="Y", 0, IF(K36="N", MIN(K35, $C34-J39), MIN(K35*0.5+K37, $C34-J39)))) -> 0 | L38: =IF($B34=0, 0, IF(K40="Y", 0, IF(L36="N", MIN(L35, $C34-K39), MIN(L35*0.5+L37, $C34-K39)))) -> 0 | M38: =IF($B34=0, 0, IF(L40="Y", 0, IF(M36="N", MIN(M35, $C34-L39), MIN(M35*0.5+M37, $C34-L39)))) -> 0 | N38: =IF($B34=0, 0, IF(M40="Y", 0, IF(N36="N", MIN(N35, $C34-M39), MIN(N35*0.5+N37, $C34-M39)))) -> 0 | O38: =IF($B34=0, 0, IF(N40="Y", 0, IF(O36="N", MIN(O35, $C34-N39), MIN(O35*0.5+O37, $C34-N39)))) -> 0 | ... AM38: =IF($B34=0, 0, IF(AL40="Y", 0, IF(AM36="N", MIN(AM35, $C34-AL39), MIN(AM35*0.5+AM37, $C34-AL39)))) -> 0
A39: Cum Paid | D39: 0 | E39: 0 | F39: 0 | G39: =G38 -> 81748.181 | H39: =G39+H38 -> 120728.51 | I39: =H39+I38 -> 145715.31 | J39: =I39+J38 -> 157500 | K39: =J39+K38 -> 157500 | L39: =K39+L38 -> 157500 | M39: =L39+M38 -> 157500 | N39: =M39+N38 -> 157500 | O39: =N39+O38 -> 157500 | ... AM39: =AL39+AM38 -> 157500
A40: Cap Hit? | D40: 0 | E40: 0 | F40: 0 | G40: =IF(G39>=$C34, "Y", "N") -> N | H40: =IF(H39>=$C34, "Y", "N") -> N | I40: =IF(I39>=$C34, "Y", "N") -> N | J40: =IF(J39>=$C34, "Y", "N") -> Y | K40: =IF(K39>=$C34, "Y", "N") -> Y | L40: =IF(L39>=$C34, "Y", "N") -> Y | M40: =IF(M39>=$C34, "Y", "N") -> Y | N40: =IF(N39>=$C34, "Y", "N") -> Y | ... AM40: =IF(AM39>=$C34, "Y", "N") -> Y
A41: Co Gets | D41: 0 | E41: 0 | F41: 0 | G41: =G35-G38 -> 0 | H41: =H35-H38 -> 0 | I41: =I35-I38 -> 0 | J41: =J35-J38 -> 5795.0205 | K41: =K35-K38 -> 10451.661 | L41: =L35-L38 -> 9369.1374 | M41: =M35-M38 -> 8091.6041 | N41: =N35-N38 -> 7149.3841 | ... AM41: =AM35-AM38 -> 1293.75
A43: =Acquisition_Plan!A8 -> 2026-06-01 | B43: =Acquisition_Plan!E8 -> 200000 | C43: =B43*(1+Inputs!$B$12) -> 210000
A44: This Mo Net | D44: 0 | E44: 0 | F44: 0 | G44: 0 | H44: =$B43*Inputs!$B$15*Curves!C5*(1-Inputs!$B$16) -> 108997.58 | I44: =$B43*Inputs!$B$15*Curves!C6*(1-Inputs!$B$16) -> 51973.778 | J44: =$B43*Inputs!$B$15*Curves!C7*(1-Inputs!$B$16) -> 33315.728 | K44: =$B43*Inputs!$B$15*Curves!C8*(1-Inputs!$B$16) -> 23439.613 | L44: =$B43*Inputs!$B$15*Curves!C9*(1-Inputs!$B$16) -> 13935.549 | M44: =$B43*Inputs!$B$15*Curves!C10*(1-Inputs!$B$16) -> 12492.183 | N44: =$B43*Inputs!$B$15*Curves!C11*(1-Inputs!$B$16) -> 10788.805 | O44: =$B43*Inputs!$B$15*Curves!C12*(1-Inputs!$B$16) -> 9532.5121 | P44: =$B43*Inputs!$B$15*Curves!C13*(1-Inputs!$B$16) -> 8521.6834 | Q44: =$B43*Inputs!$B$15*Curves!C14*(1-Inputs!$B$16) -> 9902.5733 | R44: =$B43*Inputs!$B$15*Curves!C15*(1-Inputs!$B$16) -> 6900 | S44: =$B43*Inputs!$B$15*Curves!C16*(1-Inputs!$B$16) -> 6900 | T44: =$B43*Inputs!$B$15*Curves!C17*(1-Inputs!$B$16) -> 6900 | U44: =$B43*Inputs!$B$15*Curves!C18*(1-Inputs!$B$16) -> 1725 | V44: =$B43*Inputs!$B$15*Curves!C19*(1-Inputs!$B$16) -> 1725 | W44: =$B43*Inputs!$B$15*Curves!C20*(1-Inputs!$B$16) -> 1725 | X44: =$B43*Inputs!$B$15*Curves!C21*(1-Inputs!$B$16) -> 1725 | Y44: =$B43*Inputs!$B$15*Curves!C22*(1-Inputs!$B$16) -> 1725 | Z44: =$B43*Inputs!$B$15*Curves!C23*(1-Inputs!$B$16) -> 1725 | AA44: =$B43*Inputs!$B$15*Curves!C24*(1-Inputs!$B$16) -> 1725 | AB44: =$B43*Inputs!$B$15*Curves!C25*(1-Inputs!$B$16) -> 1725 | AC44: =$B43*Inputs!$B$15*Curves!C26*(1-Inputs!$B$16) -> 1725 | AD44: =$B43*Inputs!$B$15*Curves!C27*(1-Inputs!$B$16) -> 1725 | AE44: =$B43*Inputs!$B$15*Curves!C28*(1-Inputs!$B$16) -> 1725 | AF44: =$B43*Inputs!$B$15*Curves!C29*(1-Inputs!$B$16) -> 1725 | AG44: =$B43*Inputs!$B$15*Curves!C30*(1-Inputs!$B$16) -> 1725 | AH44: =$B43*Inputs!$B$15*Curves!C31*(1-Inputs!$B$16) -> 1725 | AI44: =$B43*Inputs!$B$15*Curves!C32*(1-Inputs!$B$16) -> 1725 | AJ44: =$B43*Inputs!$B$15*Curves!C33*(1-Inputs!$B$16) -> 1725 | AK44: =$B43*Inputs!$B$15*Curves!C34*(1-Inputs!$B$16) -> 1725 | AL44: =$B43*Inputs!$B$15*Curves!C35*(1-Inputs!$B$16) -> 1725 | AM44: =$B43*Inputs!$B$15*Curves!C36*(1-Inputs!$B$16) -> 1725
A45: Payback? | D45: 0 | E45: 0 | F45: 0 | G45: 0 | H45: "N" | I45: =IF($B43=0, "N", IF(H48>=$B43, "Y", "N")) -> N | J45: =IF($B43=0, "N", IF(I48>=$B43, "Y", "N")) -> N | K45: =IF($B43=0, "N", IF(J48>=$B43, "Y", "N")) -> N | L45: =IF($B43=0, "N", IF(K48>=$B43, "Y", "N")) -> Y | M45: =IF($B43=0, "N", IF(L48>=$B43, "Y", "N")) -> Y | N45: =IF($B43=0, "N", IF(M48>=$B43, "Y", "N")) -> Y | O45: =IF($B43=0, "N", IF(N48>=$B43, "Y", "N")) -> Y | P45: =IF($B43=0, "N", IF(O48>=$B43, "Y", "N")) -> Y | ... AM45: =IF($B43=0, "N", IF(AL48>=$B43, "Y", "N")) -> Y
A46: Interest | D46: 0 | E46: 0 | F46: 0 | G46: 0 | H46: 0 | I46: =IF(AND(I45="Y", H49="N"), $B43*Inputs!$B$12/12, 0) -> 0 | J46: =IF(AND(J45="Y", I49="N"), $B43*Inputs!$B$12/12, 0) -> 0 | K46: =IF(AND(K45="Y", J49="N"), $B43*Inputs!$B$12/12, 0) -> 0 | L46: =IF(AND(L45="Y", K49="N"), $B43*Inputs!$B$12/12, 0) -> 0 | M46: =IF(AND(M45="Y", L49="N"), $B43*Inputs!$B$12/12, 0) -> 0 | N46: =IF(AND(N45="Y", M49="N"), $B43*Inputs!$B$12/12, 0) -> 0 | O46: =IF(AND(O45="Y", N49="N"), $B43*Inputs!$B$12/12, 0) -> 0 | P46: =IF(AND(P45="Y", O49="N"), $B43*Inputs!$B$12/12, 0) -> 0 | ... AM46: =IF(AND(AM45="Y", AL49="N"), $B43*Inputs!$B$12/12, 0) -> 0
A47: PVX Gets | D47: 0 | E47: 0 | F47: 0 | G47: 0 | H47: =IF($B43=0, 0, MIN(H44, $C43)) -> 108997.58 | I47: =IF($B43=0, 0, IF(H49="Y", 0, IF(I45="N", MIN(I44, $C43-H48), MIN(I44*0.5+I46, $C43-H48)))) -> 51973.778 | J47: =IF($B43=0, 0, IF(I49="Y", 0, IF(J45="N", MIN(J44, $C43-I48), MIN(J44*0.5+J46, $C43-I48)))) -> 33315.728 | K47: =IF($B43=0, 0, IF(J49="Y", 0, IF(K45="N", MIN(K44, $C43-J48), MIN(K44*0.5+K46, $C43-J48)))) -> 15712.919 | L47: =IF($B43=0, 0, IF(K49="Y", 0, IF(L45="N", MIN(L44, $C43-K48), MIN(L44*0.5+L46, $C43-K48)))) -> 0 | M47: =IF($B43=0, 0, IF(L49="Y", 0, IF(M45="N", MIN(M44, $C43-L48), MIN(M44*0.5+M46, $C43-L48)))) -> 0 | N47: =IF($B43=0, 0, IF(M49="Y", 0, IF(N45="N", MIN(N44, $C43-M48), MIN(N44*0.5+N46, $C43-M48)))) -> 0 | O47: =IF($B43=0, 0, IF(N49="Y", 0, IF(O45="N", MIN(O44, $C43-N48), MIN(O44*0.5+O46, $C43-N48)))) -> 0 | P47: =IF($B43=0, 0, IF(O49="Y", 0, IF(P45="N", MIN(P44, $C43-O48), MIN(P44*0.5+P46, $C43-O48)))) -> 0 | ... AM47: =IF($B43=0, 0, IF(AL49="Y", 0, IF(AM45="N", MIN(AM44, $C43-AL48), MIN(AM44*0.5+AM46, $C43-AL48)))) -> 0
A48: Cum Paid | D48: 0 | E48: 0 | F48: 0 | G48: 0 | H48: =H47 -> 108997.58 | I48: =H48+I47 -> 160971.35 | J48: =I48+J47 -> 194287.08 | K48: =J48+K47 -> 210000 | L48: =K48+L47 -> 210000 | M48: =L48+M47 -> 210000 | N48: =M48+N47 -> 210000 | O48: =N48+O47 -> 210000 | P48: =O48+P47 -> 210000 | ... AM48: =AL48+AM47 -> 210000
A49: Cap Hit? | D49: 0 | E49: 0 | F49: 0 | G49: 0 | H49: =IF(H48>=$C43, "Y", "N") -> N | I49: =IF(I48>=$C43, "Y", "N") -> N | J49: =IF(J48>=$C43, "Y", "N") -> N | K49: =IF(K48>=$C43, "Y", "N") -> Y | L49: =IF(L48>=$C43, "Y", "N") -> Y | M49: =IF(M48>=$C43, "Y", "N") -> Y | N49: =IF(N48>=$C43, "Y", "N") -> Y | O49: =IF(O48>=$C43, "Y", "N") -> Y | ... AM49: =IF(AM48>=$C43, "Y", "N") -> Y
A50: Co Gets | D50: 0 | E50: 0 | F50: 0 | G50: 0 | H50: =H44-H47 -> 0 | I50: =I44-I47 -> 0 | J50: =J44-J47 -> 0 | K50: =K44-K47 -> 7726.694 | L50: =L44-L47 -> 13935.549 | M50: =M44-M47 -> 12492.183 | N50: =N44-N47 -> 10788.805 | O50: =O44-O47 -> 9532.5121 | ... AM50: =AM44-AM47 -> 1725
A52: =Acquisition_Plan!A9 -> 2026-07-01 | B52: =Acquisition_Plan!E9 -> 200000 | C52: =B52*(1+Inputs!$B$12) -> 210000
A53: This Mo Net | D53: 0 | E53: 0 | F53: 0 | G53: 0 | H53: 0 | I53: =$B52*Inputs!$B$15*Curves!C5*(1-Inputs!$B$16) -> 108997.58 | J53: =$B52*Inputs!$B$15*Curves!C6*(1-Inputs!$B$16) -> 51973.778 | K53: =$B52*Inputs!$B$15*Curves!C7*(1-Inputs!$B$16) -> 33315.728 | L53: =$B52*Inputs!$B$15*Curves!C8*(1-Inputs!$B$16) -> 23439.613 | M53: =$B52*Inputs!$B$15*Curves!C9*(1-Inputs!$B$16) -> 13935.549 | N53: =$B52*Inputs!$B$15*Curves!C10*(1-Inputs!$B$16) -> 12492.183 | O53: =$B52*Inputs!$B$15*Curves!C11*(1-Inputs!$B$16) -> 10788.805 | P53: =$B52*Inputs!$B$15*Curves!C12*(1-Inputs!$B$16) -> 9532.5121 | Q53: =$B52*Inputs!$B$15*Curves!C13*(1-Inputs!$B$16) -> 8521.6834 | R53: =$B52*Inputs!$B$15*Curves!C14*(1-Inputs!$B$16) -> 9902.5733 | S53: =$B52*Inputs!$B$15*Curves!C15*(1-Inputs!$B$16) -> 6900 | T53: =$B52*Inputs!$B$15*Curves!C16*(1-Inputs!$B$16) -> 6900 | U53: =$B52*Inputs!$B$15*Curves!C17*(1-Inputs!$B$16) -> 6900 | V53: =$B52*Inputs!$B$15*Curves!C18*(1-Inputs!$B$16) -> 1725 | W53: =$B52*Inputs!$B$15*Curves!C19*(1-Inputs!$B$16) -> 1725 | X53: =$B52*Inputs!$B$15*Curves!C20*(1-Inputs!$B$16) -> 1725 | Y53: =$B52*Inputs!$B$15*Curves!C21*(1-Inputs!$B$16) -> 1725 | Z53: =$B52*Inputs!$B$15*Curves!C22*(1-Inputs!$B$16) -> 1725 | AA53: =$B52*Inputs!$B$15*Curves!C23*(1-Inputs!$B$16) -> 1725 | AB53: =$B52*Inputs!$B$15*Curves!C24*(1-Inputs!$B$16) -> 1725 | AC53: =$B52*Inputs!$B$15*Curves!C25*(1-Inputs!$B$16) -> 1725 | AD53: =$B52*Inputs!$B$15*Curves!C26*(1-Inputs!$B$16) -> 1725 | AE53: =$B52*Inputs!$B$15*Curves!C27*(1-Inputs!$B$16) -> 1725 | AF53: =$B52*Inputs!$B$15*Curves!C28*(1-Inputs!$B$16) -> 1725 | AG53: =$B52*Inputs!$B$15*Curves!C29*(1-Inputs!$B$16) -> 1725 | AH53: =$B52*Inputs!$B$15*Curves!C30*(1-Inputs!$B$16) -> 1725 | AI53: =$B52*Inputs!$B$15*Curves!C31*(1-Inputs!$B$16) -> 1725 | AJ53: =$B52*Inputs!$B$15*Curves!C32*(1-Inputs!$B$16) -> 1725 | AK53: =$B52*Inputs!$B$15*Curves!C33*(1-Inputs!$B$16) -> 1725 | AL53: =$B52*Inputs!$B$15*Curves!C34*(1-Inputs!$B$16) -> 1725 | AM53: =$B52*Inputs!$B$15*Curves!C35*(1-Inputs!$B$16) -> 1725
A54: Payback? | D54: 0 | E54: 0 | F54: 0 | G54: 0 | H54: 0 | I54: "N" | J54: =IF($B52=0, "N", IF(I57>=$B52, "Y", "N")) -> N | K54: =IF($B52=0, "N", IF(J57>=$B52, "Y", "N")) -> N | L54: =IF($B52=0, "N", IF(K57>=$B52, "Y", "N")) -> N | M54: =IF($B52=0, "N", IF(L57>=$B52, "Y", "N")) -> Y | N54: =IF($B52=0, "N", IF(M57>=$B52, "Y", "N")) -> Y | O54: =IF($B52=0, "N", IF(N57>=$B52, "Y", "N")) -> Y | P54: =IF($B52=0, "N", IF(O57>=$B52, "Y", "N")) -> Y | Q54: =IF($B52=0, "N", IF(P57>=$B52, "Y", "N")) -> Y | ... AM54: =IF($B52=0, "N", IF(AL57>=$B52, "Y", "N")) -> Y
A55: Interest | D55: 0 | E55: 0 | F55: 0 | G55: 0 | H55: 0 | I55: 0 | J55: =IF(AND(J54="Y", I58="N"), $B52*Inputs!$B$12/12, 0) -> 0 | K55: =IF(AND(K54="Y", J58="N"), $B52*Inputs!$B$12/12, 0) -> 0 | L55: =IF(AND(L54="Y", K58="N"), $B52*Inputs!$B$12/12, 0) -> 0 | M55: =IF(AND(M54="Y", L58="N"), $B52*Inputs!$B$12/12, 0) -> 0 | N55: =IF(AND(N54="Y", M58="N"), $B52*Inputs!$B$12/12, 0) -> 0 | O55: =IF(AND(O54="Y", N58="N"), $B52*Inputs!$B$12/12, 0) -> 0 | P55: =IF(AND(P54="Y", O58="N"), $B52*Inputs!$B$12/12, 0) -> 0 | Q55: =IF(AND(Q54="Y", P58="N"), $B52*Inputs!$B$12/12, 0) -> 0 | ... AM55: =IF(AND(AM54="Y", AL58="N"), $B52*Inputs!$B$12/12, 0) -> 0
A56: PVX Gets | D56: 0 | E56: 0 | F56: 0 | G56: 0 | H56: 0 | I56: =IF($B52=0, 0, MIN(I53, $C52)) -> 108997.58 | J56: =IF($B52=0, 0, IF(I58="Y", 0, IF(J54="N", MIN(J53, $C52-I57), MIN(J53*0.5+J55, $C52-I57)))) -> 51973.778 | K56: =IF($B52=0, 0, IF(J58="Y", 0, IF(K54="N", MIN(K53, $C52-J57), MIN(K53*0.5+K55, $C52-J57)))) -> 33315.728 | L56: =IF($B52=0, 0, IF(K58="Y", 0, IF(L54="N", MIN(L53, $C52-K57), MIN(L53*0.5+L55, $C52-K57)))) -> 15712.919 | M56: =IF($B52=0, 0, IF(L58="Y", 0, IF(M54="N", MIN(M53, $C52-L57), MIN(M53*0.5+M55, $C52-L57)))) -> 0 | N56: =IF($B52=0, 0, IF(M58="Y", 0, IF(N54="N", MIN(N53, $C52-M57), MIN(N53*0.5+N55, $C52-M57)))) -> 0 | O56: =IF($B52=0, 0, IF(N58="Y", 0, IF(O54="N", MIN(O53, $C52-N57), MIN(O53*0.5+O55, $C52-N57)))) -> 0 | P56: =IF($B52=0, 0, IF(O58="Y", 0, IF(P54="N", MIN(P53, $C52-O57), MIN(P53*0.5+P55, $C52-O57)))) -> 0 | Q56: =IF($B52=0, 0, IF(P58="Y", 0, IF(Q54="N", MIN(Q53, $C52-P57), MIN(Q53*0.5+Q55, $C52-P57)))) -> 0 | ... AM56: =IF($B52=0, 0, IF(AL58="Y", 0, IF(AM54="N", MIN(AM53, $C52-AL57), MIN(AM53*0.5+AM55, $C52-AL57)))) -> 0
A57: Cum Paid | D57: 0 | E57: 0 | F57: 0 | G57: 0 | H57: 0 | I57: =I56 -> 108997.58 | J57: =I57+J56 -> 160971.35 | K57: =J57+K56 -> 194287.08 | L57: =K57+L56 -> 210000 | M57: =L57+M56 -> 210000 | N57: =M57+N56 -> 210000 | O57: =N57+O56 -> 210000 | P57: =O57+P56 -> 210000 | Q57: =P57+Q56 -> 210000 | ... AM57: =AL57+AM56 -> 210000
A58: Cap Hit? | D58: 0 | E58: 0 | F58: 0 | G58: 0 | H58: 0 | I58: =IF(I57>=$C52, "Y", "N") -> N | J58: =IF(J57>=$C52, "Y", "N") -> N | K58: =IF(K57>=$C52, "Y", "N") -> N | L58: =IF(L57>=$C52, "Y", "N") -> Y | M58: =IF(M57>=$C52, "Y", "N") -> Y | N58: =IF(N57>=$C52, "Y", "N") -> Y | O58: =IF(O57>=$C52, "Y", "N") -> Y | P58: =IF(P57>=$C52, "Y", "N") -> Y | ... AM58: =IF(AM57>=$C52, "Y", "N") -> Y
A59: Co Gets | D59: 0 | E59: 0 | F59: 0 | G59: 0 | H59: 0 | I59: =I53-I56 -> 0 | J59: =J53-J56 -> 0 | K59: =K53-K56 -> 0 | L59: =L53-L56 -> 7726.694 | M59: =M53-M56 -> 13935.549 | N59: =N53-N56 -> 12492.183 | O59: =O53-O56 -> 10788.805 | P59: =P53-P56 -> 9532.5121 | ... AM59: =AM53-AM56 -> 1725
A61: =Acquisition_Plan!A10 -> 2026-07-31 | B61: =Acquisition_Plan!E10 -> 250000 | C61: =B61*(1+Inputs!$B$12) -> 262500
A62: This Mo Net | D62: 0 | E62: 0 | F62: 0 | G62: 0 | H62: 0 | I62: 0 | J62: =$B61*Inputs!$B$15*Curves!C5*(1-Inputs!$B$16) -> 136246.97 | K62: =$B61*Inputs!$B$15*Curves!C6*(1-Inputs!$B$16) -> 64967.222 | L62: =$B61*Inputs!$B$15*Curves!C7*(1-Inputs!$B$16) -> 41644.661 | M62: =$B61*Inputs!$B$15*Curves!C8*(1-Inputs!$B$16) -> 29299.516 | N62: =$B61*Inputs!$B$15*Curves!C9*(1-Inputs!$B$16) -> 17419.436 | O62: =$B61*Inputs!$B$15*Curves!C10*(1-Inputs!$B$16) -> 15615.229 | P62: =$B61*Inputs!$B$15*Curves!C11*(1-Inputs!$B$16) -> 13486.007 | Q62: =$B61*Inputs!$B$15*Curves!C12*(1-Inputs!$B$16) -> 11915.64 | R62: =$B61*Inputs!$B$15*Curves!C13*(1-Inputs!$B$16) -> 10652.104 | S62: =$B61*Inputs!$B$15*Curves!C14*(1-Inputs!$B$16) -> 12378.217 | T62: =$B61*Inputs!$B$15*Curves!C15*(1-Inputs!$B$16) -> 8625 | U62: =$B61*Inputs!$B$15*Curves!C16*(1-Inputs!$B$16) -> 8625 | V62: =$B61*Inputs!$B$15*Curves!C17*(1-Inputs!$B$16) -> 8625 | W62: =$B61*Inputs!$B$15*Curves!C18*(1-Inputs!$B$16) -> 2156.25 | X62: =$B61*Inputs!$B$15*Curves!C19*(1-Inputs!$B$16) -> 2156.25 | Y62: =$B61*Inputs!$B$15*Curves!C20*(1-Inputs!$B$16) -> 2156.25 | Z62: =$B61*Inputs!$B$15*Curves!C21*(1-Inputs!$B$16) -> 2156.25 | AA62: =$B61*Inputs!$B$15*Curves!C22*(1-Inputs!$B$16) -> 2156.25 | AB62: =$B61*Inputs!$B$15*Curves!C23*(1-Inputs!$B$16) -> 2156.25 | AC62: =$B61*Inputs!$B$15*Curves!C24*(1-Inputs!$B$16) -> 2156.25 | AD62: =$B61*Inputs!$B$15*Curves!C25*(1-Inputs!$B$16) -> 2156.25 | AE62: =$B61*Inputs!$B$15*Curves!C26*(1-Inputs!$B$16) -> 2156.25 | AF62: =$B61*Inputs!$B$15*Curves!C27*(1-Inputs!$B$16) -> 2156.25 | AG62: =$B61*Inputs!$B$15*Curves!C28*(1-Inputs!$B$16) -> 2156.25 | AH62: =$B61*Inputs!$B$15*Curves!C29*(1-Inputs!$B$16) -> 2156.25 | AI62: =$B61*Inputs!$B$15*Curves!C30*(1-Inputs!$B$16) -> 2156.25 | AJ62: =$B61*Inputs!$B$15*Curves!C31*(1-Inputs!$B$16) -> 2156.25 | AK62: =$B61*Inputs!$B$15*Curves!C32*(1-Inputs!$B$16) -> 2156.25 | AL62: =$B61*Inputs!$B$15*Curves!C33*(1-Inputs!$B$16) -> 2156.25 | AM62: =$B61*Inputs!$B$15*Curves!C34*(1-Inputs!$B$16) -> 2156.25
A63: Payback? | D63: 0 | E63: 0 | F63: 0 | G63: 0 | H63: 0 | I63: 0 | J63: "N" | K63: =IF($B61=0, "N", IF(J66>=$B61, "Y", "N")) -> N | L63: =IF($B61=0, "N", IF(K66>=$B61, "Y", "N")) -> N | M63: =IF($B61=0, "N", IF(L66>=$B61, "Y", "N")) -> N | N63: =IF($B61=0, "N", IF(M66>=$B61, "Y", "N")) -> Y | O63: =IF($B61=0, "N", IF(N66>=$B61, "Y", "N")) -> Y | P63: =IF($B61=0, "N", IF(O66>=$B61, "Y", "N")) -> Y | Q63: =IF($B61=0, "N", IF(P66>=$B61, "Y", "N")) -> Y | R63: =IF($B61=0, "N", IF(Q66>=$B61, "Y", "N")) -> Y | ... AM63: =IF($B61=0, "N", IF(AL66>=$B61, "Y", "N")) -> Y
A64: Interest | D64: 0 | E64: 0 | F64: 0 | G64: 0 | H64: 0 | I64: 0 | J64: 0 | K64: =IF(AND(K63="Y", J67="N"), $B61*Inputs!$B$12/12, 0) -> 0 | L64: =IF(AND(L63="Y", K67="N"), $B61*Inputs!$B$12/12, 0) -> 0 | M64: =IF(AND(M63="Y", L67="N"), $B61*Inputs!$B$12/12, 0) -> 0 | N64: =IF(AND(N63="Y", M67="N"), $B61*Inputs!$B$12/12, 0) -> 0 | O64: =IF(AND(O63="Y", N67="N"), $B61*Inputs!$B$12/12, 0) -> 0 | P64: =IF(AND(P63="Y", O67="N"), $B61*Inputs!$B$12/12, 0) -> 0 | Q64: =IF(AND(Q63="Y", P67="N"), $B61*Inputs!$B$12/12, 0) -> 0 | R64: =IF(AND(R63="Y", Q67="N"), $B61*Inputs!$B$12/12, 0) -> 0 | ... AM64: =IF(AND(AM63="Y", AL67="N"), $B61*Inputs!$B$12/12, 0) -> 0
A65: PVX Gets | D65: 0 | E65: 0 | F65: 0 | G65: 0 | H65: 0 | I65: 0 | J65: =IF($B61=0, 0, MIN(J62, $C61)) -> 136246.97 | K65: =IF($B61=0, 0, IF(J67="Y", 0, IF(K63="N", MIN(K62, $C61-J66), MIN(K62*0.5+K64, $C61-J66)))) -> 64967.222 | L65: =IF($B61=0, 0, IF(K67="Y", 0, IF(L63="N", MIN(L62, $C61-K66), MIN(L62*0.5+L64, $C61-K66)))) -> 41644.661 | M65: =IF($B61=0, 0, IF(L67="Y", 0, IF(M63="N", MIN(M62, $C61-L66), MIN(M62*0.5+M64, $C61-L66)))) -> 19641.148 | N65: =IF($B61=0, 0, IF(M67="Y", 0, IF(N63="N", MIN(N62, $C61-M66), MIN(N62*0.5+N64, $C61-M66)))) -> 0 | O65: =IF($B61=0, 0, IF(N67="Y", 0, IF(O63="N", MIN(O62, $C61-N66), MIN(O62*0.5+O64, $C61-N66)))) -> 0 | P65: =IF($B61=0, 0, IF(O67="Y", 0, IF(P63="N", MIN(P62, $C61-O66), MIN(P62*0.5+P64, $C61-O66)))) -> 0 | Q65: =IF($B61=0, 0, IF(P67="Y", 0, IF(Q63="N", MIN(Q62, $C61-P66), MIN(Q62*0.5+Q64, $C61-P66)))) -> 0 | R65: =IF($B61=0, 0, IF(Q67="Y", 0, IF(R63="N", MIN(R62, $C61-Q66), MIN(R62*0.5+R64, $C61-Q66)))) -> 0 | ... AM65: =IF($B61=0, 0, IF(AL67="Y", 0, IF(AM63="N", MIN(AM62, $C61-AL66), MIN(AM62*0.5+AM64, $C61-AL66)))) -> 0
A66: Cum Paid | D66: 0 | E66: 0 | F66: 0 | G66: 0 | H66: 0 | I66: 0 | J66: =J65 -> 136246.97 | K66: =J66+K65 -> 201214.19 | L66: =K66+L65 -> 242858.85 | M66: =L66+M65 -> 262500 | N66: =M66+N65 -> 262500 | O66: =N66+O65 -> 262500 | P66: =O66+P65 -> 262500 | Q66: =P66+Q65 -> 262500 | R66: =Q66+R65 -> 262500 | ... AM66: =AL66+AM65 -> 262500
A67: Cap Hit? | D67: 0 | E67: 0 | F67: 0 | G67: 0 | H67: 0 | I67: 0 | J67: =IF(J66>=$C61, "Y", "N") -> N | K67: =IF(K66>=$C61, "Y", "N") -> N | L67: =IF(L66>=$C61, "Y", "N") -> N | M67: =IF(M66>=$C61, "Y", "N") -> Y | N67: =IF(N66>=$C61, "Y", "N") -> Y | O67: =IF(O66>=$C61, "Y", "N") -> Y | P67: =IF(P66>=$C61, "Y", "N") -> Y | Q67: =IF(Q66>=$C61, "Y", "N") -> Y | ... AM67: =IF(AM66>=$C61, "Y", "N") -> Y
A68: Co Gets | D68: 0 | E68: 0 | F68: 0 | G68: 0 | H68: 0 | I68: 0 | J68: =J62-J65 -> 0 | K68: =K62-K65 -> 0 | L68: =L62-L65 -> 0 | M68: =M62-M65 -> 9658.3674 | N68: =N62-N65 -> 17419.436 | O68: =O62-O65 -> 15615.229 | P68: =P62-P65 -> 13486.007 | Q68: =Q62-Q65 -> 11915.64 | ... AM68: =AM62-AM65 -> 2156.25
A70: =Acquisition_Plan!A11 -> 2026-08-30 | B70: =Acquisition_Plan!E11 -> 250000 | C70: =B70*(1+Inputs!$B$12) -> 262500
A71: This Mo Net | D71: 0 | E71: 0 | F71: 0 | G71: 0 | H71: 0 | I71: 0 | J71: 0 | K71: =$B70*Inputs!$B$15*Curves!C5*(1-Inputs!$B$16) -> 136246.97 | L71: =$B70*Inputs!$B$15*Curves!C6*(1-Inputs!$B$16) -> 64967.222 | M71: =$B70*Inputs!$B$15*Curves!C7*(1-Inputs!$B$16) -> 41644.661 | N71: =$B70*Inputs!$B$15*Curves!C8*(1-Inputs!$B$16) -> 29299.516 | O71: =$B70*Inputs!$B$15*Curves!C9*(1-Inputs!$B$16) -> 17419.436 | P71: =$B70*Inputs!$B$15*Curves!C10*(1-Inputs!$B$16) -> 15615.229 | Q71: =$B70*Inputs!$B$15*Curves!C11*(1-Inputs!$B$16) -> 13486.007 | R71: =$B70*Inputs!$B$15*Curves!C12*(1-Inputs!$B$16) -> 11915.64 | S71: =$B70*Inputs!$B$15*Curves!C13*(1-Inputs!$B$16) -> 10652.104 | T71: =$B70*Inputs!$B$15*Curves!C14*(1-Inputs!$B$16) -> 12378.217 | U71: =$B70*Inputs!$B$15*Curves!C15*(1-Inputs!$B$16) -> 8625 | V71: =$B70*Inputs!$B$15*Curves!C16*(1-Inputs!$B$16) -> 8625 | W71: =$B70*Inputs!$B$15*Curves!C17*(1-Inputs!$B$16) -> 8625 | X71: =$B70*Inputs!$B$15*Curves!C18*(1-Inputs!$B$16) -> 2156.25 | Y71: =$B70*Inputs!$B$15*Curves!C19*(1-Inputs!$B$16) -> 2156.25 | Z71: =$B70*Inputs!$B$15*Curves!C20*(1-Inputs!$B$16) -> 2156.25 | AA71: =$B70*Inputs!$B$15*Curves!C21*(1-Inputs!$B$16) -> 2156.25 | AB71: =$B70*Inputs!$B$15*Curves!C22*(1-Inputs!$B$16) -> 2156.25 | AC71: =$B70*Inputs!$B$15*Curves!C23*(1-Inputs!$B$16) -> 2156.25 | AD71: =$B70*Inputs!$B$15*Curves!C24*(1-Inputs!$B$16) -> 2156.25 | AE71: =$B70*Inputs!$B$15*Curves!C25*(1-Inputs!$B$16) -> 2156.25 | AF71: =$B70*Inputs!$B$15*Curves!C26*(1-Inputs!$B$16) -> 2156.25 | AG71: =$B70*Inputs!$B$15*Curves!C27*(1-Inputs!$B$16) -> 2156.25 | AH71: =$B70*Inputs!$B$15*Curves!C28*(1-Inputs!$B$16) -> 2156.25 | AI71: =$B70*Inputs!$B$15*Curves!C29*(1-Inputs!$B$16) -> 2156.25 | AJ71: =$B70*Inputs!$B$15*Curves!C30*(1-Inputs!$B$16) -> 2156.25 | AK71: =$B70*Inputs!$B$15*Curves!C31*(1-Inputs!$B$16) -> 2156.25 | AL71: =$B70*Inputs!$B$15*Curves!C32*(1-Inputs!$B$16) -> 2156.25 | AM71: =$B70*Inputs!$B$15*Curves!C33*(1-Inputs!$B$16) -> 2156.25
A72: Payback? | D72: 0 | E72: 0 | F72: 0 | G72: 0 | H72: 0 | I72: 0 | J72: 0 | K72: "N" | L72: =IF($B70=0, "N", IF(K75>=$B70, "Y", "N")) -> N | M72: =IF($B70=0, "N", IF(L75>=$B70, "Y", "N")) -> N | N72: =IF($B70=0, "N", IF(M75>=$B70, "Y", "N")) -> N | O72: =IF($B70=0, "N", IF(N75>=$B70, "Y", "N")) -> Y | P72: =IF($B70=0, "N", IF(O75>=$B70, "Y", "N")) -> Y | Q72: =IF($B70=0, "N", IF(P75>=$B70, "Y", "N")) -> Y | R72: =IF($B70=0, "N", IF(Q75>=$B70, "Y", "N")) -> Y | S72: =IF($B70=0, "N", IF(R75>=$B70, "Y", "N")) -> Y | ... AM72: =IF($B70=0, "N", IF(AL75>=$B70, "Y", "N")) -> Y
A73: Interest | D73: 0 | E73: 0 | F73: 0 | G73: 0 | H73: 0 | I73: 0 | J73: 0 | K73: 0 | L73: =IF(AND(L72="Y", K76="N"), $B70*Inputs!$B$12/12, 0) -> 0 | M73: =IF(AND(M72="Y", L76="N"), $B70*Inputs!$B$12/12, 0) -> 0 | N73: =IF(AND(N72="Y", M76="N"), $B70*Inputs!$B$12/12, 0) -> 0 | O73: =IF(AND(O72="Y", N76="N"), $B70*Inputs!$B$12/12, 0) -> 0 | P73: =IF(AND(P72="Y", O76="N"), $B70*Inputs!$B$12/12, 0) -> 0 | Q73: =IF(AND(Q72="Y", P76="N"), $B70*Inputs!$B$12/12, 0) -> 0 | R73: =IF(AND(R72="Y", Q76="N"), $B70*Inputs!$B$12/12, 0) -> 0 | S73: =IF(AND(S72="Y", R76="N"), $B70*Inputs!$B$12/12, 0) -> 0 | ... AM73: =IF(AND(AM72="Y", AL76="N"), $B70*Inputs!$B$12/12, 0) -> 0
A74: PVX Gets | D74: 0 | E74: 0 | F74: 0 | G74: 0 | H74: 0 | I74: 0 | J74: 0 | K74: =IF($B70=0, 0, MIN(K71, $C70)) -> 136246.97 | L74: =IF($B70=0, 0, IF(K76="Y", 0, IF(L72="N", MIN(L71, $C70-K75), MIN(L71*0.5+L73, $C70-K75)))) -> 64967.222 | M74: =IF($B70=0, 0, IF(L76="Y", 0, IF(M72="N", MIN(M71, $C70-L75), MIN(M71*0.5+M73, $C70-L75)))) -> 41644.661 | N74: =IF($B70=0, 0, IF(M76="Y", 0, IF(N72="N", MIN(N71, $C70-M75), MIN(N71*0.5+N73, $C70-M75)))) -> 19641.148 | O74: =IF($B70=0, 0, IF(N76="Y", 0, IF(O72="N", MIN(O71, $C70-N75), MIN(O71*0.5+O73, $C70-N75)))) -> 0 | P74: =IF($B70=0, 0, IF(O76="Y", 0, IF(P72="N", MIN(P71, $C70-O75), MIN(P71*0.5+P73, $C70-O75)))) -> 0 | Q74: =IF($B70=0, 0, IF(P76="Y", 0, IF(Q72="N", MIN(Q71, $C70-P75), MIN(Q71*0.5+Q73, $C70-P75)))) -> 0 | R74: =IF($B70=0, 0, IF(Q76="Y", 0, IF(R72="N", MIN(R71, $C70-Q75), MIN(R71*0.5+R73, $C70-Q75)))) -> 0 | S74: =IF($B70=0, 0, IF(R76="Y", 0, IF(S72="N", MIN(S71, $C70-R75), MIN(S71*0.5+S73, $C70-R75)))) -> 0 | ... AM74: =IF($B70=0, 0, IF(AL76="Y", 0, IF(AM72="N", MIN(AM71, $C70-AL75), MIN(AM71*0.5+AM73, $C70-AL75)))) -> 0
A75: Cum Paid | D75: 0 | E75: 0 | F75: 0 | G75: 0 | H75: 0 | I75: 0 | J75: 0 | K75: =K74 -> 136246.97 | L75: =K75+L74 -> 201214.19 | M75: =L75+M74 -> 242858.85 | N75: =M75+N74 -> 262500 | O75: =N75+O74 -> 262500 | P75: =O75+P74 -> 262500 | Q75: =P75+Q74 -> 262500 | R75: =Q75+R74 -> 262500 | S75: =R75+S74 -> 262500 | ... AM75: =AL75+AM74 -> 262500
A76: Cap Hit? | D76: 0 | E76: 0 | F76: 0 | G76: 0 | H76: 0 | I76: 0 | J76: 0 | K76: =IF(K75>=$C70, "Y", "N") -> N | L76: =IF(L75>=$C70, "Y", "N") -> N | M76: =IF(M75>=$C70, "Y", "N") -> N | N76: =IF(N75>=$C70, "Y", "N") -> Y | O76: =IF(O75>=$C70, "Y", "N") -> Y | P76: =IF(P75>=$C70, "Y", "N") -> Y | Q76: =IF(Q75>=$C70, "Y", "N") -> Y | R76: =IF(R75>=$C70, "Y", "N") -> Y | ... AM76: =IF(AM75>=$C70, "Y", "N") -> Y
A77: Co Gets | D77: 0 | E77: 0 | F77: 0 | G77: 0 | H77: 0 | I77: 0 | J77: 0 | K77: =K71-K74 -> 0 | L77: =L71-L74 -> 0 | M77: =M71-M74 -> 0 | N77: =N71-N74 -> 9658.3674 | O77: =O71-O74 -> 17419.436 | P77: =P71-P74 -> 15615.229 | Q77: =Q71-Q74 -> 13486.007 | R77: =R71-R74 -> 11915.64 | ... AM77: =AM71-AM74 -> 2156.25
A79: =Acquisition_Plan!A12 -> 2026-09-29 | B79: =Acquisition_Plan!E12 -> 300000 | C79: =B79*(1+Inputs!$B$12) -> 315000
A80: This Mo Net | D80: 0 | E80: 0 | F80: 0 | G80: 0 | H80: 0 | I80: 0 | J80: 0 | K80: 0 | L80: =$B79*Inputs!$B$15*Curves!C5*(1-Inputs!$B$16) -> 163496.36 | M80: =$B79*Inputs!$B$15*Curves!C6*(1-Inputs!$B$16) -> 77960.667 | N80: =$B79*Inputs!$B$15*Curves!C7*(1-Inputs!$B$16) -> 49973.593 | O80: =$B79*Inputs!$B$15*Curves!C8*(1-Inputs!$B$16) -> 35159.419 | P80: =$B79*Inputs!$B$15*Curves!C9*(1-Inputs!$B$16) -> 20903.323 | Q80: =$B79*Inputs!$B$15*Curves!C10*(1-Inputs!$B$16) -> 18738.275 | R80: =$B79*Inputs!$B$15*Curves!C11*(1-Inputs!$B$16) -> 16183.208 | S80: =$B79*Inputs!$B$15*Curves!C12*(1-Inputs!$B$16) -> 14298.768 | T80: =$B79*Inputs!$B$15*Curves!C13*(1-Inputs!$B$16) -> 12782.525 | U80: =$B79*Inputs!$B$15*Curves!C14*(1-Inputs!$B$16) -> 14853.86 | V80: =$B79*Inputs!$B$15*Curves!C15*(1-Inputs!$B$16) -> 10350 | W80: =$B79*Inputs!$B$15*Curves!C16*(1-Inputs!$B$16) -> 10350 | X80: =$B79*Inputs!$B$15*Curves!C17*(1-Inputs!$B$16) -> 10350 | Y80: =$B79*Inputs!$B$15*Curves!C18*(1-Inputs!$B$16) -> 2587.5 | Z80: =$B79*Inputs!$B$15*Curves!C19*(1-Inputs!$B$16) -> 2587.5 | AA80: =$B79*Inputs!$B$15*Curves!C20*(1-Inputs!$B$16) -> 2587.5 | AB80: =$B79*Inputs!$B$15*Curves!C21*(1-Inputs!$B$16) -> 2587.5 | AC80: =$B79*Inputs!$B$15*Curves!C22*(1-Inputs!$B$16) -> 2587.5 | AD80: =$B79*Inputs!$B$15*Curves!C23*(1-Inputs!$B$16) -> 2587.5 | AE80: =$B79*Inputs!$B$15*Curves!C24*(1-Inputs!$B$16) -> 2587.5 | AF80: =$B79*Inputs!$B$15*Curves!C25*(1-Inputs!$B$16) -> 2587.5 | AG80: =$B79*Inputs!$B$15*Curves!C26*(1-Inputs!$B$16) -> 2587.5 | AH80: =$B79*Inputs!$B$15*Curves!C27*(1-Inputs!$B$16) -> 2587.5 | AI80: =$B79*Inputs!$B$15*Curves!C28*(1-Inputs!$B$16) -> 2587.5 | AJ80: =$B79*Inputs!$B$15*Curves!C29*(1-Inputs!$B$16) -> 2587.5 | AK80: =$B79*Inputs!$B$15*Curves!C30*(1-Inputs!$B$16) -> 2587.5 | AL80: =$B79*Inputs!$B$15*Curves!C31*(1-Inputs!$B$16) -> 2587.5 | AM80: =$B79*Inputs!$B$15*Curves!C32*(1-Inputs!$B$16) -> 2587.5
A81: Payback? | D81: 0 | E81: 0 | F81: 0 | G81: 0 | H81: 0 | I81: 0 | J81: 0 | K81: 0 | L81: "N" | M81: =IF($B79=0, "N", IF(L84>=$B79, "Y", "N")) -> N | N81: =IF($B79=0, "N", IF(M84>=$B79, "Y", "N")) -> N | O81: =IF($B79=0, "N", IF(N84>=$B79, "Y", "N")) -> N | P81: =IF($B79=0, "N", IF(O84>=$B79, "Y", "N")) -> Y | Q81: =IF($B79=0, "N", IF(P84>=$B79, "Y", "N")) -> Y | R81: =IF($B79=0, "N", IF(Q84>=$B79, "Y", "N")) -> Y | S81: =IF($B79=0, "N", IF(R84>=$B79, "Y", "N")) -> Y | T81: =IF($B79=0, "N", IF(S84>=$B79, "Y", "N")) -> Y | ... AM81: =IF($B79=0, "N", IF(AL84>=$B79, "Y", "N")) -> Y
A82: Interest | D82: 0 | E82: 0 | F82: 0 | G82: 0 | H82: 0 | I82: 0 | J82: 0 | K82: 0 | L82: 0 | M82: =IF(AND(M81="Y", L85="N"), $B79*Inputs!$B$12/12, 0) -> 0 | N82: =IF(AND(N81="Y", M85="N"), $B79*Inputs!$B$12/12, 0) -> 0 | O82: =IF(AND(O81="Y", N85="N"), $B79*Inputs!$B$12/12, 0) -> 0 | P82: =IF(AND(P81="Y", O85="N"), $B79*Inputs!$B$12/12, 0) -> 0 | Q82: =IF(AND(Q81="Y", P85="N"), $B79*Inputs!$B$12/12, 0) -> 0 | R82: =IF(AND(R81="Y", Q85="N"), $B79*Inputs!$B$12/12, 0) -> 0 | S82: =IF(AND(S81="Y", R85="N"), $B79*Inputs!$B$12/12, 0) -> 0 | T82: =IF(AND(T81="Y", S85="N"), $B79*Inputs!$B$12/12, 0) -> 0 | ... AM82: =IF(AND(AM81="Y", AL85="N"), $B79*Inputs!$B$12/12, 0) -> 0
A83: PVX Gets | D83: 0 | E83: 0 | F83: 0 | G83: 0 | H83: 0 | I83: 0 | J83: 0 | K83: 0 | L83: =IF($B79=0, 0, MIN(L80, $C79)) -> 163496.36 | M83: =IF($B79=0, 0, IF(L85="Y", 0, IF(M81="N", MIN(M80, $C79-L84), MIN(M80*0.5+M82, $C79-L84)))) -> 77960.667 | N83: =IF($B79=0, 0, IF(M85="Y", 0, IF(N81="N", MIN(N80, $C79-M84), MIN(N80*0.5+N82, $C79-M84)))) -> 49973.593 | O83: =IF($B79=0, 0, IF(N85="Y", 0, IF(O81="N", MIN(O80, $C79-N84), MIN(O80*0.5+O82, $C79-N84)))) -> 23569.378 | P83: =IF($B79=0, 0, IF(O85="Y", 0, IF(P81="N", MIN(P80, $C79-O84), MIN(P80*0.5+P82, $C79-O84)))) -> 0 | Q83: =IF($B79=0, 0, IF(P85="Y", 0, IF(Q81="N", MIN(Q80, $C79-P84), MIN(Q80*0.5+Q82, $C79-P84)))) -> 0 | R83: =IF($B79=0, 0, IF(Q85="Y", 0, IF(R81="N", MIN(R80, $C79-Q84), MIN(R80*0.5+R82, $C79-Q84)))) -> 0 | S83: =IF($B79=0, 0, IF(R85="Y", 0, IF(S81="N", MIN(S80, $C79-R84), MIN(S80*0.5+S82, $C79-R84)))) -> 0 | T83: =IF($B79=0, 0, IF(S85="Y", 0, IF(T81="N", MIN(T80, $C79-S84), MIN(T80*0.5+T82, $C79-S84)))) -> 0 | ... AM83: =IF($B79=0, 0, IF(AL85="Y", 0, IF(AM81="N", MIN(AM80, $C79-AL84), MIN(AM80*0.5+AM82, $C79-AL84)))) -> 0
A84: Cum Paid | D84: 0 | E84: 0 | F84: 0 | G84: 0 | H84: 0 | I84: 0 | J84: 0 | K84: 0 | L84: =L83 -> 163496.36 | M84: =L84+M83 -> 241457.03 | N84: =M84+N83 -> 291430.62 | O84: =N84+O83 -> 315000 | P84: =O84+P83 -> 315000 | Q84: =P84+Q83 -> 315000 | R84: =Q84+R83 -> 315000 | S84: =R84+S83 -> 315000 | T84: =S84+T83 -> 315000 | ... AM84: =AL84+AM83 -> 315000
A85: Cap Hit? | D85: 0 | E85: 0 | F85: 0 | G85: 0 | H85: 0 | I85: 0 | J85: 0 | K85: 0 | L85: =IF(L84>=$C79, "Y", "N") -> N | M85: =IF(M84>=$C79, "Y", "N") -> N | N85: =IF(N84>=$C79, "Y", "N") -> N | O85: =IF(O84>=$C79, "Y", "N") -> Y | P85: =IF(P84>=$C79, "Y", "N") -> Y | Q85: =IF(Q84>=$C79, "Y", "N") -> Y | R85: =IF(R84>=$C79, "Y", "N") -> Y | S85: =IF(S84>=$C79, "Y", "N") -> Y | ... AM85: =IF(AM84>=$C79, "Y", "N") -> Y
A86: Co Gets | D86: 0 | E86: 0 | F86: 0 | G86: 0 | H86: 0 | I86: 0 | J86: 0 | K86: 0 | L86: =L80-L83 -> 0 | M86: =M80-M83 -> 0 | N86: =N80-N83 -> 0 | O86: =O80-O83 -> 11590.041 | P86: =P80-P83 -> 20903.323 | Q86: =Q80-Q83 -> 18738.275 | R86: =R80-R83 -> 16183.208 | S86: =S80-S83 -> 14298.768 | ... AM86: =AM80-AM83 -> 2587.5
A88: =Acquisition_Plan!A13 -> 2026-10-29 | B88: =Acquisition_Plan!E13 -> 300000 | C88: =B88*(1+Inputs!$B$12) -> 315000
A89: This Mo Net | D89: 0 | E89: 0 | F89: 0 | G89: 0 | H89: 0 | I89: 0 | J89: 0 | K89: 0 | L89: 0 | M89: =$B88*Inputs!$B$15*Curves!C5*(1-Inputs!$B$16) -> 163496.36 | N89: =$B88*Inputs!$B$15*Curves!C6*(1-Inputs!$B$16) -> 77960.667 | O89: =$B88*Inputs!$B$15*Curves!C7*(1-Inputs!$B$16) -> 49973.593 | P89: =$B88*Inputs!$B$15*Curves!C8*(1-Inputs!$B$16) -> 35159.419 | Q89: =$B88*Inputs!$B$15*Curves!C9*(1-Inputs!$B$16) -> 20903.323 | R89: =$B88*Inputs!$B$15*Curves!C10*(1-Inputs!$B$16) -> 18738.275 | S89: =$B88*Inputs!$B$15*Curves!C11*(1-Inputs!$B$16) -> 16183.208 | T89: =$B88*Inputs!$B$15*Curves!C12*(1-Inputs!$B$16) -> 14298.768 | U89: =$B88*Inputs!$B$15*Curves!C13*(1-Inputs!$B$16) -> 12782.525 | V89: =$B88*Inputs!$B$15*Curves!C14*(1-Inputs!$B$16) -> 14853.86 | W89: =$B88*Inputs!$B$15*Curves!C15*(1-Inputs!$B$16) -> 10350 | X89: =$B88*Inputs!$B$15*Curves!C16*(1-Inputs!$B$16) -> 10350 | Y89: =$B88*Inputs!$B$15*Curves!C17*(1-Inputs!$B$16) -> 10350 | Z89: =$B88*Inputs!$B$15*Curves!C18*(1-Inputs!$B$16) -> 2587.5 | AA89: =$B88*Inputs!$B$15*Curves!C19*(1-Inputs!$B$16) -> 2587.5 | AB89: =$B88*Inputs!$B$15*Curves!C20*(1-Inputs!$B$16) -> 2587.5 | AC89: =$B88*Inputs!$B$15*Curves!C21*(1-Inputs!$B$16) -> 2587.5 | AD89: =$B88*Inputs!$B$15*Curves!C22*(1-Inputs!$B$16) -> 2587.5 | AE89: =$B88*Inputs!$B$15*Curves!C23*(1-Inputs!$B$16) -> 2587.5 | AF89: =$B88*Inputs!$B$15*Curves!C24*(1-Inputs!$B$16) -> 2587.5 | AG89: =$B88*Inputs!$B$15*Curves!C25*(1-Inputs!$B$16) -> 2587.5 | AH89: =$B88*Inputs!$B$15*Curves!C26*(1-Inputs!$B$16) -> 2587.5 | AI89: =$B88*Inputs!$B$15*Curves!C27*(1-Inputs!$B$16) -> 2587.5 | AJ89: =$B88*Inputs!$B$15*Curves!C28*(1-Inputs!$B$16) -> 2587.5 | AK89: =$B88*Inputs!$B$15*Curves!C29*(1-Inputs!$B$16) -> 2587.5 | AL89: =$B88*Inputs!$B$15*Curves!C30*(1-Inputs!$B$16) -> 2587.5 | AM89: =$B88*Inputs!$B$15*Curves!C31*(1-Inputs!$B$16) -> 2587.5
A90: Payback? | D90: 0 | E90: 0 | F90: 0 | G90: 0 | H90: 0 | I90: 0 | J90: 0 | K90: 0 | L90: 0 | M90: "N" | N90: =IF($B88=0, "N", IF(M93>=$B88, "Y", "N")) -> N | O90: =IF($B88=0, "N", IF(N93>=$B88, "Y", "N")) -> N | P90: =IF($B88=0, "N", IF(O93>=$B88, "Y", "N")) -> N | Q90: =IF($B88=0, "N", IF(P93>=$B88, "Y", "N")) -> Y | R90: =IF($B88=0, "N", IF(Q93>=$B88, "Y", "N")) -> Y | S90: =IF($B88=0, "N", IF(R93>=$B88, "Y", "N")) -> Y | T90: =IF($B88=0, "N", IF(S93>=$B88, "Y", "N")) -> Y | U90: =IF($B88=0, "N", IF(T93>=$B88, "Y", "N")) -> Y | ... AM90: =IF($B88=0, "N", IF(AL93>=$B88, "Y", "N")) -> Y
A91: Interest | D91: 0 | E91: 0 | F91: 0 | G91: 0 | H91: 0 | I91: 0 | J91: 0 | K91: 0 | L91: 0 | M91: 0 | N91: =IF(AND(N90="Y", M94="N"), $B88*Inputs!$B$12/12, 0) -> 0 | O91: =IF(AND(O90="Y", N94="N"), $B88*Inputs!$B$12/12, 0) -> 0 | P91: =IF(AND(P90="Y", O94="N"), $B88*Inputs!$B$12/12, 0) -> 0 | Q91: =IF(AND(Q90="Y", P94="N"), $B88*Inputs!$B$12/12, 0) -> 0 | R91: =IF(AND(R90="Y", Q94="N"), $B88*Inputs!$B$12/12, 0) -> 0 | S91: =IF(AND(S90="Y", R94="N"), $B88*Inputs!$B$12/12, 0) -> 0 | T91: =IF(AND(T90="Y", S94="N"), $B88*Inputs!$B$12/12, 0) -> 0 | U91: =IF(AND(U90="Y", T94="N"), $B88*Inputs!$B$12/12, 0) -> 0 | ... AM91: =IF(AND(AM90="Y", AL94="N"), $B88*Inputs!$B$12/12, 0) -> 0
A92: PVX Gets | D92: 0 | E92: 0 | F92: 0 | G92: 0 | H92: 0 | I92: 0 | J92: 0 | K92: 0 | L92: 0 | M92: =IF($B88=0, 0, MIN(M89, $C88)) -> 163496.36 | N92: =IF($B88=0, 0, IF(M94="Y", 0, IF(N90="N", MIN(N89, $C88-M93), MIN(N89*0.5+N91, $C88-M93)))) -> 77960.667 | O92: =IF($B88=0, 0, IF(N94="Y", 0, IF(O90="N", MIN(O89, $C88-N93), MIN(O89*0.5+O91, $C88-N93)))) -> 49973.593 | P92: =IF($B88=0, 0, IF(O94="Y", 0, IF(P90="N", MIN(P89, $C88-O93), MIN(P89*0.5+P91, $C88-O93)))) -> 23569.378 | Q92: =IF($B88=0, 0, IF(P94="Y", 0, IF(Q90="N", MIN(Q89, $C88-P93), MIN(Q89*0.5+Q91, $C88-P93)))) -> 0 | R92: =IF($B88=0, 0, IF(Q94="Y", 0, IF(R90="N", MIN(R89, $C88-Q93), MIN(R89*0.5+R91, $C88-Q93)))) -> 0 | S92: =IF($B88=0, 0, IF(R94="Y", 0, IF(S90="N", MIN(S89, $C88-R93), MIN(S89*0.5+S91, $C88-R93)))) -> 0 | T92: =IF($B88=0, 0, IF(S94="Y", 0, IF(T90="N", MIN(T89, $C88-S93), MIN(T89*0.5+T91, $C88-S93)))) -> 0 | U92: =IF($B88=0, 0, IF(T94="Y", 0, IF(U90="N", MIN(U89, $C88-T93), MIN(U89*0.5+U91, $C88-T93)))) -> 0 | ... AM92: =IF($B88=0, 0, IF(AL94="Y", 0, IF(AM90="N", MIN(AM89, $C88-AL93), MIN(AM89*0.5+AM91, $C88-AL93)))) -> 0
A93: Cum Paid | D93: 0 | E93: 0 | F93: 0 | G93: 0 | H93: 0 | I93: 0 | J93: 0 | K93: 0 | L93: 0 | M93: =M92 -> 163496.36 | N93: =M93+N92 -> 241457.03 | O93: =N93+O92 -> 291430.62 | P93: =O93+P92 -> 315000 | Q93: =P93+Q92 -> 315000 | R93: =Q93+R92 -> 315000 | S93: =R93+S92 -> 315000 | T93: =S93+T92 -> 315000 | U93: =T93+U92 -> 315000 | ... AM93: =AL93+AM92 -> 315000
A94: Cap Hit? | D94: 0 | E94: 0 | F94: 0 | G94: 0 | H94: 0 | I94: 0 | J94: 0 | K94: 0 | L94: 0 | M94: =IF(M93>=$C88, "Y", "N") -> N | N94: =IF(N93>=$C88, "Y", "N") -> N | O94: =IF(O93>=$C88, "Y", "N") -> N | P94: =IF(P93>=$C88, "Y", "N") -> Y | Q94: =IF(Q93>=$C88, "Y", "N") -> Y | R94: =IF(R93>=$C88, "Y", "N") -> Y | S94: =IF(S93>=$C88, "Y", "N") -> Y | T94: =IF(T93>=$C88, "Y", "N") -> Y | ... AM94: =IF(AM93>=$C88, "Y", "N") -> Y
A95: Co Gets | D95: 0 | E95: 0 | F95: 0 | G95: 0 | H95: 0 | I95: 0 | J95: 0 | K95: 0 | L95: 0 | M95: =M89-M92 -> 0 | N95: =N89-N92 -> 0 | O95: =O89-O92 -> 0 | P95: =P89-P92 -> 11590.041 | Q95: =Q89-Q92 -> 20903.323 | R95: =R89-R92 -> 18738.275 | S95: =S89-S92 -> 16183.208 | T95: =T89-T92 -> 14298.768 | ... AM95: =AM89-AM92 -> 2587.5
A97: =Acquisition_Plan!A14 -> 2026-11-28 | B97: =Acquisition_Plan!E14 -> 350000 | C97: =B97*(1+Inputs!$B$12) -> 367500
A98: This Mo Net | D98: 0 | E98: 0 | F98: 0 | G98: 0 | H98: 0 | I98: 0 | J98: 0 | K98: 0 | L98: 0 | M98: 0 | N98: =$B97*Inputs!$B$15*Curves!C5*(1-Inputs!$B$16) -> 190745.76 | O98: =$B97*Inputs!$B$15*Curves!C6*(1-Inputs!$B$16) -> 90954.111 | P98: =$B97*Inputs!$B$15*Curves!C7*(1-Inputs!$B$16) -> 58302.525 | Q98: =$B97*Inputs!$B$15*Curves!C8*(1-Inputs!$B$16) -> 41019.322 | R98: =$B97*Inputs!$B$15*Curves!C9*(1-Inputs!$B$16) -> 24387.21 | S98: =$B97*Inputs!$B$15*Curves!C10*(1-Inputs!$B$16) -> 21861.321 | T98: =$B97*Inputs!$B$15*Curves!C11*(1-Inputs!$B$16) -> 18880.41 | U98: =$B97*Inputs!$B$15*Curves!C12*(1-Inputs!$B$16) -> 16681.896 | V98: =$B97*Inputs!$B$15*Curves!C13*(1-Inputs!$B$16) -> 14912.946 | W98: =$B97*Inputs!$B$15*Curves!C14*(1-Inputs!$B$16) -> 17329.503 | X98: =$B97*Inputs!$B$15*Curves!C15*(1-Inputs!$B$16) -> 12075 | Y98: =$B97*Inputs!$B$15*Curves!C16*(1-Inputs!$B$16) -> 12075 | Z98: =$B97*Inputs!$B$15*Curves!C17*(1-Inputs!$B$16) -> 12075 | AA98: =$B97*Inputs!$B$15*Curves!C18*(1-Inputs!$B$16) -> 3018.75 | AB98: =$B97*Inputs!$B$15*Curves!C19*(1-Inputs!$B$16) -> 3018.75 | AC98: =$B97*Inputs!$B$15*Curves!C20*(1-Inputs!$B$16) -> 3018.75 | AD98: =$B97*Inputs!$B$15*Curves!C21*(1-Inputs!$B$16) -> 3018.75 | AE98: =$B97*Inputs!$B$15*Curves!C22*(1-Inputs!$B$16) -> 3018.75 | AF98: =$B97*Inputs!$B$15*Curves!C23*(1-Inputs!$B$16) -> 3018.75 | AG98: =$B97*Inputs!$B$15*Curves!C24*(1-Inputs!$B$16) -> 3018.75 | AH98: =$B97*Inputs!$B$15*Curves!C25*(1-Inputs!$B$16) -> 3018.75 | AI98: =$B97*Inputs!$B$15*Curves!C26*(1-Inputs!$B$16) -> 3018.75 | AJ98: =$B97*Inputs!$B$15*Curves!C27*(1-Inputs!$B$16) -> 3018.75 | AK98: =$B97*Inputs!$B$15*Curves!C28*(1-Inputs!$B$16) -> 3018.75 | AL98: =$B97*Inputs!$B$15*Curves!C29*(1-Inputs!$B$16) -> 3018.75 | AM98: =$B97*Inputs!$B$15*Curves!C30*(1-Inputs!$B$16) -> 3018.75
A99: Payback? | D99: 0 | E99: 0 | F99: 0 | G99: 0 | H99: 0 | I99: 0 | J99: 0 | K99: 0 | L99: 0 | M99: 0 | N99: "N" | O99: =IF($B97=0, "N", IF(N102>=$B97, "Y", "N")) -> N | P99: =IF($B97=0, "N", IF(O102>=$B97, "Y", "N")) -> N | Q99: =IF($B97=0, "N", IF(P102>=$B97, "Y", "N")) -> N | R99: =IF($B97=0, "N", IF(Q102>=$B97, "Y", "N")) -> Y | S99: =IF($B97=0, "N", IF(R102>=$B97, "Y", "N")) -> Y | T99: =IF($B97=0, "N", IF(S102>=$B97, "Y", "N")) -> Y | U99: =IF($B97=0, "N", IF(T102>=$B97, "Y", "N")) -> Y | V99: =IF($B97=0, "N", IF(U102>=$B97, "Y", "N")) -> Y | ... AM99: =IF($B97=0, "N", IF(AL102>=$B97, "Y", "N")) -> Y
A100: Interest | D100: 0 | E100: 0 | F100: 0 | G100: 0 | H100: 0 | I100: 0 | J100: 0 | K100: 0 | L100: 0 | M100: 0 | N100: 0 | O100: =IF(AND(O99="Y", N103="N"), $B97*Inputs!$B$12/12, 0) -> 0 | P100: =IF(AND(P99="Y", O103="N"), $B97*Inputs!$B$12/12, 0) -> 0 | Q100: =IF(AND(Q99="Y", P103="N"), $B97*Inputs!$B$12/12, 0) -> 0 | R100: =IF(AND(R99="Y", Q103="N"), $B97*Inputs!$B$12/12, 0) -> 0 | S100: =IF(AND(S99="Y", R103="N"), $B97*Inputs!$B$12/12, 0) -> 0 | T100: =IF(AND(T99="Y", S103="N"), $B97*Inputs!$B$12/12, 0) -> 0 | U100: =IF(AND(U99="Y", T103="N"), $B97*Inputs!$B$12/12, 0) -> 0 | V100: =IF(AND(V99="Y", U103="N"), $B97*Inputs!$B$12/12, 0) -> 0 | ... AM100: =IF(AND(AM99="Y", AL103="N"), $B97*Inputs!$B$12/12, 0) -> 0
A101: PVX Gets | D101: 0 | E101: 0 | F101: 0 | G101: 0 | H101: 0 | I101: 0 | J101: 0 | K101: 0 | L101: 0 | M101: 0 | N101: =IF($B97=0, 0, MIN(N98, $C97)) -> 190745.76 | O101: =IF($B97=0, 0, IF(N103="Y", 0, IF(O99="N", MIN(O98, $C97-N102), MIN(O98*0.5+O100, $C97-N102)))) -> 90954.111 | P101: =IF($B97=0, 0, IF(O103="Y", 0, IF(P99="N", MIN(P98, $C97-O102), MIN(P98*0.5+P100, $C97-O102)))) -> 58302.525 | Q101: =IF($B97=0, 0, IF(P103="Y", 0, IF(Q99="N", MIN(Q98, $C97-P102), MIN(Q98*0.5+Q100, $C97-P102)))) -> 27497.608 | R101: =IF($B97=0, 0, IF(Q103="Y", 0, IF(R99="N", MIN(R98, $C97-Q102), MIN(R98*0.5+R100, $C97-Q102)))) -> 0 | S101: =IF($B97=0, 0, IF(R103="Y", 0, IF(S99="N", MIN(S98, $C97-R102), MIN(S98*0.5+S100, $C97-R102)))) -> 0 | T101: =IF($B97=0, 0, IF(S103="Y", 0, IF(T99="N", MIN(T98, $C97-S102), MIN(T98*0.5+T100, $C97-S102)))) -> 0 | U101: =IF($B97=0, 0, IF(T103="Y", 0, IF(U99="N", MIN(U98, $C97-T102), MIN(U98*0.5+U100, $C97-T102)))) -> 0 | V101: =IF($B97=0, 0, IF(U103="Y", 0, IF(V99="N", MIN(V98, $C97-U102), MIN(V98*0.5+V100, $C97-U102)))) -> 0 | ... AM101: =IF($B97=0, 0, IF(AL103="Y", 0, IF(AM99="N", MIN(AM98, $C97-AL102), MIN(AM98*0.5+AM100, $C97-AL102)))) -> 0
A102: Cum Paid | D102: 0 | E102: 0 | F102: 0 | G102: 0 | H102: 0 | I102: 0 | J102: 0 | K102: 0 | L102: 0 | M102: 0 | N102: =N101 -> 190745.76 | O102: =N102+O101 -> 281699.87 | P102: =O102+P101 -> 340002.39 | Q102: =P102+Q101 -> 367500 | R102: =Q102+R101 -> 367500 | S102: =R102+S101 -> 367500 | T102: =S102+T101 -> 367500 | U102: =T102+U101 -> 367500 | V102: =U102+V101 -> 367500 | ... AM102: =AL102+AM101 -> 367500
A103: Cap Hit? | D103: 0 | E103: 0 | F103: 0 | G103: 0 | H103: 0 | I103: 0 | J103: 0 | K103: 0 | L103: 0 | M103: 0 | N103: =IF(N102>=$C97, "Y", "N") -> N | O103: =IF(O102>=$C97, "Y", "N") -> N | P103: =IF(P102>=$C97, "Y", "N") -> N | Q103: =IF(Q102>=$C97, "Y", "N") -> Y | R103: =IF(R102>=$C97, "Y", "N") -> Y | S103: =IF(S102>=$C97, "Y", "N") -> Y | T103: =IF(T102>=$C97, "Y", "N") -> Y | U103: =IF(U102>=$C97, "Y", "N") -> Y | ... AM103: =IF(AM102>=$C97, "Y", "N") -> Y
A104: Co Gets | D104: 0 | E104: 0 | F104: 0 | G104: 0 | H104: 0 | I104: 0 | J104: 0 | K104: 0 | L104: 0 | M104: 0 | N104: =N98-N101 -> 0 | O104: =O98-O101 -> 0 | P104: =P98-P101 -> 0 | Q104: =Q98-Q101 -> 13521.714 | R104: =R98-R101 -> 24387.21 | S104: =S98-S101 -> 21861.321 | T104: =T98-T101 -> 18880.41 | U104: =U98-U101 -> 16681.896 | ... AM104: =AM98-AM101 -> 3018.75
A106: =Acquisition_Plan!A15 -> 2026-12-28 | B106: =Acquisition_Plan!E15 -> 350000 | C106: =B106*(1+Inputs!$B$12) -> 367500
A107: This Mo Net | D107: 0 | E107: 0 | F107: 0 | G107: 0 | H107: 0 | I107: 0 | J107: 0 | K107: 0 | L107: 0 | M107: 0 | N107: 0 | O107: =$B106*Inputs!$B$15*Curves!C5*(1-Inputs!$B$16) -> 190745.76 | P107: =$B106*Inputs!$B$15*Curves!C6*(1-Inputs!$B$16) -> 90954.111 | Q107: =$B106*Inputs!$B$15*Curves!C7*(1-Inputs!$B$16) -> 58302.525 | R107: =$B106*Inputs!$B$15*Curves!C8*(1-Inputs!$B$16) -> 41019.322 | S107: =$B106*Inputs!$B$15*Curves!C9*(1-Inputs!$B$16) -> 24387.21 | T107: =$B106*Inputs!$B$15*Curves!C10*(1-Inputs!$B$16) -> 21861.321 | U107: =$B106*Inputs!$B$15*Curves!C11*(1-Inputs!$B$16) -> 18880.41 | V107: =$B106*Inputs!$B$15*Curves!C12*(1-Inputs!$B$16) -> 16681.896 | W107: =$B106*Inputs!$B$15*Curves!C13*(1-Inputs!$B$16) -> 14912.946 | X107: =$B106*Inputs!$B$15*Curves!C14*(1-Inputs!$B$16) -> 17329.503 | Y107: =$B106*Inputs!$B$15*Curves!C15*(1-Inputs!$B$16) -> 12075 | Z107: =$B106*Inputs!$B$15*Curves!C16*(1-Inputs!$B$16) -> 12075 | AA107: =$B106*Inputs!$B$15*Curves!C17*(1-Inputs!$B$16) -> 12075 | AB107: =$B106*Inputs!$B$15*Curves!C18*(1-Inputs!$B$16) -> 3018.75 | AC107: =$B106*Inputs!$B$15*Curves!C19*(1-Inputs!$B$16) -> 3018.75 | AD107: =$B106*Inputs!$B$15*Curves!C20*(1-Inputs!$B$16) -> 3018.75 | AE107: =$B106*Inputs!$B$15*Curves!C21*(1-Inputs!$B$16) -> 3018.75 | AF107: =$B106*Inputs!$B$15*Curves!C22*(1-Inputs!$B$16) -> 3018.75 | AG107: =$B106*Inputs!$B$15*Curves!C23*(1-Inputs!$B$16) -> 3018.75 | AH107: =$B106*Inputs!$B$15*Curves!C24*(1-Inputs!$B$16) -> 3018.75 | AI107: =$B106*Inputs!$B$15*Curves!C25*(1-Inputs!$B$16) -> 3018.75 | AJ107: =$B106*Inputs!$B$15*Curves!C26*(1-Inputs!$B$16) -> 3018.75 | AK107: =$B106*Inputs!$B$15*Curves!C27*(1-Inputs!$B$16) -> 3018.75 | AL107: =$B106*Inputs!$B$15*Curves!C28*(1-Inputs!$B$16) -> 3018.75 | AM107: =$B106*Inputs!$B$15*Curves!C29*(1-Inputs!$B$16) -> 3018.75
A108: Payback? | D108: 0 | E108: 0 | F108: 0 | G108: 0 | H108: 0 | I108: 0 | J108: 0 | K108: 0 | L108: 0 | M108: 0 | N108: 0 | O108: "N" | P108: =IF($B106=0, "N", IF(O111>=$B106, "Y", "N")) -> N | Q108: =IF($B106=0, "N", IF(P111>=$B106, "Y", "N")) -> N | R108: =IF($B106=0, "N", IF(Q111>=$B106, "Y", "N")) -> N | S108: =IF($B106=0, "N", IF(R111>=$B106, "Y", "N")) -> Y | T108: =IF($B106=0, "N", IF(S111>=$B106, "Y", "N")) -> Y | U108: =IF($B106=0, "N", IF(T111>=$B106, "Y", "N")) -> Y | V108: =IF($B106=0, "N", IF(U111>=$B106, "Y", "N")) -> Y | W108: =IF($B106=0, "N", IF(V111>=$B106, "Y", "N")) -> Y | ... AM108: =IF($B106=0, "N", IF(AL111>=$B106, "Y", "N")) -> Y
A109: Interest | D109: 0 | E109: 0 | F109: 0 | G109: 0 | H109: 0 | I109: 0 | J109: 0 | K109: 0 | L109: 0 | M109: 0 | N109: 0 | O109: 0 | P109: =IF(AND(P108="Y", O112="N"), $B106*Inputs!$B$12/12, 0) -> 0 | Q109: =IF(AND(Q108="Y", P112="N"), $B106*Inputs!$B$12/12, 0) -> 0 | R109: =IF(AND(R108="Y", Q112="N"), $B106*Inputs!$B$12/12, 0) -> 0 | S109: =IF(AND(S108="Y", R112="N"), $B106*Inputs!$B$12/12, 0) -> 0 | T109: =IF(AND(T108="Y", S112="N"), $B106*Inputs!$B$12/12, 0) -> 0 | U109: =IF(AND(U108="Y", T112="N"), $B106*Inputs!$B$12/12, 0) -> 0 | V109: =IF(AND(V108="Y", U112="N"), $B106*Inputs!$B$12/12, 0) -> 0 | W109: =IF(AND(W108="Y", V112="N"), $B106*Inputs!$B$12/12, 0) -> 0 | ... AM109: =IF(AND(AM108="Y", AL112="N"), $B106*Inputs!$B$12/12, 0) -> 0
A110: PVX Gets | D110: 0 | E110: 0 | F110: 0 | G110: 0 | H110: 0 | I110: 0 | J110: 0 | K110: 0 | L110: 0 | M110: 0 | N110: 0 | O110: =IF($B106=0, 0, MIN(O107, $C106)) -> 190745.76 | P110: =IF($B106=0, 0, IF(O112="Y", 0, IF(P108="N", MIN(P107, $C106-O111), MIN(P107*0.5+P109, $C106-O111)))) -> 90954.111 | Q110: =IF($B106=0, 0, IF(P112="Y", 0, IF(Q108="N", MIN(Q107, $C106-P111), MIN(Q107*0.5+Q109, $C106-P111)))) -> 58302.525 | R110: =IF($B106=0, 0, IF(Q112="Y", 0, IF(R108="N", MIN(R107, $C106-Q111), MIN(R107*0.5+R109, $C106-Q111)))) -> 27497.608 | S110: =IF($B106=0, 0, IF(R112="Y", 0, IF(S108="N", MIN(S107, $C106-R111), MIN(S107*0.5+S109, $C106-R111)))) -> 0 | T110: =IF($B106=0, 0, IF(S112="Y", 0, IF(T108="N", MIN(T107, $C106-S111), MIN(T107*0.5+T109, $C106-S111)))) -> 0 | U110: =IF($B106=0, 0, IF(T112="Y", 0, IF(U108="N", MIN(U107, $C106-T111), MIN(U107*0.5+U109, $C106-T111)))) -> 0 | V110: =IF($B106=0, 0, IF(U112="Y", 0, IF(V108="N", MIN(V107, $C106-U111), MIN(V107*0.5+V109, $C106-U111)))) -> 0 | W110: =IF($B106=0, 0, IF(V112="Y", 0, IF(W108="N", MIN(W107, $C106-V111), MIN(W107*0.5+W109, $C106-V111)))) -> 0 | ... AM110: =IF($B106=0, 0, IF(AL112="Y", 0, IF(AM108="N", MIN(AM107, $C106-AL111), MIN(AM107*0.5+AM109, $C106-AL111)))) -> 0
A111: Cum Paid | D111: 0 | E111: 0 | F111: 0 | G111: 0 | H111: 0 | I111: 0 | J111: 0 | K111: 0 | L111: 0 | M111: 0 | N111: 0 | O111: =O110 -> 190745.76 | P111: =O111+P110 -> 281699.87 | Q111: =P111+Q110 -> 340002.39 | R111: =Q111+R110 -> 367500 | S111: =R111+S110 -> 367500 | T111: =S111+T110 -> 367500 | U111: =T111+U110 -> 367500 | V111: =U111+V110 -> 367500 | W111: =V111+W110 -> 367500 | ... AM111: =AL111+AM110 -> 367500
A112: Cap Hit? | D112: 0 | E112: 0 | F112: 0 | G112: 0 | H112: 0 | I112: 0 | J112: 0 | K112: 0 | L112: 0 | M112: 0 | N112: 0 | O112: =IF(O111>=$C106, "Y", "N") -> N | P112: =IF(P111>=$C106, "Y", "N") -> N | Q112: =IF(Q111>=$C106, "Y", "N") -> N | R112: =IF(R111>=$C106, "Y", "N") -> Y | S112: =IF(S111>=$C106, "Y", "N") -> Y | T112: =IF(T111>=$C106, "Y", "N") -> Y | U112: =IF(U111>=$C106, "Y", "N") -> Y | V112: =IF(V111>=$C106, "Y", "N") -> Y | ... AM112: =IF(AM111>=$C106, "Y", "N") -> Y
...

Sheet PVX_Summary
A1: PVX Monthly Summary
A3: Month | B3: PVX Draw | C3: PVX Gets | D3: Company Gets
A4: 2026-02-01 | B4: =Acquisition_Plan!E4 -> 0 | C4: =PVX_Detail!D11+PVX_Detail!D20+PVX_Detail!D29+PVX_Detail!D38+PVX_Detail!D47+PVX_Detail!D56+PVX_Detail!D65+PVX_Detail!D74+PVX_Detail!D83+PVX_Detail!D92+PVX_Detail!D101+PVX_Detail!D110+PVX_Detail!D119+PVX_Detail!D128+PVX_Detail!D137+PVX_Detail!D146+PVX_Detail!D155+PVX_Detail!D164+PVX_Detail!D173+PVX_Detail!D182+PVX_Detail!D191+PVX_Detail!D200+PVX_Detail!D209+PVX_Detail!D218+PVX_Detail!D227+PVX_Detail!D236+PVX_Detail!D245+PVX_Detail!D254+PVX_Detail!D263+PVX_Detail!D272+PVX_Detail!D281+PVX_Detail!D290+PVX_Detail!D299+PVX_Detail!D308+PVX_Detail!D317+PVX_Detail!D326 -> 0 | D4: =PVX_Detail!D14+PVX_Detail!D23+PVX_Detail!D32+PVX_Detail!D41+PVX_Detail!D50+PVX_Detail!D59+PVX_Detail!D68+PVX_Detail!D77+PVX_Detail!D86+PVX_Detail!D95+PVX_Detail!D104+PVX_Detail!D113+PVX_Detail!D122+PVX_Detail!D131+PVX_Detail!D140+PVX_Detail!D149+PVX_Detail!D158+PVX_Detail!D167+PVX_Detail!D176+PVX_Detail!D185+PVX_Detail!D194+PVX_Detail!D203+PVX_Detail!D212+PVX_Detail!D221+PVX_Detail!D230+PVX_Detail!D239+PVX_Detail!D248+PVX_Detail!D257+PVX_Detail!D266+PVX_Detail!D275+PVX_Detail!D284+PVX_Detail!D293+PVX_Detail!D302+PVX_Detail!D311+PVX_Detail!D320+PVX_Detail!D329 -> 0
A5: 2026-03-03 | B5: =Acquisition_Plan!E5 -> 0 | C5: =PVX_Detail!E11+PVX_Detail!E20+PVX_Detail!E29+PVX_Detail!E38+PVX_Detail!E47+PVX_Detail!E56+PVX_Detail!E65+PVX_Detail!E74+PVX_Detail!E83+PVX_Detail!E92+PVX_Detail!E101+PVX_Detail!E110+PVX_Detail!E119+PVX_Detail!E128+PVX_Detail!E137+PVX_Detail!E146+PVX_Detail!E155+PVX_Detail!E164+PVX_Detail!E173+PVX_Detail!E182+PVX_Detail!E191+PVX_Detail!E200+PVX_Detail!E209+PVX_Detail!E218+PVX_Detail!E227+PVX_Detail!E236+PVX_Detail!E245+PVX_Detail!E254+PVX_Detail!E263+PVX_Detail!E272+PVX_Detail!E281+PVX_Detail!E290+PVX_Detail!E299+PVX_Detail!E308+PVX_Detail!E317+PVX_Detail!E326 -> 0 | D5: =PVX_Detail!E14+PVX_Detail!E23+PVX_Detail!E32+PVX_Detail!E41+PVX_Detail!E50+PVX_Detail!E59+PVX_Detail!E68+PVX_Detail!E77+PVX_Detail!E86+PVX_Detail!E95+PVX_Detail!E104+PVX_Detail!E113+PVX_Detail!E122+PVX_Detail!E131+PVX_Detail!E140+PVX_Detail!E149+PVX_Detail!E158+PVX_Detail!E167+PVX_Detail!E176+PVX_Detail!E185+PVX_Detail!E194+PVX_Detail!E203+PVX_Detail!E212+PVX_Detail!E221+PVX_Detail!E230+PVX_Detail!E239+PVX_Detail!E248+PVX_Detail!E257+PVX_Detail!E266+PVX_Detail!E275+PVX_Detail!E284+PVX_Detail!E293+PVX_Detail!E302+PVX_Detail!E311+PVX_Detail!E320+PVX_Detail!E329 -> 0
A6: 2026-04-02 | B6: =Acquisition_Plan!E6 -> 150000 | C6: =PVX_Detail!F11+PVX_Detail!F20+PVX_Detail!F29+PVX_Detail!F38+PVX_Detail!F47+PVX_Detail!F56+PVX_Detail!F65+PVX_Detail!F74+PVX_Detail!F83+PVX_Detail!F92+PVX_Detail!F101+PVX_Detail!F110+PVX_Detail!F119+PVX_Detail!F128+PVX_Detail!F137+PVX_Detail!F146+PVX_Detail!F155+PVX_Detail!F164+PVX_Detail!F173+PVX_Detail!F182+PVX_Detail!F191+PVX_Detail!F200+PVX_Detail!F209+PVX_Detail!F218+PVX_Detail!F227+PVX_Detail!F236+PVX_Detail!F245+PVX_Detail!F254+PVX_Detail!F263+PVX_Detail!F272+PVX_Detail!F281+PVX_Detail!F290+PVX_Detail!F299+PVX_Detail!F308+PVX_Detail!F317+PVX_Detail!F326 -> 81748.181 | D6: =PVX_Detail!F14+PVX_Detail!F23+PVX_Detail!F32+PVX_Detail!F41+PVX_Detail!F50+PVX_Detail!F59+PVX_Detail!F68+PVX_Detail!F77+PVX_Detail!F86+PVX_Detail!F95+PVX_Detail!F104+PVX_Detail!F113+PVX_Detail!F122+PVX_Detail!F131+PVX_Detail!F140+PVX_Detail!F149+PVX_Detail!F158+PVX_Detail!F167+PVX_Detail!F176+PVX_Detail!F185+PVX_Detail!F194+PVX_Detail!F203+PVX_Detail!F212+PVX_Detail!F221+PVX_Detail!F230+PVX_Detail!F239+PVX_Detail!F248+PVX_Detail!F257+PVX_Detail!F266+PVX_Detail!F275+PVX_Detail!F284+PVX_Detail!F293+PVX_Detail!F302+PVX_Detail!F311+PVX_Detail!F320+PVX_Detail!F329 -> 0
A7: 2026-05-02 | B7: =Acquisition_Plan!E7 -> 150000 | C7: =PVX_Detail!G11+PVX_Detail!G20+PVX_Detail!G29+PVX_Detail!G38+PVX_Detail!G47+PVX_Detail!G56+PVX_Detail!G65+PVX_Detail!G74+PVX_Detail!G83+PVX_Detail!G92+PVX_Detail!G101+PVX_Detail!G110+PVX_Detail!G119+PVX_Detail!G128+PVX_Detail!G137+PVX_Detail!G146+PVX_Detail!G155+PVX_Detail!G164+PVX_Detail!G173+PVX_Detail!G182+PVX_Detail!G191+PVX_Detail!G200+PVX_Detail!G209+PVX_Detail!G218+PVX_Detail!G227+PVX_Detail!G236+PVX_Detail!G245+PVX_Detail!G254+PVX_Detail!G263+PVX_Detail!G272+PVX_Detail!G281+PVX_Detail!G290+PVX_Detail!G299+PVX_Detail!G308+PVX_Detail!G317+PVX_Detail!G326 -> 120728.51 | D7: =PVX_Detail!G14+PVX_Detail!G23+PVX_Detail!G32+PVX_Detail!G41+PVX_Detail!G50+PVX_Detail!G59+PVX_Detail!G68+PVX_Detail!G77+PVX_Detail!G86+PVX_Detail!G95+PVX_Detail!G104+PVX_Detail!G113+PVX_Detail!G122+PVX_Detail!G131+PVX_Detail!G140+PVX_Detail!G149+PVX_Detail!G158+PVX_Detail!G167+PVX_Detail!G176+PVX_Detail!G185+PVX_Detail!G194+PVX_Detail!G203+PVX_Detail!G212+PVX_Detail!G221+PVX_Detail!G230+PVX_Detail!G239+PVX_Detail!G248+PVX_Detail!G257+PVX_Detail!G266+PVX_Detail!G275+PVX_Detail!G284+PVX_Detail!G293+PVX_Detail!G302+PVX_Detail!G311+PVX_Detail!G320+PVX_Detail!G329 -> 0
A8: 2026-06-01 | B8: =Acquisition_Plan!E8 -> 200000 | C8: =PVX_Detail!H11+PVX_Detail!H20+PVX_Detail!H29+PVX_Detail!H38+PVX_Detail!H47+PVX_Detail!H56+PVX_Detail!H65+PVX_Detail!H74+PVX_Detail!H83+PVX_Detail!H92+PVX_Detail!H101+PVX_Detail!H110+PVX_Detail!H119+PVX_Detail!H128+PVX_Detail!H137+PVX_Detail!H146+PVX_Detail!H155+PVX_Detail!H164+PVX_Detail!H173+PVX_Detail!H182+PVX_Detail!H191+PVX_Detail!H200+PVX_Detail!H209+PVX_Detail!H218+PVX_Detail!H227+PVX_Detail!H236+PVX_Detail!H245+PVX_Detail!H254+PVX_Detail!H263+PVX_Detail!H272+PVX_Detail!H281+PVX_Detail!H290+PVX_Detail!H299+PVX_Detail!H308+PVX_Detail!H317+PVX_Detail!H326 -> 172964.7 | D8: =PVX_Detail!H14+PVX_Detail!H23+PVX_Detail!H32+PVX_Detail!H41+PVX_Detail!H50+PVX_Detail!H59+PVX_Detail!H68+PVX_Detail!H77+PVX_Detail!H86+PVX_Detail!H95+PVX_Detail!H104+PVX_Detail!H113+PVX_Detail!H122+PVX_Detail!H131+PVX_Detail!H140+PVX_Detail!H149+PVX_Detail!H158+PVX_Detail!H167+PVX_Detail!H176+PVX_Detail!H185+PVX_Detail!H194+PVX_Detail!H203+PVX_Detail!H212+PVX_Detail!H221+PVX_Detail!H230+PVX_Detail!H239+PVX_Detail!H248+PVX_Detail!H257+PVX_Detail!H266+PVX_Detail!H275+PVX_Detail!H284+PVX_Detail!H293+PVX_Detail!H302+PVX_Detail!H311+PVX_Detail!H320+PVX_Detail!H329 -> 0
A9: 2026-07-01 | B9: =Acquisition_Plan!E9 -> 200000 | C9: =PVX_Detail!I11+PVX_Detail!I20+PVX_Detail!I29+PVX_Detail!I38+PVX_Detail!I47+PVX_Detail!I56+PVX_Detail!I65+PVX_Detail!I74+PVX_Detail!I83+PVX_Detail!I92+PVX_Detail!I101+PVX_Detail!I110+PVX_Detail!I119+PVX_Detail!I128+PVX_Detail!I137+PVX_Detail!I146+PVX_Detail!I155+PVX_Detail!I164+PVX_Detail!I173+PVX_Detail!I182+PVX_Detail!I191+PVX_Detail!I200+PVX_Detail!I209+PVX_Detail!I218+PVX_Detail!I227+PVX_Detail!I236+PVX_Detail!I245+PVX_Detail!I254+PVX_Detail!I263+PVX_Detail!I272+PVX_Detail!I281+PVX_Detail!I290+PVX_Detail!I299+PVX_Detail!I308+PVX_Detail!I317+PVX_Detail!I326 -> 197742.84 | D9: =PVX_Detail!I14+PVX_Detail!I23+PVX_Detail!I32+PVX_Detail!I41+PVX_Detail!I50+PVX_Detail!I59+PVX_Detail!I68+PVX_Detail!I77+PVX_Detail!I86+PVX_Detail!I95+PVX_Detail!I104+PVX_Detail!I113+PVX_Detail!I122+PVX_Detail!I131+PVX_Detail!I140+PVX_Detail!I149+PVX_Detail!I158+PVX_Detail!I167+PVX_Detail!I176+PVX_Detail!I185+PVX_Detail!I194+PVX_Detail!I203+PVX_Detail!I212+PVX_Detail!I221+PVX_Detail!I230+PVX_Detail!I239+PVX_Detail!I248+PVX_Detail!I257+PVX_Detail!I266+PVX_Detail!I275+PVX_Detail!I284+PVX_Detail!I293+PVX_Detail!I302+PVX_Detail!I311+PVX_Detail!I320+PVX_Detail!I329 -> 5795.0205
A10: 2026-07-31 | B10: =Acquisition_Plan!E10 -> 250000 | C10: =PVX_Detail!J11+PVX_Detail!J20+PVX_Detail!J29+PVX_Detail!J38+PVX_Detail!J47+PVX_Detail!J56+PVX_Detail!J65+PVX_Detail!J74+PVX_Detail!J83+PVX_Detail!J92+PVX_Detail!J101+PVX_Detail!J110+PVX_Detail!J119+PVX_Detail!J128+PVX_Detail!J137+PVX_Detail!J146+PVX_Detail!J155+PVX_Detail!J164+PVX_Detail!J173+PVX_Detail!J182+PVX_Detail!J191+PVX_Detail!J200+PVX_Detail!J209+PVX_Detail!J218+PVX_Detail!J227+PVX_Detail!J236+PVX_Detail!J245+PVX_Detail!J254+PVX_Detail!J263+PVX_Detail!J272+PVX_Detail!J281+PVX_Detail!J290+PVX_Detail!J299+PVX_Detail!J308+PVX_Detail!J317+PVX_Detail!J326 -> 233321.16 | D10: =PVX_Detail!J14+PVX_Detail!J23+PVX_Detail!J32+PVX_Detail!J41+PVX_Detail!J50+PVX_Detail!J59+PVX_Detail!J68+PVX_Detail!J77+PVX_Detail!J86+PVX_Detail!J95+PVX_Detail!J104+PVX_Detail!J113+PVX_Detail!J122+PVX_Detail!J131+PVX_Detail!J140+PVX_Detail!J149+PVX_Detail!J158+PVX_Detail!J167+PVX_Detail!J176+PVX_Detail!J185+PVX_Detail!J194+PVX_Detail!J203+PVX_Detail!J212+PVX_Detail!J221+PVX_Detail!J230+PVX_Detail!J239+PVX_Detail!J248+PVX_Detail!J257+PVX_Detail!J266+PVX_Detail!J275+PVX_Detail!J284+PVX_Detail!J293+PVX_Detail!J302+PVX_Detail!J311+PVX_Detail!J320+PVX_Detail!J329 -> 16246.682
A11: 2026-08-30 | B11: =Acquisition_Plan!E11 -> 250000 | C11: =PVX_Detail!K11+PVX_Detail!K20+PVX_Detail!K29+PVX_Detail!K38+PVX_Detail!K47+PVX_Detail!K56+PVX_Detail!K65+PVX_Detail!K74+PVX_Detail!K83+PVX_Detail!K92+PVX_Detail!K101+PVX_Detail!K110+PVX_Detail!K119+PVX_Detail!K128+PVX_Detail!K137+PVX_Detail!K146+PVX_Detail!K155+PVX_Detail!K164+PVX_Detail!K173+PVX_Detail!K182+PVX_Detail!K191+PVX_Detail!K200+PVX_Detail!K209+PVX_Detail!K218+PVX_Detail!K227+PVX_Detail!K236+PVX_Detail!K245+PVX_Detail!K254+PVX_Detail!K263+PVX_Detail!K272+PVX_Detail!K281+PVX_Detail!K290+PVX_Detail!K299+PVX_Detail!K308+PVX_Detail!K317+PVX_Detail!K326 -> 250242.84 | D11: =PVX_Detail!K14+PVX_Detail!K23+PVX_Detail!K32+PVX_Detail!K41+PVX_Detail!K50+PVX_Detail!K59+PVX_Detail!K68+PVX_Detail!K77+PVX_Detail!K86+PVX_Detail!K95+PVX_Detail!K104+PVX_Detail!K113+PVX_Detail!K122+PVX_Detail!K131+PVX_Detail!K140+PVX_Detail!K149+PVX_Detail!K158+PVX_Detail!K167+PVX_Detail!K176+PVX_Detail!K185+PVX_Detail!K194+PVX_Detail!K203+PVX_Detail!K212+PVX_Detail!K221+PVX_Detail!K230+PVX_Detail!K239+PVX_Detail!K248+PVX_Detail!K257+PVX_Detail!K266+PVX_Detail!K275+PVX_Detail!K284+PVX_Detail!K293+PVX_Detail!K302+PVX_Detail!K311+PVX_Detail!K320+PVX_Detail!K329 -> 27547.493
A12: 2026-09-29 | B12: =Acquisition_Plan!E12 -> 300000 | C12: =PVX_Detail!L11+PVX_Detail!L20+PVX_Detail!L29+PVX_Detail!L38+PVX_Detail!L47+PVX_Detail!L56+PVX_Detail!L65+PVX_Detail!L74+PVX_Detail!L83+PVX_Detail!L92+PVX_Detail!L101+PVX_Detail!L110+PVX_Detail!L119+PVX_Detail!L128+PVX_Detail!L137+PVX_Detail!L146+PVX_Detail!L155+PVX_Detail!L164+PVX_Detail!L173+PVX_Detail!L182+PVX_Detail!L191+PVX_Detail!L200+PVX_Detail!L209+PVX_Detail!L218+PVX_Detail!L227+PVX_Detail!L236+PVX_Detail!L245+PVX_Detail!L254+PVX_Detail!L263+PVX_Detail!L272+PVX_Detail!L281+PVX_Detail!L290+PVX_Detail!L299+PVX_Detail!L308+PVX_Detail!L317+PVX_Detail!L326 -> 285821.16 | D12: =PVX_Detail!L14+PVX_Detail!L23+PVX_Detail!L32+PVX_Detail!L41+PVX_Detail!L50+PVX_Detail!L59+PVX_Detail!L68+PVX_Detail!L77+PVX_Detail!L86+PVX_Detail!L95+PVX_Detail!L104+PVX_Detail!L113+PVX_Detail!L122+PVX_Detail!L131+PVX_Detail!L140+PVX_Detail!L149+PVX_Detail!L158+PVX_Detail!L167+PVX_Detail!L176+PVX_Detail!L185+PVX_Detail!L194+PVX_Detail!L203+PVX_Detail!L212+PVX_Detail!L221+PVX_Detail!L230+PVX_Detail!L239+PVX_Detail!L248+PVX_Detail!L257+PVX_Detail!L266+PVX_Detail!L275+PVX_Detail!L284+PVX_Detail!L293+PVX_Detail!L302+PVX_Detail!L311+PVX_Detail!L320+PVX_Detail!L329 -> 39122.984
A13: 2026-10-29 | B13: =Acquisition_Plan!E13 -> 300000 | C13: =PVX_Detail!M11+PVX_Detail!M20+PVX_Detail!M29+PVX_Detail!M38+PVX_Detail!M47+PVX_Detail!M56+PVX_Detail!M65+PVX_Detail!M74+PVX_Detail!M83+PVX_Detail!M92+PVX_Detail!M101+PVX_Detail!M110+PVX_Detail!M119+PVX_Detail!M128+PVX_Detail!M137+PVX_Detail!M146+PVX_Detail!M155+PVX_Detail!M164+PVX_Detail!M173+PVX_Detail!M182+PVX_Detail!M191+PVX_Detail!M200+PVX_Detail!M209+PVX_Detail!M218+PVX_Detail!M227+PVX_Detail!M236+PVX_Detail!M245+PVX_Detail!M254+PVX_Detail!M263+PVX_Detail!M272+PVX_Detail!M281+PVX_Detail!M290+PVX_Detail!M299+PVX_Detail!M308+PVX_Detail!M317+PVX_Detail!M326 -> 302742.84 | D13: =PVX_Detail!M14+PVX_Detail!M23+PVX_Detail!M32+PVX_Detail!M41+PVX_Detail!M50+PVX_Detail!M59+PVX_Detail!M68+PVX_Detail!M77+PVX_Detail!M86+PVX_Detail!M95+PVX_Detail!M104+PVX_Detail!M113+PVX_Detail!M122+PVX_Detail!M131+PVX_Detail!M140+PVX_Detail!M149+PVX_Detail!M158+PVX_Detail!M167+PVX_Detail!M176+PVX_Detail!M185+PVX_Detail!M194+PVX_Detail!M203+PVX_Detail!M212+PVX_Detail!M221+PVX_Detail!M230+PVX_Detail!M239+PVX_Detail!M248+PVX_Detail!M257+PVX_Detail!M266+PVX_Detail!M275+PVX_Detail!M284+PVX_Detail!M293+PVX_Detail!M302+PVX_Detail!M311+PVX_Detail!M320+PVX_Detail!M329 -> 51327.087
A14: 2026-11-28 | B14: =Acquisition_Plan!E14 -> 350000 | C14: =PVX_Detail!N11+PVX_Detail!N20+PVX_Detail!N29+PVX_Detail!N38+PVX_Detail!N47+PVX_Detail!N56+PVX_Detail!N65+PVX_Detail!N74+PVX_Detail!N83+PVX_Detail!N92+PVX_Detail!N101+PVX_Detail!N110+PVX_Detail!N119+PVX_Detail!N128+PVX_Detail!N137+PVX_Detail!N146+PVX_Detail!N155+PVX_Detail!N164+PVX_Detail!N173+PVX_Detail!N182+PVX_Detail!N191+PVX_Detail!N200+PVX_Detail!N209+PVX_Detail!N218+PVX_Detail!N227+PVX_Detail!N236+PVX_Detail!N245+PVX_Detail!N254+PVX_Detail!N263+PVX_Detail!N272+PVX_Detail!N281+PVX_Detail!N290+PVX_Detail!N299+PVX_Detail!N308+PVX_Detail!N317+PVX_Detail!N326 -> 338321.16 | D14: =PVX_Detail!N14+PVX_Detail!N23+PVX_Detail!N32+PVX_Detail!N41+PVX_Detail!N50+PVX_Detail!N59+PVX_Detail!N68+PVX_Detail!N77+PVX_Detail!N86+PVX_Detail!N95+PVX_Detail!N104+PVX_Detail!N113+PVX_Detail!N122+PVX_Detail!N131+PVX_Detail!N140+PVX_Detail!N149+PVX_Detail!N158+PVX_Detail!N167+PVX_Detail!N176+PVX_Detail!N185+PVX_Detail!N194+PVX_Detail!N203+PVX_Detail!N212+PVX_Detail!N221+PVX_Detail!N230+PVX_Detail!N239+PVX_Detail!N248+PVX_Detail!N257+PVX_Detail!N266+PVX_Detail!N275+PVX_Detail!N284+PVX_Detail!N293+PVX_Detail!N302+PVX_Detail!N311+PVX_Detail!N320+PVX_Detail!N329 -> 63899.438
A15: 2026-12-28 | B15: =Acquisition_Plan!E15 -> 350000 | C15: =PVX_Detail!O11+PVX_Detail!O20+PVX_Detail!O29+PVX_Detail!O38+PVX_Detail!O47+PVX_Detail!O56+PVX_Detail!O65+PVX_Detail!O74+PVX_Detail!O83+PVX_Detail!O92+PVX_Detail!O101+PVX_Detail!O110+PVX_Detail!O119+PVX_Detail!O128+PVX_Detail!O137+PVX_Detail!O146+PVX_Detail!O155+PVX_Detail!O164+PVX_Detail!O173+PVX_Detail!O182+PVX_Detail!O191+PVX_Detail!O200+PVX_Detail!O209+PVX_Detail!O218+PVX_Detail!O227+PVX_Detail!O236+PVX_Detail!O245+PVX_Detail!O254+PVX_Detail!O263+PVX_Detail!O272+PVX_Detail!O281+PVX_Detail!O290+PVX_Detail!O299+PVX_Detail!O308+PVX_Detail!O317+PVX_Detail!O326 -> 355242.84 | D15: =PVX_Detail!O14+PVX_Detail!O23+PVX_Detail!O32+PVX_Detail!O41+PVX_Detail!O50+PVX_Detail!O59+PVX_Detail!O68+PVX_Detail!O77+PVX_Detail!O86+PVX_Detail!O95+PVX_Detail!O104+PVX_Detail!O113+PVX_Detail!O122+PVX_Detail!O131+PVX_Detail!O140+PVX_Detail!O149+PVX_Detail!O158+PVX_Detail!O167+PVX_Detail!O176+PVX_Detail!O185+PVX_Detail!O194+PVX_Detail!O203+PVX_Detail!O212+PVX_Detail!O221+PVX_Detail!O230+PVX_Detail!O239+PVX_Detail!O248+PVX_Detail!O257+PVX_Detail!O266+PVX_Detail!O275+PVX_Detail!O284+PVX_Detail!O293+PVX_Detail!O302+PVX_Detail!O311+PVX_Detail!O320+PVX_Detail!O329 -> 78764.216
A16: 2027-01-27 | B16: =Acquisition_Plan!E16 -> 400000 | C16: =PVX_Detail!P11+PVX_Detail!P20+PVX_Detail!P29+PVX_Detail!P38+PVX_Detail!P47+PVX_Detail!P56+PVX_Detail!P65+PVX_Detail!P74+PVX_Detail!P83+PVX_Detail!P92+PVX_Detail!P101+PVX_Detail!P110+PVX_Detail!P119+PVX_Detail!P128+PVX_Detail!P137+PVX_Detail!P146+PVX_Detail!P155+PVX_Detail!P164+PVX_Detail!P173+PVX_Detail!P182+PVX_Detail!P191+PVX_Detail!P200+PVX_Detail!P209+PVX_Detail!P218+PVX_Detail!P227+PVX_Detail!P236+PVX_Detail!P245+PVX_Detail!P254+PVX_Detail!P263+PVX_Detail!P272+PVX_Detail!P281+PVX_Detail!P290+PVX_Detail!P299+PVX_Detail!P308+PVX_Detail!P317+PVX_Detail!P326 -> 390821.16 | D16: =PVX_Detail!P14+PVX_Detail!P23+PVX_Detail!P32+PVX_Detail!P41+PVX_Detail!P50+PVX_Detail!P59+PVX_Detail!P68+PVX_Detail!P77+PVX_Detail!P86+PVX_Detail!P95+PVX_Detail!P104+PVX_Detail!P113+PVX_Detail!P122+PVX_Detail!P131+PVX_Detail!P140+PVX_Detail!P149+PVX_Detail!P158+PVX_Detail!P167+PVX_Detail!P176+PVX_Detail!P185+PVX_Detail!P194+PVX_Detail!P203+PVX_Detail!P212+PVX_Detail!P221+PVX_Detail!P230+PVX_Detail!P239+PVX_Detail!P248+PVX_Detail!P257+PVX_Detail!P266+PVX_Detail!P275+PVX_Detail!P284+PVX_Detail!P293+PVX_Detail!P302+PVX_Detail!P311+PVX_Detail!P320+PVX_Detail!P329 -> 92250.725
A17: 2027-02-26 | B17: =Acquisition_Plan!E17 -> 400000 | C17: =PVX_Detail!Q11+PVX_Detail!Q20+PVX_Detail!Q29+PVX_Detail!Q38+PVX_Detail!Q47+PVX_Detail!Q56+PVX_Detail!Q65+PVX_Detail!Q74+PVX_Detail!Q83+PVX_Detail!Q92+PVX_Detail!Q101+PVX_Detail!Q110+PVX_Detail!Q119+PVX_Detail!Q128+PVX_Detail!Q137+PVX_Detail!Q146+PVX_Detail!Q155+PVX_Detail!Q164+PVX_Detail!Q173+PVX_Detail!Q182+PVX_Detail!Q191+PVX_Detail!Q200+PVX_Detail!Q209+PVX_Detail!Q218+PVX_Detail!Q227+PVX_Detail!Q236+PVX_Detail!Q245+PVX_Detail!Q254+PVX_Detail!Q263+PVX_Detail!Q272+PVX_Detail!Q281+PVX_Detail!Q290+PVX_Detail!Q299+PVX_Detail!Q308+PVX_Detail!Q317+PVX_Detail!Q326 -> 407742.84 | D17: =PVX_Detail!Q14+PVX_Detail!Q23+PVX_Detail!Q32+PVX_Detail!Q41+PVX_Detail!Q50+PVX_Detail!Q59+PVX_Detail!Q68+PVX_Detail!Q77+PVX_Detail!Q86+PVX_Detail!Q95+PVX_Detail!Q104+PVX_Detail!Q113+PVX_Detail!Q122+PVX_Detail!Q131+PVX_Detail!Q140+PVX_Detail!Q149+PVX_Detail!Q158+PVX_Detail!Q167+PVX_Detail!Q176+PVX_Detail!Q185+PVX_Detail!Q194+PVX_Detail!Q203+PVX_Detail!Q212+PVX_Detail!Q221+PVX_Detail!Q230+PVX_Detail!Q239+PVX_Detail!Q248+PVX_Detail!Q257+PVX_Detail!Q266+PVX_Detail!Q275+PVX_Detail!Q284+PVX_Detail!Q293+PVX_Detail!Q302+PVX_Detail!Q311+PVX_Detail!Q320+PVX_Detail!Q329 -> 107339.22
A18: 2027-03-28 | B18: =Acquisition_Plan!E18 -> 400000 | C18: =PVX_Detail!R11+PVX_Detail!R20+PVX_Detail!R29+PVX_Detail!R38+PVX_Detail!R47+PVX_Detail!R56+PVX_Detail!R65+PVX_Detail!R74+PVX_Detail!R83+PVX_Detail!R92+PVX_Detail!R101+PVX_Detail!R110+PVX_Detail!R119+PVX_Detail!R128+PVX_Detail!R137+PVX_Detail!R146+PVX_Detail!R155+PVX_Detail!R164+PVX_Detail!R173+PVX_Detail!R182+PVX_Detail!R191+PVX_Detail!R200+PVX_Detail!R209+PVX_Detail!R218+PVX_Detail!R227+PVX_Detail!R236+PVX_Detail!R245+PVX_Detail!R254+PVX_Detail!R263+PVX_Detail!R272+PVX_Detail!R281+PVX_Detail!R290+PVX_Detail!R299+PVX_Detail!R308+PVX_Detail!R317+PVX_Detail!R326 -> 416071.77 | D18: =PVX_Detail!R14+PVX_Detail!R23+PVX_Detail!R32+PVX_Detail!R41+PVX_Detail!R50+PVX_Detail!R59+PVX_Detail!R68+PVX_Detail!R77+PVX_Detail!R86+PVX_Detail!R95+PVX_Detail!R104+PVX_Detail!R113+PVX_Detail!R122+PVX_Detail!R131+PVX_Detail!R140+PVX_Detail!R149+PVX_Detail!R158+PVX_Detail!R167+PVX_Detail!R176+PVX_Detail!R185+PVX_Detail!R194+PVX_Detail!R203+PVX_Detail!R212+PVX_Detail!R221+PVX_Detail!R230+PVX_Detail!R239+PVX_Detail!R248+PVX_Detail!R257+PVX_Detail!R266+PVX_Detail!R275+PVX_Detail!R284+PVX_Detail!R293+PVX_Detail!R302+PVX_Detail!R311+PVX_Detail!R320+PVX_Detail!R329 -> 122550.73
A19: 2027-04-27 | B19: =Acquisition_Plan!E19 -> 400000 | C19: =PVX_Detail!S11+PVX_Detail!S20+PVX_Detail!S29+PVX_Detail!S38+PVX_Detail!S47+PVX_Detail!S56+PVX_Detail!S65+PVX_Detail!S74+PVX_Detail!S83+PVX_Detail!S92+PVX_Detail!S101+PVX_Detail!S110+PVX_Detail!S119+PVX_Detail!S128+PVX_Detail!S137+PVX_Detail!S146+PVX_Detail!S155+PVX_Detail!S164+PVX_Detail!S173+PVX_Detail!S182+PVX_Detail!S191+PVX_Detail!S200+PVX_Detail!S209+PVX_Detail!S218+PVX_Detail!S227+PVX_Detail!S236+PVX_Detail!S245+PVX_Detail!S254+PVX_Detail!S263+PVX_Detail!S272+PVX_Detail!S281+PVX_Detail!S290+PVX_Detail!S299+PVX_Detail!S308+PVX_Detail!S317+PVX_Detail!S326 -> 420000 | D19: =PVX_Detail!S14+PVX_Detail!S23+PVX_Detail!S32+PVX_Detail!S41+PVX_Detail!S50+PVX_Detail!S59+PVX_Detail!S68+PVX_Detail!S77+PVX_Detail!S86+PVX_Detail!S95+PVX_Detail!S104+PVX_Detail!S113+PVX_Detail!S122+PVX_Detail!S131+PVX_Detail!S140+PVX_Detail!S149+PVX_Detail!S158+PVX_Detail!S167+PVX_Detail!S176+PVX_Detail!S185+PVX_Detail!S194+PVX_Detail!S203+PVX_Detail!S212+PVX_Detail!S221+PVX_Detail!S230+PVX_Detail!S239+PVX_Detail!S248+PVX_Detail!S257+PVX_Detail!S266+PVX_Detail!S275+PVX_Detail!S284+PVX_Detail!S293+PVX_Detail!S302+PVX_Detail!S311+PVX_Detail!S320+PVX_Detail!S329 -> 135482.97
A20: 2027-05-27 | B20: =Acquisition_Plan!E20 -> 400000 | C20: =PVX_Detail!T11+PVX_Detail!T20+PVX_Detail!T29+PVX_Detail!T38+PVX_Detail!T47+PVX_Detail!T56+PVX_Detail!T65+PVX_Detail!T74+PVX_Detail!T83+PVX_Detail!T92+PVX_Detail!T101+PVX_Detail!T110+PVX_Detail!T119+PVX_Detail!T128+PVX_Detail!T137+PVX_Detail!T146+PVX_Detail!T155+PVX_Detail!T164+PVX_Detail!T173+PVX_Detail!T182+PVX_Detail!T191+PVX_Detail!T200+PVX_Detail!T209+PVX_Detail!T218+PVX_Detail!T227+PVX_Detail!T236+PVX_Detail!T245+PVX_Detail!T254+PVX_Detail!T263+PVX_Detail!T272+PVX_Detail!T281+PVX_Detail!T290+PVX_Detail!T299+PVX_Detail!T308+PVX_Detail!T317+PVX_Detail!T326 -> 420000 | D20: =PVX_Detail!T14+PVX_Detail!T23+PVX_Detail!T32+PVX_Detail!T41+PVX_Detail!T50+PVX_Detail!T59+PVX_Detail!T68+PVX_Detail!T77+PVX_Detail!T86+PVX_Detail!T95+PVX_Detail!T104+PVX_Detail!T113+PVX_Detail!T122+PVX_Detail!T131+PVX_Detail!T140+PVX_Detail!T149+PVX_Detail!T158+PVX_Detail!T167+PVX_Detail!T176+PVX_Detail!T185+PVX_Detail!T194+PVX_Detail!T203+PVX_Detail!T212+PVX_Detail!T221+PVX_Detail!T230+PVX_Detail!T239+PVX_Detail!T248+PVX_Detail!T257+PVX_Detail!T266+PVX_Detail!T275+PVX_Detail!T284+PVX_Detail!T293+PVX_Detail!T302+PVX_Detail!T311+PVX_Detail!T320+PVX_Detail!T329 -> 148538.23
A21: 2027-06-26 | B21: =Acquisition_Plan!E21 -> 400000 | C21: =PVX_Detail!U11+PVX_Detail!U20+PVX_Detail!U29+PVX_Detail!U38+PVX_Detail!U47+PVX_Detail!U56+PVX_Detail!U65+PVX_Detail!U74+PVX_Detail!U83+PVX_Detail!U92+PVX_Detail!U101+PVX_Detail!U110+PVX_Detail!U119+PVX_Detail!U128+PVX_Detail!U137+PVX_Detail!U146+PVX_Detail!U155+PVX_Detail!U164+PVX_Detail!U173+PVX_Detail!U182+PVX_Detail!U191+PVX_Detail!U200+PVX_Detail!U209+PVX_Detail!U218+PVX_Detail!U227+PVX_Detail!U236+PVX_Detail!U245+PVX_Detail!U254+PVX_Detail!U263+PVX_Detail!U272+PVX_Detail!U281+PVX_Detail!U290+PVX_Detail!U299+PVX_Detail!U308+PVX_Detail!U317+PVX_Detail!U326 -> 420000 | D21: =PVX_Detail!U14+PVX_Detail!U23+PVX_Detail!U32+PVX_Detail!U41+PVX_Detail!U50+PVX_Detail!U59+PVX_Detail!U68+PVX_Detail!U77+PVX_Detail!U86+PVX_Detail!U95+PVX_Detail!U104+PVX_Detail!U113+PVX_Detail!U122+PVX_Detail!U131+PVX_Detail!U140+PVX_Detail!U149+PVX_Detail!U158+PVX_Detail!U167+PVX_Detail!U176+PVX_Detail!U185+PVX_Detail!U194+PVX_Detail!U203+PVX_Detail!U212+PVX_Detail!U221+PVX_Detail!U230+PVX_Detail!U239+PVX_Detail!U248+PVX_Detail!U257+PVX_Detail!U266+PVX_Detail!U275+PVX_Detail!U284+PVX_Detail!U293+PVX_Detail!U302+PVX_Detail!U311+PVX_Detail!U320+PVX_Detail!U329 -> 159970.04
A22: 2027-07-26 | B22: =Acquisition_Plan!E22 -> 400000 | C22: =PVX_Detail!V11+PVX_Detail!V20+PVX_Detail!V29+PVX_Detail!V38+PVX_Detail!V47+PVX_Detail!V56+PVX_Detail!V65+PVX_Detail!V74+PVX_Detail!V83+PVX_Detail!V92+PVX_Detail!V101+PVX_Detail!V110+PVX_Detail!V119+PVX_Detail!V128+PVX_Detail!V137+PVX_Detail!V146+PVX_Detail!V155+PVX_Detail!V164+PVX_Detail!V173+PVX_Detail!V182+PVX_Detail!V191+PVX_Detail!V200+PVX_Detail!V209+PVX_Detail!V218+PVX_Detail!V227+PVX_Detail!V236+PVX_Detail!V245+PVX_Detail!V254+PVX_Detail!V263+PVX_Detail!V272+PVX_Detail!V281+PVX_Detail!V290+PVX_Detail!V299+PVX_Detail!V308+PVX_Detail!V317+PVX_Detail!V326 -> 420000 | D22: =PVX_Detail!V14+PVX_Detail!V23+PVX_Detail!V32+PVX_Detail!V41+PVX_Detail!V50+PVX_Detail!V59+PVX_Detail!V68+PVX_Detail!V77+PVX_Detail!V86+PVX_Detail!V95+PVX_Detail!V104+PVX_Detail!V113+PVX_Detail!V122+PVX_Detail!V131+PVX_Detail!V140+PVX_Detail!V149+PVX_Detail!V158+PVX_Detail!V167+PVX_Detail!V176+PVX_Detail!V185+PVX_Detail!V194+PVX_Detail!V203+PVX_Detail!V212+PVX_Detail!V221+PVX_Detail!V230+PVX_Detail!V239+PVX_Detail!V248+PVX_Detail!V257+PVX_Detail!V266+PVX_Detail!V275+PVX_Detail!V284+PVX_Detail!V293+PVX_Detail!V302+PVX_Detail!V311+PVX_Detail!V320+PVX_Detail!V329 -> 169972.66
A23: 2027-08-25 | B23: =Acquisition_Plan!E23 -> 400000 | C23: =PVX_Detail!W11+PVX_Detail!W20+PVX_Detail!W29+PVX_Detail!W38+PVX_Detail!W47+PVX_Detail!W56+PVX_Detail!W65+PVX_Detail!W74+PVX_Detail!W83+PVX_Detail!W92+PVX_Detail!W101+PVX_Detail!W110+PVX_Detail!W119+PVX_Detail!W128+PVX_Detail!W137+PVX_Detail!W146+PVX_Detail!W155+PVX_Detail!W164+PVX_Detail!W173+PVX_Detail!W182+PVX_Detail!W191+PVX_Detail!W200+PVX_Detail!W209+PVX_Detail!W218+PVX_Detail!W227+PVX_Detail!W236+PVX_Detail!W245+PVX_Detail!W254+PVX_Detail!W263+PVX_Detail!W272+PVX_Detail!W281+PVX_Detail!W290+PVX_Detail!W299+PVX_Detail!W308+PVX_Detail!W317+PVX_Detail!W326 -> 420000 | D23: =PVX_Detail!W14+PVX_Detail!W23+PVX_Detail!W32+PVX_Detail!W41+PVX_Detail!W50+PVX_Detail!W59+PVX_Detail!W68+PVX_Detail!W77+PVX_Detail!W86+PVX_Detail!W95+PVX_Detail!W104+PVX_Detail!W113+PVX_Detail!W122+PVX_Detail!W131+PVX_Detail!W140+PVX_Detail!W149+PVX_Detail!W158+PVX_Detail!W167+PVX_Detail!W176+PVX_Detail!W185+PVX_Detail!W194+PVX_Detail!W203+PVX_Detail!W212+PVX_Detail!W221+PVX_Detail!W230+PVX_Detail!W239+PVX_Detail!W248+PVX_Detail!W257+PVX_Detail!W266+PVX_Detail!W275+PVX_Detail!W284+PVX_Detail!W293+PVX_Detail!W302+PVX_Detail!W311+PVX_Detail!W320+PVX_Detail!W329 -> 178712.69
A24: 2027-09-24 | B24: =Acquisition_Plan!E24 -> 400000 | C24: =PVX_Detail!X11+PVX_Detail!X20+PVX_Detail!X29+PVX_Detail!X38+PVX_Detail!X47+PVX_Detail!X56+PVX_Detail!X65+PVX_Detail!X74+PVX_Detail!X83+PVX_Detail!X92+PVX_Detail!X101+PVX_Detail!X110+PVX_Detail!X119+PVX_Detail!X128+PVX_Detail!X137+PVX_Detail!X146+PVX_Detail!X155+PVX_Detail!X164+PVX_Detail!X173+PVX_Detail!X182+PVX_Detail!X191+PVX_Detail!X200+PVX_Detail!X209+PVX_Detail!X218+PVX_Detail!X227+PVX_Detail!X236+PVX_Detail!X245+PVX_Detail!X254+PVX_Detail!X263+PVX_Detail!X272+PVX_Detail!X281+PVX_Detail!X290+PVX_Detail!X299+PVX_Detail!X308+PVX_Detail!X317+PVX_Detail!X326 -> 420000 | D24: =PVX_Detail!X14+PVX_Detail!X23+PVX_Detail!X32+PVX_Detail!X41+PVX_Detail!X50+PVX_Detail!X59+PVX_Detail!X68+PVX_Detail!X77+PVX_Detail!X86+PVX_Detail!X95+PVX_Detail!X104+PVX_Detail!X113+PVX_Detail!X122+PVX_Detail!X131+PVX_Detail!X140+PVX_Detail!X149+PVX_Detail!X158+PVX_Detail!X167+PVX_Detail!X176+PVX_Detail!X185+PVX_Detail!X194+PVX_Detail!X203+PVX_Detail!X212+PVX_Detail!X221+PVX_Detail!X230+PVX_Detail!X239+PVX_Detail!X248+PVX_Detail!X257+PVX_Detail!X266+PVX_Detail!X275+PVX_Detail!X284+PVX_Detail!X293+PVX_Detail!X302+PVX_Detail!X311+PVX_Detail!X320+PVX_Detail!X329 -> 186449.36
A25: 2027-10-24 | B25: =Acquisition_Plan!E25 -> 400000 | C25: =PVX_Detail!Y11+PVX_Detail!Y20+PVX_Detail!Y29+PVX_Detail!Y38+PVX_Detail!Y47+PVX_Detail!Y56+PVX_Detail!Y65+PVX_Detail!Y74+PVX_Detail!Y83+PVX_Detail!Y92+PVX_Detail!Y101+PVX_Detail!Y110+PVX_Detail!Y119+PVX_Detail!Y128+PVX_Detail!Y137+PVX_Detail!Y146+PVX_Detail!Y155+PVX_Detail!Y164+PVX_Detail!Y173+PVX_Detail!Y182+PVX_Detail!Y191+PVX_Detail!Y200+PVX_Detail!Y209+PVX_Detail!Y218+PVX_Detail!Y227+PVX_Detail!Y236+PVX_Detail!Y245+PVX_Detail!Y254+PVX_Detail!Y263+PVX_Detail!Y272+PVX_Detail!Y281+PVX_Detail!Y290+PVX_Detail!Y299+PVX_Detail!Y308+PVX_Detail!Y317+PVX_Detail!Y326 -> 420000 | D25: =PVX_Detail!Y14+PVX_Detail!Y23+PVX_Detail!Y32+PVX_Detail!Y41+PVX_Detail!Y50+PVX_Detail!Y59+PVX_Detail!Y68+PVX_Detail!Y77+PVX_Detail!Y86+PVX_Detail!Y95+PVX_Detail!Y104+PVX_Detail!Y113+PVX_Detail!Y122+PVX_Detail!Y131+PVX_Detail!Y140+PVX_Detail!Y149+PVX_Detail!Y158+PVX_Detail!Y167+PVX_Detail!Y176+PVX_Detail!Y185+PVX_Detail!Y194+PVX_Detail!Y203+PVX_Detail!Y212+PVX_Detail!Y221+PVX_Detail!Y230+PVX_Detail!Y239+PVX_Detail!Y248+PVX_Detail!Y257+PVX_Detail!Y266+PVX_Detail!Y275+PVX_Detail!Y284+PVX_Detail!Y293+PVX_Detail!Y302+PVX_Detail!Y311+PVX_Detail!Y320+PVX_Detail!Y329 -> 193237.5
A26: 2027-11-23 | B26: =Acquisition_Plan!E26 -> 400000 | C26: =PVX_Detail!Z11+PVX_Detail!Z20+PVX_Detail!Z29+PVX_Detail!Z38+PVX_Detail!Z47+PVX_Detail!Z56+PVX_Detail!Z65+PVX_Detail!Z74+PVX_Detail!Z83+PVX_Detail!Z92+PVX_Detail!Z101+PVX_Detail!Z110+PVX_Detail!Z119+PVX_Detail!Z128+PVX_Detail!Z137+PVX_Detail!Z146+PVX_Detail!Z155+PVX_Detail!Z164+PVX_Detail!Z173+PVX_Detail!Z182+PVX_Detail!Z191+PVX_Detail!Z200+PVX_Detail!Z209+PVX_Detail!Z218+PVX_Detail!Z227+PVX_Detail!Z236+PVX_Detail!Z245+PVX_Detail!Z254+PVX_Detail!Z263+PVX_Detail!Z272+PVX_Detail!Z281+PVX_Detail!Z290+PVX_Detail!Z299+PVX_Detail!Z308+PVX_Detail!Z317+PVX_Detail!Z326 -> 420000 | D26: =PVX_Detail!Z14+PVX_Detail!Z23+PVX_Detail!Z32+PVX_Detail!Z41+PVX_Detail!Z50+PVX_Detail!Z59+PVX_Detail!Z68+PVX_Detail!Z77+PVX_Detail!Z86+PVX_Detail!Z95+PVX_Detail!Z104+PVX_Detail!Z113+PVX_Detail!Z122+PVX_Detail!Z131+PVX_Detail!Z140+PVX_Detail!Z149+PVX_Detail!Z158+PVX_Detail!Z167+PVX_Detail!Z176+PVX_Detail!Z185+PVX_Detail!Z194+PVX_Detail!Z203+PVX_Detail!Z212+PVX_Detail!Z221+PVX_Detail!Z230+PVX_Detail!Z239+PVX_Detail!Z248+PVX_Detail!Z257+PVX_Detail!Z266+PVX_Detail!Z275+PVX_Detail!Z284+PVX_Detail!Z293+PVX_Detail!Z302+PVX_Detail!Z311+PVX_Detail!Z320+PVX_Detail!Z329 -> 199275
A27: 2027-12-23 | B27: =Acquisition_Plan!E27 -> 400000 | C27: =PVX_Detail!AA11+PVX_Detail!AA20+PVX_Detail!AA29+PVX_Detail!AA38+PVX_Detail!AA47+PVX_Detail!AA56+PVX_Detail!AA65+PVX_Detail!AA74+PVX_Detail!AA83+PVX_Detail!AA92+PVX_Detail!AA101+PVX_Detail!AA110+PVX_Detail!AA119+PVX_Detail!AA128+PVX_Detail!AA137+PVX_Detail!AA146+PVX_Detail!AA155+PVX_Detail!AA164+PVX_Detail!AA173+PVX_Detail!AA182+PVX_Detail!AA191+PVX_Detail!AA200+PVX_Detail!AA209+PVX_Detail!AA218+PVX_Detail!AA227+PVX_Detail!AA236+PVX_Detail!AA245+PVX_Detail!AA254+PVX_Detail!AA263+PVX_Detail!AA272+PVX_Detail!AA281+PVX_Detail!AA290+PVX_Detail!AA299+PVX_Detail!AA308+PVX_Detail!AA317+PVX_Detail!AA326 -> 420000 | D27: =PVX_Detail!AA14+PVX_Detail!AA23+PVX_Detail!AA32+PVX_Detail!AA41+PVX_Detail!AA50+PVX_Detail!AA59+PVX_Detail!AA68+PVX_Detail!AA77+PVX_Detail!AA86+PVX_Detail!AA95+PVX_Detail!AA104+PVX_Detail!AA113+PVX_Detail!AA122+PVX_Detail!AA131+PVX_Detail!AA140+PVX_Detail!AA149+PVX_Detail!AA158+PVX_Detail!AA167+PVX_Detail!AA176+PVX_Detail!AA185+PVX_Detail!AA194+PVX_Detail!AA203+PVX_Detail!AA212+PVX_Detail!AA221+PVX_Detail!AA230+PVX_Detail!AA239+PVX_Detail!AA248+PVX_Detail!AA257+PVX_Detail!AA266+PVX_Detail!AA275+PVX_Detail!AA284+PVX_Detail!AA293+PVX_Detail!AA302+PVX_Detail!AA311+PVX_Detail!AA320+PVX_Detail!AA329 -> 204018.75
A28: 2028-01-22 | B28: =Acquisition_Plan!E28 -> 400000 | C28: =PVX_Detail!AB11+PVX_Detail!AB20+PVX_Detail!AB29+PVX_Detail!AB38+PVX_Detail!AB47+PVX_Detail!AB56+PVX_Detail!AB65+PVX_Detail!AB74+PVX_Detail!AB83+PVX_Detail!AB92+PVX_Detail!AB101+PVX_Detail!AB110+PVX_Detail!AB119+PVX_Detail!AB128+PVX_Detail!AB137+PVX_Detail!AB146+PVX_Detail!AB155+PVX_Detail!AB164+PVX_Detail!AB173+PVX_Detail!AB182+PVX_Detail!AB191+PVX_Detail!AB200+PVX_Detail!AB209+PVX_Detail!AB218+PVX_Detail!AB227+PVX_Detail!AB236+PVX_Detail!AB245+PVX_Detail!AB254+PVX_Detail!AB263+PVX_Detail!AB272+PVX_Detail!AB281+PVX_Detail!AB290+PVX_Detail!AB299+PVX_Detail!AB308+PVX_Detail!AB317+PVX_Detail!AB326 -> 420000 | D28: =PVX_Detail!AB14+PVX_Detail!AB23+PVX_Detail!AB32+PVX_Detail!AB41+PVX_Detail!AB50+PVX_Detail!AB59+PVX_Detail!AB68+PVX_Detail!AB77+PVX_Detail!AB86+PVX_Detail!AB95+PVX_Detail!AB104+PVX_Detail!AB113+PVX_Detail!AB122+PVX_Detail!AB131+PVX_Detail!AB140+PVX_Detail!AB149+PVX_Detail!AB158+PVX_Detail!AB167+PVX_Detail!AB176+PVX_Detail!AB185+PVX_Detail!AB194+PVX_Detail!AB203+PVX_Detail!AB212+PVX_Detail!AB221+PVX_Detail!AB230+PVX_Detail!AB239+PVX_Detail!AB248+PVX_Detail!AB257+PVX_Detail!AB266+PVX_Detail!AB275+PVX_Detail!AB284+PVX_Detail!AB293+PVX_Detail!AB302+PVX_Detail!AB311+PVX_Detail!AB320+PVX_Detail!AB329 -> 208762.5
